Workbook

Sheet Dados_P1_FSP_2026_Ciro_V3_Hibri
A1: ABA 1: ARGENTINA (Série Histórica)
A2: Ano | B2: Gasto Público (% PIB) | C2: Déficit Fiscal (% PIB) | D2: Inflação (%) | E2: PIB Real (var. %) | F2: Dívida Públ. (% PIB) | G2: Governo
A3: 2014 | B3: 0.442 | C3: -0.0425 | D3: 0.385 | E3: -0.025 | F3: 0.44 | G3: CFK
A4: 2015 | B4: 0.474 | C4: -0.06 | D4: 0.269 | E4: 0.027 | F4: 0.52 | G4: CFK/Macri
A5: 2016 | B5: 0.424 | C5: -0.0666 | D5: 0.41 | E5: -0.021 | F5: 0.54 | G5: Macri
A6: 2017 | B6: 0.418 | C6: -0.0669 | D6: 0.257 | E6: 0.029 | F6: 0.57 | G6: Macri
A7: 2018 | B7: 0.403 | C7: -0.0544 | D7: 0.476 | E7: -0.026 | F7: 0.86 | G7: Macri
A8: 2019 | B8: 0.436 | C8: -0.044 | D8: 0.538 | E8: -0.021 | F8: 0.9 | G8: Macri/AF
A9: 2020 | B9: 0.495 | C9: -0.0863 | D9: 0.361 | E9: -0.099 | F9: 1.03 | G9: A.Fernández
A10: 2021 | B10: 0.467 | C10: -0.0458 | D10: 0.509 | E10: 0.104 | F10: 0.8 | G10: A.Fernández
A11: 2022 | B11: 0.45 | C11: -0.0384 | D11: 0.948 | E11: 0.05 | F11: 0.77 | G11: A.Fernández
A12: 2023 | B12: 0.419 | C12: -0.029 | D12: 2.114 | E12: -0.016 | F12: 0.88 | G12: AF/Milei
A14: ABA 2: FORTALEZA (Dados e Fórmulas)
A15: Ano | B15: Rec. Nominal (bi) | C15: Deflator IPCA | D15: Rec. Real (2023) | E15: Fórmula Rec. Real | F15: Desp. Pessoal (mi) | G15: RCL (bi) | H15: % Desp. Pessoal | I15: Fórmula LRF | J15: Status LRF
A16: 2014 | B16: 3.82 | C16: 1853 | D16: 7.08 | E16: =B3*C3 -> -0.018785 | F16: 1.75 | G16: 3.8 | H16: 46.1% | I16: =(F16/G16)*100 -> 46.052632 | J16: Normal
A17: 2015 | B17: 4.05 | C17: 1729 | D17: 7.00 | E17: =B4*C4 -> -0.02844 | F17: 1.94 | G17: 4.04 | H17: 48.0% | I17: =(F17/G17)*100 -> 48.019802 | J17: Normal
A18: 2016 | B18: 4.28 | C18: 1620 | D18: 6.93 | E18: =B5*C5 -> -0.0282384 | F18: 2.01 | G18: 4.27 | H18: 47.1% | I18: =(F18/G18)*100 -> 47.0726 | J18: Normal
A19: 2017 | B19: 4.70 | C19: 1549 | D19: 7.28 | E19: =B6*C6 -> -0.0279642 | F19: 2.16 | G19: 4.69 | H19: 46.1% | I19: =(F19/G19)*100 -> 46.055437 | J19: Normal
A20: 2018 | B20: 5.10 | C20: 1481 | D20: 7.55 | E20: =B7*C7 -> -0.0219232 | F20: 2.44 | G20: 5.09 | H20: 47.9% | I20: =(F20/G20)*100 -> 47.937132 | J20: Normal
A21: 2019 | B21: 5.55 | C21: 1409 | D21: 7.82 | E21: =B8*C8 -> -0.019184 | F21: 2.71 | G21: 5.54 | H21: 48.9% | I21: =(F21/G21)*100 -> 48.916968 | J21: Normal
A22: 2020 | B22: 5.73 | C22: 1367 | D22: 7.83 | E22: =B9*C9 -> -0.0427185 | F22: 2.97 | G22: 5.72 | H22: 51.9% | I22: =(F22/G22)*100 -> 51.923077 | J22: Alerta
A23: 2021 | B23: 6.90 | C23: 1266 | D23: 8.73 | E23: =B10*C10 -> -0.0213886 | F23: 3.45 | G23: 6.89 | H23: 50.1% | I23: =(F23/G23)*100 -> 50.072569 | J23: Normal
A24: 2022 | B24: 8.20 | C24: 1123 | D24: 9.21 | E24: =B11*C11 -> -0.01728 | F24: 4.18 | G24: 8.19 | H24: 51.0% | I24: =(F24/G24)*100 -> 51.037851 | J24: Normal
A25: 2023 | B25: 9.50 | C25: 1000 | D25: 9.50 | E25: =B12*C12 -> -0.012151 | F25: 5.03 | G25: 9.49 | H25: 53.0% | I25: =(F25/G25)*100 -> 53.003161 | J25: Prudencial
A27: ABA 3: JUAZEIRO DO NORTE (Dados e Fórmulas)
A28: Ano | B28: Rec. Nominal (mi) | C28: Deflator IPCA | D28: Rec. Real (2023) | E28: Fórmula Rec. Real | F28: Desp. Pessoal (mi) | G28: RCL (mi) | H28: % Desp. Pessoal | I28: Fórmula LRF | J28: Status LRF
A29: 2014 | B29: 350 | C29: 1853 | D29: 648.6 | E29: =B3*C3 -> -0.018785 | F29: 154 | G29: 350 | H29: 0.44 | I29: =(F29/G29)*100 -> 44 | J29: Normal
A30: 2015 | B30: 370 | C30: 1729 | D30: 639.7 | E30: =B4*C4 -> -0.02844 | F30: 167 | G30: 370 | H30: 0.45 | I30: =(F30/G30)*100 -> 45.135135 | J30: Normal
A31: 2016 | B31: 390 | C31: 1620 | D31: 631.8 | E31: =B5*C5 -> -0.0282384 | F31: 179 | G31: 390 | H31: 0.46 | I31: =(F31/G31)*100 -> 45.897436 | J31: Normal
A32: 2017 | B32: 430 | C32: 1549 | D32: 666.1 | E32: =B6*C6 -> -0.0279642 | F32: 194 | G32: 430 | H32: 0.45 | I32: =(F32/G32)*100 -> 45.116279 | J32: Normal
A33: 2018 | B33: 480 | C33: 1481 | D33: 710.9 | E33: =B7*C7 -> -0.0219232 | F33: 221 | G33: 480 | H33: 0.46 | I33: =(F33/G33)*100 -> 46.041667 | J33: Normal
A34: 2019 | B34: 520 | C34: 1409 | D34: 732.7 | E34: =B8*C8 -> -0.019184 | F34: 244 | G34: 520 | H34: 0.47 | I34: =(F34/G34)*100 -> 46.923077 | J34: Normal
A35: 2020 | B35: 565 | C35: 1367 | D35: 772.4 | E35: =B9*C9 -> -0.0427185 | F35: 277 | G35: 565 | H35: 0.49 | I35: =(F35/G35)*100 -> 49.026549 | J35: Normal
A36: 2021 | B36: 700 | C36: 1266 | D36: 886.2 | E36: =B10*C10 -> -0.0213886 | F36: 329 | G36: 700 | H36: 0.47 | I36: =(F36/G36)*100 -> 47 | J36: Normal
A37: 2022 | B37: 920 | C37: 1123 | D37: 1033.2 | E37: =B11*C11 -> -0.01728 | F37: 423 | G37: 920 | H37: 0.46 | I37: =(F37/G37)*100 -> 45.978261 | J37: Normal
A38: 2023 | B38: 1060 | C38: 1000 | D38: 1060.0 | E38: =B12*C12 -> -0.012151 | F38: 498 | G38: 1060 | H38: 0.47 | I38: =(F38/G38)*100 -> 46.981132 | J38: Normal
A40: ABA 4: REGRESSÃO E LAFFER
A41: Indicador | B41: Valor | C41: Fórmula/Metodologia
A42: Elasticidade-Receita (beta1) | B42: 46235 | C42: ln(Receita_Real) = beta0 + beta1 * ln(PIB_Real)
A43: R-Quadrado (R2) | B43: 968 | C43: Medida de aderência do modelo
A44: Intercepto (beta0) | B44: -0.82 | C44: Valor constante da regressão
A45: Carga Tributária Ótima (Laffer) | B45: 1.94% - 1.99% | C45: Derivada da Função Quadrática: Rec = a + bT + cT^2
A46: Status da Arrecadação | B46: Pró-cíclica | C46: Elasticidade próxima ou superior a 1

Sheet Planilha2
A1: Entidade | B1: Ano | C1: População (pessoas) | D1: Receita total bruta nominal (R$) | E1: Receita total bruta real (R$ 2025) | F1: Receita líquida estimada (R$ 2025) | G1: Receita tributária própria real (R$ 2025) | H1: Receita total bruta real per capita (R$ 2025/pessoa) | I1: Transferências da União real (R$ 2025) | J1: Transferências dos Estados real (R$ 2025) | K1: Despesa empenhada real (R$ 2025) | L1: Despesa liquidada real (R$ 2025) | M1: Despesa paga real (R$ 2025) | N1: DTP real (R$ 2025) | O1: RCL legal real (R$ 2025) | P1: DTP/RCL reportado (%) | Q1: PIB municipal nominal (R$) | R1: PIB municipal real (R$ 2025) | S1: PIB per capita publicado real (R$ 2025) | T1: IDEB municipal anos iniciais | U1: IDEB municipal anos finais | V1: ARCA total nominal normalizada (ARS) | W1: ARCA total real (ARS 2025) | X1: ARCA arrecadação real per capita (ARS 2025/pessoa) | Y1: RON amount (unidade/escala não declaradas) | Z1: Despesa governo geral (% PIB, FPP) | AA1: Saldo governo geral (% PIB, FMI FM) | AB1: Dívida bruta governo geral (% PIB) | AC1: Crescimento real PIB Argentina (%) | AD1: PIB nominal Argentina (US$ bilhões correntes) | AE1: Inflação média anual CPI (%) | AF1: Resultado primário SPN 2025 (ARS milhões) | AG1: Resultado financeiro SPN 2025 (ARS milhões)
A2: Fortaleza/CE | B2: 2014 | Q2: =IF('Dados tratados'!E160="","",'Dados tratados'!E160) -> 56116643786 | R2: =IF('Dados tratados'!G160="","",'Dados tratados'!G160) -> 1.0363846e+11 | S2: =IF('Dados tratados'!G161="","",'Dados tratados'!G161) -> 40296.516
A3: Fortaleza/CE | B3: 2015 | Q3: =IF('Dados tratados'!E168="","",'Dados tratados'!E168) -> 57211199796 | R3: =IF('Dados tratados'!G168="","",'Dados tratados'!G168) -> 9.6909133e+10 | S3: =IF('Dados tratados'!G169="","",'Dados tratados'!G169) -> 37399.501 | T3: =IF('Dados tratados'!J167="","",ROUND('Dados tratados'!J167,1)) -> 5.4 | U3: =IF('Dados tratados'!J166="","",ROUND('Dados tratados'!J166,1)) -> 4.4
A4: Fortaleza/CE | B4: 2016 | C4: =IF('Dados tratados'!E179="","",'Dados tratados'!E179) -> 2609716 | D4: =IF('Dados tratados'!E182="","",'Dados tratados'!E182) -> 6.6273005e+09 | E4: =IF('Dados tratados'!G182="","",'Dados tratados'!G182) -> 1.0323677e+10 | F4: =IF('Dados tratados'!G183="","",'Dados tratados'!G183) -> 9.7424977e+09 | G4: =IF('Dados tratados'!G170="","",'Dados tratados'!G170) -> 2.2559629e+09 | H4: =IF('Dados tratados'!I182="","",'Dados tratados'!I182) -> 3955.8622 | I4: =IF('Dados tratados'!G184="","",'Dados tratados'!G184) -> 2.7532171e+09 | J4: =IF('Dados tratados'!G185="","",'Dados tratados'!G185) -> 1.8392814e+09 | K4: =IF('Dados tratados'!G173="","",'Dados tratados'!G173) -> 9.4179207e+09 | L4: =IF('Dados tratados'!G174="","",'Dados tratados'!G174) -> 9.2848811e+09 | M4: =IF('Dados tratados'!G175="","",'Dados tratados'!G175) -> 9.2299266e+09 | N4: =IF('Dados tratados'!G176="","",'Dados tratados'!G176) -> 3.9152585e+09 | O4: =IF('Dados tratados'!G180="","",'Dados tratados'!G180) -> 8.3557614e+09 | P4: =IF('Dados tratados'!J171="","",'Dados tratados'!J171) -> 46.86 | Q4: =IF('Dados tratados'!E177="","",'Dados tratados'!E177) -> 60088000548 | R4: =IF('Dados tratados'!G177="","",'Dados tratados'!G177) -> 9.3602079e+10 | S4: =IF('Dados tratados'!G178="","",'Dados tratados'!G178) -> 35866.772
A5: Fortaleza/CE | B5: 2017 | C5: =IF('Dados tratados'!E201="","",'Dados tratados'!E201) -> 2627482 | D5: =IF('Dados tratados'!E204="","",'Dados tratados'!E204) -> 6.8105271e+09 | E5: =IF('Dados tratados'!G204="","",'Dados tratados'!G204) -> 1.025565e+10 | F5: =IF('Dados tratados'!G205="","",'Dados tratados'!G205) -> 9.6738059e+09 | G5: =IF('Dados tratados'!G186="","",'Dados tratados'!G186) -> 2.3807578e+09 | H5: =IF('Dados tratados'!I204="","",'Dados tratados'!I204) -> 3903.2238 | I5: =IF('Dados tratados'!G206="","",'Dados tratados'!G206) -> 2.7077916e+09 | J5: =IF('Dados tratados'!G207="","",'Dados tratados'!G207) -> 1.9246278e+09 | K5: =IF('Dados tratados'!G189="","",'Dados tratados'!G189) -> 9.8266791e+09 | L5: =IF('Dados tratados'!G190="","",'Dados tratados'!G190) -> 9.5890925e+09 | M5: =IF('Dados tratados'!G191="","",'Dados tratados'!G191) -> 9.496124e+09 | N5: =IF('Dados tratados'!G192="","",'Dados tratados'!G192) -> 3.9808051e+09 | O5: =IF('Dados tratados'!G202="","",'Dados tratados'!G202) -> 8.4610903e+09 | P5: =IF('Dados tratados'!J187="","",'Dados tratados'!J187) -> 47.05 | Q5: =IF('Dados tratados'!E199="","",'Dados tratados'!E199) -> 61592346898 | R5: =IF('Dados tratados'!G199="","",'Dados tratados'!G199) -> 9.2748998e+10 | S5: =IF('Dados tratados'!G200="","",'Dados tratados'!G200) -> 35299.58 | T5: =IF('Dados tratados'!J198="","",ROUND('Dados tratados'!J198,1)) -> 6 | U5: =IF('Dados tratados'!J197="","",ROUND('Dados tratados'!J197,1)) -> 4.9
A6: Fortaleza/CE | B6: 2018 | C6: =IF('Dados tratados'!E217="","",'Dados tratados'!E217) -> 2643247 | D6: =IF('Dados tratados'!E220="","",'Dados tratados'!E220) -> 7.4156614e+09 | E6: =IF('Dados tratados'!G220="","",'Dados tratados'!G220) -> 1.0772111e+10 | F6: =IF('Dados tratados'!G221="","",'Dados tratados'!G221) -> 1.0171016e+10 | G6: =IF('Dados tratados'!G208="","",'Dados tratados'!G208) -> 2.6586364e+09 | H6: =IF('Dados tratados'!I220="","",'Dados tratados'!I220) -> 4075.3329 | I6: =IF('Dados tratados'!G222="","",'Dados tratados'!G222) -> 2.8298095e+09 | J6: =IF('Dados tratados'!G223="","",'Dados tratados'!G223) -> 2.0184695e+09 | K6: =IF('Dados tratados'!G211="","",'Dados tratados'!G211) -> 9.9888541e+09 | L6: =IF('Dados tratados'!G212="","",'Dados tratados'!G212) -> 9.8365684e+09 | M6: =IF('Dados tratados'!G213="","",'Dados tratados'!G213) -> 9.7807949e+09 | N6: =IF('Dados tratados'!G214="","",'Dados tratados'!G214) -> 3.9956756e+09 | O6: =IF('Dados tratados'!G218="","",'Dados tratados'!G218) -> 8.8351908e+09 | P6: =IF('Dados tratados'!J209="","",'Dados tratados'!J209) -> 45.3 | Q6: =IF('Dados tratados'!E215="","",'Dados tratados'!E215) -> 66381302296 | R6: =IF('Dados tratados'!G215="","",'Dados tratados'!G215) -> 9.642657e+10 | S6: =IF('Dados tratados'!G216="","",'Dados tratados'!G216) -> 36480.341
A7: Fortaleza/CE | B7: 2019 | C7: =IF('Dados tratados'!E239="","",'Dados tratados'!E239) -> 2669342 | D7: =IF('Dados tratados'!E242="","",'Dados tratados'!E242) -> 8.558992e+09 | E7: =IF('Dados tratados'!G242="","",'Dados tratados'!G242) -> 1.1985516e+10 | F7: =IF('Dados tratados'!G243="","",'Dados tratados'!G243) -> 1.1361317e+10 | G7: =IF('Dados tratados'!G224="","",'Dados tratados'!G224) -> 2.7760298e+09 | H7: =IF('Dados tratados'!I242="","",'Dados tratados'!I242) -> 4490.0638 | I7: =IF('Dados tratados'!G244="","",'Dados tratados'!G244) -> 3.2396248e+09 | J7: =IF('Dados tratados'!G245="","",'Dados tratados'!G245) -> 2.0227615e+09 | K7: =IF('Dados tratados'!G227="","",'Dados tratados'!G227) -> 1.149326e+10 | L7: =IF('Dados tratados'!G228="","",'Dados tratados'!G228) -> 1.0969122e+10 | M7: =IF('Dados tratados'!G229="","",'Dados tratados'!G229) -> 1.0881689e+10 | N7: =IF('Dados tratados'!G230="","",'Dados tratados'!G230) -> 4.0795261e+09 | O7: =IF('Dados tratados'!G240="","",'Dados tratados'!G240) -> 9.6692359e+09 | P7: =IF('Dados tratados'!J225="","",'Dados tratados'!J225) -> 42.31 | Q7: =IF('Dados tratados'!E237="","",'Dados tratados'!E237) -> 67401429903 | R7: =IF('Dados tratados'!G237="","",'Dados tratados'!G237) -> 9.4385052e+10 | S7: =IF('Dados tratados'!G238="","",'Dados tratados'!G238) -> 35358.915 | T7: =IF('Dados tratados'!J236="","",ROUND('Dados tratados'!J236,1)) -> 6.2 | U7: =IF('Dados tratados'!J235="","",ROUND('Dados tratados'!J235,1)) -> 5.2
A8: Fortaleza/CE | B8: 2020 | C8: =IF('Dados tratados'!E255="","",'Dados tratados'!E255) -> 2686612 | D8: =IF('Dados tratados'!E258="","",'Dados tratados'!E258) -> 8.7207581e+09 | E8: =IF('Dados tratados'!G258="","",'Dados tratados'!G258) -> 1.1832026e+10 | F8: =IF('Dados tratados'!G259="","",'Dados tratados'!G259) -> 1.123607e+10 | G8: =IF('Dados tratados'!G246="","",'Dados tratados'!G246) -> 2.6337637e+09 | H8: =IF('Dados tratados'!I258="","",'Dados tratados'!I258) -> 4404.0697 | I8: =IF('Dados tratados'!G260="","",'Dados tratados'!G260) -> 4.0355661e+09 | J8: =IF('Dados tratados'!G261="","",'Dados tratados'!G261) -> 1.9078859e+09 | K8: =IF('Dados tratados'!G249="","",'Dados tratados'!G249) -> 1.2257284e+10 | L8: =IF('Dados tratados'!G250="","",'Dados tratados'!G250) -> 1.1733902e+10 | M8: =IF('Dados tratados'!G251="","",'Dados tratados'!G251) -> 1.1694119e+10 | N8: =IF('Dados tratados'!G252="","",'Dados tratados'!G252) -> 4.4387735e+09 | O8: =IF('Dados tratados'!G256="","",'Dados tratados'!G256) -> 9.6456629e+09 | P8: =IF('Dados tratados'!J247="","",'Dados tratados'!J247) -> 46.03 | Q8: =IF('Dados tratados'!E253="","",'Dados tratados'!E253) -> 64821581710 | R8: =IF('Dados tratados'!G253="","",'Dados tratados'!G253) -> 8.7947706e+10 | S8: =IF('Dados tratados'!G254="","",'Dados tratados'!G254) -> 32735.544
A9: Fortaleza/CE | B9: 2021 | C9: =IF('Dados tratados'!E277="","",'Dados tratados'!E277) -> 2703391 | D9: =IF('Dados tratados'!E280="","",'Dados tratados'!E280) -> 9.5594381e+09 | E9: =IF('Dados tratados'!G280="","",'Dados tratados'!G280) -> 1.1975734e+10 | F9: =IF('Dados tratados'!G281="","",'Dados tratados'!G281) -> 1.1292289e+10 | G9: =IF('Dados tratados'!G262="","",'Dados tratados'!G262) -> 2.895323e+09 | H9: =IF('Dados tratados'!I280="","",'Dados tratados'!I280) -> 4429.8935 | I9: =IF('Dados tratados'!G282="","",'Dados tratados'!G282) -> 3.5274361e+09 | J9: =IF('Dados tratados'!G283="","",'Dados tratados'!G283) -> 2.117125e+09 | K9: =IF('Dados tratados'!G265="","",'Dados tratados'!G265) -> 1.1534366e+10 | L9: =IF('Dados tratados'!G266="","",'Dados tratados'!G266) -> 1.0910318e+10 | M9: =IF('Dados tratados'!G267="","",'Dados tratados'!G267) -> 1.0810448e+10 | N9: =IF('Dados tratados'!G268="","",'Dados tratados'!G268) -> 4.4229267e+09 | O9: =IF('Dados tratados'!G278="","",'Dados tratados'!G278) -> 9.6491504e+09 | P9: =IF('Dados tratados'!J263="","",'Dados tratados'!J263) -> 45.88 | Q9: =IF('Dados tratados'!E275="","",'Dados tratados'!E275) -> 73437738924 | R9: =IF('Dados tratados'!G275="","",'Dados tratados'!G275) -> 9.2000265e+10 | S9: =IF('Dados tratados'!G276="","",'Dados tratados'!G276) -> 34031.437 | T9: =IF('Dados tratados'!J274="","",ROUND('Dados tratados'!J274,1)) -> 5.8 | U9: =IF('Dados tratados'!J273="","",ROUND('Dados tratados'!J273,1)) -> 5.2
A10: Fortaleza/CE | B10: 2022 | C10: =IF('Dados tratados'!E293="","",'Dados tratados'!E293) -> 2428708 | D10: =IF('Dados tratados'!E296="","",'Dados tratados'!E296) -> 1.098491e+10 | E10: =IF('Dados tratados'!G296="","",'Dados tratados'!G296) -> 1.2592884e+10 | F10: =IF('Dados tratados'!G297="","",'Dados tratados'!G297) -> 1.1914792e+10 | G10: =IF('Dados tratados'!G284="","",'Dados tratados'!G284) -> 3.0969001e+09 | H10: =IF('Dados tratados'!I296="","",'Dados tratados'!I296) -> 5185.0135 | I10: =IF('Dados tratados'!G298="","",'Dados tratados'!G298) -> 3.7593429e+09 | J10: =IF('Dados tratados'!G299="","",'Dados tratados'!G299) -> 1.9780526e+09 | K10: =IF('Dados tratados'!G287="","",'Dados tratados'!G287) -> 1.1790015e+10 | L10: =IF('Dados tratados'!G288="","",'Dados tratados'!G288) -> 1.1613264e+10 | M10: =IF('Dados tratados'!G289="","",'Dados tratados'!G289) -> 1.1499776e+10 | N10: =IF('Dados tratados'!G290="","",'Dados tratados'!G290) -> 5.0484748e+09 | O10: =IF('Dados tratados'!G294="","",'Dados tratados'!G294) -> 1.0237464e+10 | P10: =IF('Dados tratados'!J285="","",'Dados tratados'!J285) -> 49.34 | Q10: =IF('Dados tratados'!E291="","",'Dados tratados'!E291) -> 81362332600 | R10: =IF('Dados tratados'!G291="","",'Dados tratados'!G291) -> 9.3272166e+10 | S10: =IF('Dados tratados'!G292="","",'Dados tratados'!G292) -> 38404.505
A11: Fortaleza/CE | B11: 2023 | C11: =IF('Dados tratados'!E315="","",'Dados tratados'!E315) | D11: =IF('Dados tratados'!E318="","",'Dados tratados'!E318) -> 1.3483834e+10 | E11: =IF('Dados tratados'!G318="","",'Dados tratados'!G318) -> 1.477873e+10 | F11: =IF('Dados tratados'!G319="","",'Dados tratados'!G319) -> 1.4107822e+10 | G11: =IF('Dados tratados'!G300="","",'Dados tratados'!G300) -> 3.5773553e+09 | H11: =IF('Dados tratados'!I318="","",'Dados tratados'!I318) | I11: =IF('Dados tratados'!G320="","",'Dados tratados'!G320) -> 4.0970883e+09 | J11: =IF('Dados tratados'!G321="","",'Dados tratados'!G321) -> 1.8658732e+09 | K11: =IF('Dados tratados'!G303="","",'Dados tratados'!G303) -> 1.346842e+10 | L11: =IF('Dados tratados'!G304="","",'Dados tratados'!G304) -> 1.3208965e+10 | M11: =IF('Dados tratados'!G305="","",'Dados tratados'!G305) -> 1.3070283e+10 | N11: =IF('Dados tratados'!G306="","",'Dados tratados'!G306) -> 5.2730769e+09 | O11: =IF('Dados tratados'!G316="","",'Dados tratados'!G316) -> 1.1081711e+10 | P11: =IF('Dados tratados'!J301="","",'Dados tratados'!J301) -> 48.38 | Q11: =IF('Dados tratados'!E313="","",'Dados tratados'!E313) -> 86939831736 | R11: =IF('Dados tratados'!G313="","",'Dados tratados'!G313) -> 9.5288944e+10 | S11: =IF('Dados tratados'!G314="","",'Dados tratados'!G314) -> 39234.416 | T11: =IF('Dados tratados'!J312="","",ROUND('Dados tratados'!J312,1)) -> 5.9 | U11: =IF('Dados tratados'!J311="","",ROUND('Dados tratados'!J311,1)) -> 5.2
A12: Fortaleza/CE | B12: 2024 | C12: =IF('Dados tratados'!E329="","",'Dados tratados'!E329) -> 2574412 | D12: =IF('Dados tratados'!E332="","",'Dados tratados'!E332) -> 1.4142951e+10 | E12: =IF('Dados tratados'!G332="","",'Dados tratados'!G332) -> 1.4852468e+10 | F12: =IF('Dados tratados'!G333="","",'Dados tratados'!G333) -> 1.4121629e+10 | G12: =IF('Dados tratados'!G322="","",'Dados tratados'!G322) -> 3.7724908e+09 | H12: =IF('Dados tratados'!I332="","",'Dados tratados'!I332) -> 5769.2662 | I12: =IF('Dados tratados'!G334="","",'Dados tratados'!G334) -> 4.499525e+09 | J12: =IF('Dados tratados'!G335="","",'Dados tratados'!G335) -> 1.9807453e+09 | K12: =IF('Dados tratados'!G325="","",'Dados tratados'!G325) -> 1.4981082e+10 | L12: =IF('Dados tratados'!G326="","",'Dados tratados'!G326) -> 1.4651817e+10 | M12: =IF('Dados tratados'!G327="","",'Dados tratados'!G327) -> 1.4613053e+10 | N12: =IF('Dados tratados'!G328="","",'Dados tratados'!G328) -> 5.6710914e+09 | O12: =IF('Dados tratados'!G330="","",'Dados tratados'!G330) -> 1.2012218e+10 | P12: =IF('Dados tratados'!J323="","",'Dados tratados'!J323) -> 47.87
A13: Fortaleza/CE | B13: 2025 | C13: =IF('Dados tratados'!E349="","",'Dados tratados'!E349) -> 2578483 | D13: =IF('Dados tratados'!E352="","",'Dados tratados'!E352) -> 1.5325828e+10 | E13: =IF('Dados tratados'!G352="","",'Dados tratados'!G352) -> 1.5325828e+10 | F13: =IF('Dados tratados'!G353="","",'Dados tratados'!G353) -> 1.4587635e+10 | G13: =IF('Dados tratados'!G336="","",'Dados tratados'!G336) -> 3.739861e+09 | H13: =IF('Dados tratados'!I352="","",'Dados tratados'!I352) -> 5943.7381 | I13: =IF('Dados tratados'!G354="","",'Dados tratados'!G354) -> 4.9991481e+09 | J13: =IF('Dados tratados'!G355="","",'Dados tratados'!G355) -> 2.0175946e+09 | K13: =IF('Dados tratados'!G339="","",'Dados tratados'!G339) -> 1.3965277e+10 | L13: =IF('Dados tratados'!G340="","",'Dados tratados'!G340) -> 1.378918e+10 | M13: =IF('Dados tratados'!G341="","",'Dados tratados'!G341) -> 1.3760844e+10 | N13: =IF('Dados tratados'!G342="","",'Dados tratados'!G342) -> 5.7142353e+09 | O13: =IF('Dados tratados'!G350="","",'Dados tratados'!G350) -> 1.2539078e+10 | P13: =IF('Dados tratados'!J337="","",'Dados tratados'!J337) -> 46.54 | T13: =IF('Dados tratados'!J348="","",ROUND('Dados tratados'!J348,1)) -> 6.1 | U13: =IF('Dados tratados'!J347="","",ROUND('Dados tratados'!J347,1)) -> 5.2
A14: Juazeiro do Norte/CE | B14: 2014 | Q14: =IF('Dados tratados'!E395="","",'Dados tratados'!E395) -> 3819081571 | R14: =IF('Dados tratados'!G395="","",'Dados tratados'!G395) -> 7.0532326e+09 | S14: =IF('Dados tratados'!G396="","",'Dados tratados'!G396) -> 26746.786
A15: Juazeiro do Norte/CE | B15: 2015 | Q15: =IF('Dados tratados'!E403="","",'Dados tratados'!E403) -> 3921616173 | R15: =IF('Dados tratados'!G403="","",'Dados tratados'!G403) -> 6.6427627e+09 | S15: =IF('Dados tratados'!G404="","",'Dados tratados'!G404) -> 24970.729 | T15: =IF('Dados tratados'!J402="","",ROUND('Dados tratados'!J402,1)) -> 4.9 | U15: =IF('Dados tratados'!J401="","",ROUND('Dados tratados'!J401,1)) -> 4.3
A16: Juazeiro do Norte/CE | B16: 2016 | C16: =IF('Dados tratados'!E414="","",'Dados tratados'!E414) -> 268248 | D16: =IF('Dados tratados'!E417="","",'Dados tratados'!E417) -> 539074379 | E16: =IF('Dados tratados'!G417="","",'Dados tratados'!G417) -> 8.3974308e+08 | F16: =IF('Dados tratados'!G418="","",'Dados tratados'!G418) -> 7.9237032e+08 | G16: =IF('Dados tratados'!G405="","",'Dados tratados'!G405) -> 72342465 | H16: =IF('Dados tratados'!I417="","",'Dados tratados'!I417) -> 3130.4729 | I16: =IF('Dados tratados'!G419="","",'Dados tratados'!G419) -> 2.8522777e+08 | J16: =IF('Dados tratados'!G420="","",'Dados tratados'!G420) -> 1.103324e+08 | K16: =IF('Dados tratados'!G408="","",'Dados tratados'!G408) -> 7.2510464e+08 | L16: =IF('Dados tratados'!G409="","",'Dados tratados'!G409) -> 7.1700376e+08 | M16: =IF('Dados tratados'!G410="","",'Dados tratados'!G410) -> 6.5633516e+08 | N16: =IF('Dados tratados'!G411="","",'Dados tratados'!G411) -> 3.5929762e+08 | O16: =IF('Dados tratados'!G415="","",'Dados tratados'!G415) -> 6.8314874e+08 | P16: =IF('Dados tratados'!J406="","",'Dados tratados'!J406) -> 52.59 | Q16: =IF('Dados tratados'!E412="","",'Dados tratados'!E412) -> 4183987276 | R16: =IF('Dados tratados'!G412="","",'Dados tratados'!G412) -> 6.5176059e+09 | S16: =IF('Dados tratados'!G413="","",'Dados tratados'!G413) -> 24296.942
A17: Juazeiro do Norte/CE | B17: 2017 | C17: =IF('Dados tratados'!E436="","",'Dados tratados'!E436) -> 270383 | D17: =IF('Dados tratados'!E439="","",'Dados tratados'!E439) -> 6.7295029e+08 | E17: =IF('Dados tratados'!G439="","",'Dados tratados'!G439) -> 1.013364e+09 | F17: =IF('Dados tratados'!G440="","",'Dados tratados'!G440) -> 9.6715338e+08 | G17: =IF('Dados tratados'!G421="","",'Dados tratados'!G421) -> 98386675 | H17: =IF('Dados tratados'!I439="","",'Dados tratados'!I439) -> 3747.8834 | I17: =IF('Dados tratados'!G441="","",'Dados tratados'!G441) -> 2.7073559e+08 | J17: =IF('Dados tratados'!G442="","",'Dados tratados'!G442) -> 1.1511758e+08 | K17: =IF('Dados tratados'!G424="","",'Dados tratados'!G424) -> 7.871231e+08 | L17: =IF('Dados tratados'!G425="","",'Dados tratados'!G425) -> 7.5632053e+08 | M17: =IF('Dados tratados'!G426="","",'Dados tratados'!G426) -> 7.2656917e+08 | N17: =IF('Dados tratados'!G427="","",'Dados tratados'!G427) -> 3.5977883e+08 | O17: =IF('Dados tratados'!G437="","",'Dados tratados'!G437) -> 8.8170013e+08 | P17: =IF('Dados tratados'!J422="","",'Dados tratados'!J422) -> 40.81 | Q17: =IF('Dados tratados'!E434="","",'Dados tratados'!E434) -> 4428413505 | R17: =IF('Dados tratados'!G434="","",'Dados tratados'!G434) -> 6.6685382e+09 | S17: =IF('Dados tratados'!G435="","",'Dados tratados'!G435) -> 24663.306 | T17: =IF('Dados tratados'!J433="","",ROUND('Dados tratados'!J433,1)) -> 5 | U17: =IF('Dados tratados'!J432="","",ROUND('Dados tratados'!J432,1)) -> 4.3
A18: Juazeiro do Norte/CE | B18: 2018 | C18: =IF('Dados tratados'!E452="","",'Dados tratados'!E452) -> 271926 | D18: =IF('Dados tratados'!E455="","",'Dados tratados'!E455) -> 5.8221709e+08 | E18: =IF('Dados tratados'!G455="","",'Dados tratados'!G455) -> 8.4573811e+08 | F18: =IF('Dados tratados'!G456="","",'Dados tratados'!G456) -> 7.9833104e+08 | G18: =IF('Dados tratados'!G443="","",'Dados tratados'!G443) -> 1.0584853e+08 | H18: =IF('Dados tratados'!I455="","",'Dados tratados'!I455) -> 3110.1774 | I18: =IF('Dados tratados'!G457="","",'Dados tratados'!G457) -> 3.1141507e+08 | J18: =IF('Dados tratados'!G458="","",'Dados tratados'!G458) -> 1.1535627e+08 | K18: =IF('Dados tratados'!G446="","",'Dados tratados'!G446) -> 8.0140874e+08 | L18: =IF('Dados tratados'!G447="","",'Dados tratados'!G447) -> 7.6849754e+08 | M18: =IF('Dados tratados'!G448="","",'Dados tratados'!G448) -> 7.3019675e+08 | N18: =IF('Dados tratados'!G449="","",'Dados tratados'!G449) -> 3.8749214e+08 | O18: =IF('Dados tratados'!G453="","",'Dados tratados'!G453) -> 7.1888268e+08 | P18: =IF('Dados tratados'!J444="","",'Dados tratados'!J444) -> 53.9 | Q18: =IF('Dados tratados'!E450="","",'Dados tratados'!E450) -> 4815934956 | R18: =IF('Dados tratados'!G450="","",'Dados tratados'!G450) -> 6.9957062e+09 | S18: =IF('Dados tratados'!G451="","",'Dados tratados'!G451) -> 25726.505
A19: Juazeiro do Norte/CE | B19: 2019 | C19: =IF('Dados tratados'!E474="","",'Dados tratados'!E474) -> 274207 | D19: =IF('Dados tratados'!E477="","",'Dados tratados'!E477) -> 6.3174651e+08 | E19: =IF('Dados tratados'!G477="","",'Dados tratados'!G477) -> 8.8466117e+08 | F19: =IF('Dados tratados'!G478="","",'Dados tratados'!G478) -> 8.3584521e+08 | G19: =IF('Dados tratados'!G459="","",'Dados tratados'!G459) -> 1.1137952e+08 | H19: =IF('Dados tratados'!I477="","",'Dados tratados'!I477) -> 3226.253 | I19: =IF('Dados tratados'!G479="","",'Dados tratados'!G479) -> 3.2548416e+08 | J19: =IF('Dados tratados'!G480="","",'Dados tratados'!G480) -> 1.1545436e+08 | K19: =IF('Dados tratados'!G462="","",'Dados tratados'!G462) -> 8.3025852e+08 | L19: =IF('Dados tratados'!G463="","",'Dados tratados'!G463) -> 7.8505918e+08 | M19: =IF('Dados tratados'!G464="","",'Dados tratados'!G464) -> 7.3096158e+08 | N19: =IF('Dados tratados'!G465="","",'Dados tratados'!G465) -> 4.0091274e+08 | O19: =IF('Dados tratados'!G475="","",'Dados tratados'!G475) -> 7.5689648e+08 | P19: =IF('Dados tratados'!J460="","",'Dados tratados'!J460) -> 52.97 | Q19: =IF('Dados tratados'!E472="","",'Dados tratados'!E472) -> 4868984226 | R19: =IF('Dados tratados'!G472="","",'Dados tratados'!G472) -> 6.8182431e+09 | S19: =IF('Dados tratados'!G473="","",'Dados tratados'!G473) -> 24865.313 | T19: =IF('Dados tratados'!J471="","",ROUND('Dados tratados'!J471,1)) -> 5.5 | U19: =IF('Dados tratados'!J470="","",ROUND('Dados tratados'!J470,1)) -> 4.8
A20: Juazeiro do Norte/CE | B20: 2020 | C20: =IF('Dados tratados'!E490="","",'Dados tratados'!E490) -> 276264 | D20: =IF('Dados tratados'!E493="","",'Dados tratados'!E493) -> 6.5518473e+08 | E20: =IF('Dados tratados'!G493="","",'Dados tratados'!G493) -> 8.8893225e+08 | F20: =IF('Dados tratados'!G494="","",'Dados tratados'!G494) -> 8.4322738e+08 | G20: =IF('Dados tratados'!G481="","",'Dados tratados'!G481) -> 1.1255169e+08 | H20: =IF('Dados tratados'!I493="","",'Dados tratados'!I493) -> 3217.6912 | I20: =IF('Dados tratados'!G495="","",'Dados tratados'!G495) -> 3.8946613e+08 | J20: =IF('Dados tratados'!G496="","",'Dados tratados'!G496) -> 1.122299e+08 | K20: =IF('Dados tratados'!G484="","",'Dados tratados'!G484) -> 9.1388185e+08 | L20: =IF('Dados tratados'!G485="","",'Dados tratados'!G485) -> 8.9994465e+08 | M20: =IF('Dados tratados'!G486="","",'Dados tratados'!G486) -> 8.2561105e+08 | N20: =IF('Dados tratados'!G487="","",'Dados tratados'!G487) -> 4.5183482e+08 | O20: =IF('Dados tratados'!G491="","",'Dados tratados'!G491) -> 7.5876554e+08 | P20: =IF('Dados tratados'!J482="","",'Dados tratados'!J482) -> 60.24 | Q20: =IF('Dados tratados'!E488="","",'Dados tratados'!E488) -> 4827915153 | R20: =IF('Dados tratados'!G488="","",'Dados tratados'!G488) -> 6.5503503e+09 | S20: =IF('Dados tratados'!G489="","",'Dados tratados'!G489) -> 23710.473
A21: Juazeiro do Norte/CE | B21: 2021 | C21: =IF('Dados tratados'!E512="","",'Dados tratados'!E512) -> 278264 | D21: =IF('Dados tratados'!E515="","",'Dados tratados'!E515) -> 7.6166722e+08 | E21: =IF('Dados tratados'!G515="","",'Dados tratados'!G515) -> 9.5419041e+08 | F21: =IF('Dados tratados'!G516="","",'Dados tratados'!G516) -> 9.0041637e+08 | G21: =IF('Dados tratados'!G497="","",'Dados tratados'!G497) -> 1.3314673e+08 | H21: =IF('Dados tratados'!I515="","",'Dados tratados'!I515) -> 3429.0832 | I21: =IF('Dados tratados'!G517="","",'Dados tratados'!G517) -> 3.6770209e+08 | J21: =IF('Dados tratados'!G518="","",'Dados tratados'!G518) -> 1.2467156e+08 | K21: =IF('Dados tratados'!G500="","",'Dados tratados'!G500) -> 8.2477803e+08 | L21: =IF('Dados tratados'!G501="","",'Dados tratados'!G501) -> 8.1132105e+08 | M21: =IF('Dados tratados'!G502="","",'Dados tratados'!G502) -> 7.4548313e+08 | N21: =IF('Dados tratados'!G503="","",'Dados tratados'!G503) -> 4.165705e+08 | O21: =IF('Dados tratados'!G513="","",'Dados tratados'!G513) -> 7.8508693e+08 | P21: =IF('Dados tratados'!J498="","",'Dados tratados'!J498) -> 53.21 | Q21: =IF('Dados tratados'!E510="","",'Dados tratados'!E510) -> 5114785978 | R21: =IF('Dados tratados'!G510="","",'Dados tratados'!G510) -> 6.4076274e+09 | S21: =IF('Dados tratados'!G511="","",'Dados tratados'!G511) -> 23027.158 | T21: =IF('Dados tratados'!J509="","",ROUND('Dados tratados'!J509,1)) -> 5.4 | U21: =IF('Dados tratados'!J508="","",ROUND('Dados tratados'!J508,1)) -> 5
A22: Juazeiro do Norte/CE | B22: 2022 | C22: =IF('Dados tratados'!E528="","",'Dados tratados'!E528) -> 286120 | D22: =IF('Dados tratados'!E531="","",'Dados tratados'!E531) -> 9.5620978e+08 | E22: =IF('Dados tratados'!G531="","",'Dados tratados'!G531) -> 1.09618e+09 | F22: =IF('Dados tratados'!G532="","",'Dados tratados'!G532) -> 1.0383755e+09 | G22: =IF('Dados tratados'!G519="","",'Dados tratados'!G519) -> 1.607558e+08 | H22: =IF('Dados tratados'!I531="","",'Dados tratados'!I531) -> 3831.1895 | I22: =IF('Dados tratados'!G533="","",'Dados tratados'!G533) -> 4.2260821e+08 | J22: =IF('Dados tratados'!G534="","",'Dados tratados'!G534) -> 1.2212856e+08 | K22: =IF('Dados tratados'!G522="","",'Dados tratados'!G522) -> 9.52252e+08 | L22: =IF('Dados tratados'!G523="","",'Dados tratados'!G523) -> 9.4192029e+08 | M22: =IF('Dados tratados'!G524="","",'Dados tratados'!G524) -> 9.017633e+08 | N22: =IF('Dados tratados'!G525="","",'Dados tratados'!G525) -> 4.7990483e+08 | O22: =IF('Dados tratados'!G529="","",'Dados tratados'!G529) -> 8.912051e+08 | P22: =IF('Dados tratados'!J520="","",'Dados tratados'!J520) -> 53.88 | Q22: =IF('Dados tratados'!E526="","",'Dados tratados'!E526) -> 5783730209 | R22: =IF('Dados tratados'!G526="","",'Dados tratados'!G526) -> 6.6303537e+09 | S22: =IF('Dados tratados'!G527="","",'Dados tratados'!G527) -> 23173.33
A23: Juazeiro do Norte/CE | B23: 2023 | C23: =IF('Dados tratados'!E550="","",'Dados tratados'!E550) | D23: =IF('Dados tratados'!E553="","",'Dados tratados'!E553) -> 1.0051759e+09 | E23: =IF('Dados tratados'!G553="","",'Dados tratados'!G553) -> 1.1017062e+09 | F23: =IF('Dados tratados'!G554="","",'Dados tratados'!G554) -> 1.0442806e+09 | G23: =IF('Dados tratados'!G535="","",'Dados tratados'!G535) -> 1.7593054e+08 | H23: =IF('Dados tratados'!I553="","",'Dados tratados'!I553) | I23: =IF('Dados tratados'!G555="","",'Dados tratados'!G555) -> 4.307229e+08 | J23: =IF('Dados tratados'!G556="","",'Dados tratados'!G556) -> 1.2527713e+08 | K23: =IF('Dados tratados'!G538="","",'Dados tratados'!G538) -> 1.0015591e+09 | L23: =IF('Dados tratados'!G539="","",'Dados tratados'!G539) -> 9.8737728e+08 | M23: =IF('Dados tratados'!G540="","",'Dados tratados'!G540) -> 9.4330299e+08 | N23: =IF('Dados tratados'!G541="","",'Dados tratados'!G541) -> 4.5771223e+08 | O23: =IF('Dados tratados'!G551="","",'Dados tratados'!G551) -> 8.8029671e+08 | P23: =IF('Dados tratados'!J536="","",'Dados tratados'!J536) -> 53.78 | Q23: =IF('Dados tratados'!E548="","",'Dados tratados'!E548) -> 6457542671 | R23: =IF('Dados tratados'!G548="","",'Dados tratados'!G548) -> 7.0776813e+09 | S23: =IF('Dados tratados'!G549="","",'Dados tratados'!G549) -> 24736.757 | T23: =IF('Dados tratados'!J547="","",ROUND('Dados tratados'!J547,1)) -> 5.5 | U23: =IF('Dados tratados'!J546="","",ROUND('Dados tratados'!J546,1)) -> 4.9
A24: Juazeiro do Norte/CE | B24: 2024 | C24: =IF('Dados tratados'!E564="","",'Dados tratados'!E564) -> 303004 | D24: =IF('Dados tratados'!E567="","",'Dados tratados'!E567) -> 1.1806379e+09 | E24: =IF('Dados tratados'!G567="","",'Dados tratados'!G567) -> 1.2398676e+09 | F24: =IF('Dados tratados'!G568="","",'Dados tratados'!G568) -> 1.1779188e+09 | G24: =IF('Dados tratados'!G557="","",'Dados tratados'!G557) -> 1.8410232e+08 | H24: =IF('Dados tratados'!I567="","",'Dados tratados'!I567) -> 4091.9184 | I24: =IF('Dados tratados'!G569="","",'Dados tratados'!G569) -> 5.0272049e+08 | J24: =IF('Dados tratados'!G570="","",'Dados tratados'!G570) -> 1.3090848e+08 | K24: =IF('Dados tratados'!G560="","",'Dados tratados'!G560) -> 1.1519602e+09 | L24: =IF('Dados tratados'!G561="","",'Dados tratados'!G561) -> 1.1371512e+09 | M24: =IF('Dados tratados'!G562="","",'Dados tratados'!G562) -> 1.098317e+09 | N24: =IF('Dados tratados'!G563="","",'Dados tratados'!G563) -> 4.7663873e+08 | O24: =IF('Dados tratados'!G565="","",'Dados tratados'!G565) -> 1.0082374e+09 | P24: =IF('Dados tratados'!J558="","",'Dados tratados'!J558) -> 48.8
A25: Juazeiro do Norte/CE | B25: 2025 | C25: =IF('Dados tratados'!E584="","",'Dados tratados'!E584) -> 305531 | D25: =IF('Dados tratados'!E587="","",'Dados tratados'!E587) -> 1.3114161e+09 | E25: =IF('Dados tratados'!G587="","",'Dados tratados'!G587) -> 1.3114161e+09 | F25: =IF('Dados tratados'!G588="","",'Dados tratados'!G588) -> 1.247858e+09 | G25: =IF('Dados tratados'!G571="","",'Dados tratados'!G571) -> 2.1317204e+08 | H25: =IF('Dados tratados'!I587="","",'Dados tratados'!I587) -> 4292.252 | I25: =IF('Dados tratados'!G589="","",'Dados tratados'!G589) -> 5.3016049e+08 | J25: =IF('Dados tratados'!G590="","",'Dados tratados'!G590) -> 1.3407585e+08 | K25: =IF('Dados tratados'!G574="","",'Dados tratados'!G574) -> 1.1693958e+09 | L25: =IF('Dados tratados'!G575="","",'Dados tratados'!G575) -> 1.1467558e+09 | M25: =IF('Dados tratados'!G576="","",'Dados tratados'!G576) -> 1.1103404e+09 | N25: =IF('Dados tratados'!G577="","",'Dados tratados'!G577) -> 4.9204277e+08 | O25: =IF('Dados tratados'!G585="","",'Dados tratados'!G585) -> 1.0484594e+09 | P25: =IF('Dados tratados'!J572="","",'Dados tratados'!J572) -> 48.18 | T25: =IF('Dados tratados'!J583="","",ROUND('Dados tratados'!J583,1)) -> 5.6 | U25: =IF('Dados tratados'!J582="","",ROUND('Dados tratados'!J582,1)) -> 4.9
A26: Argentina | B26: 2014
A27: Argentina | B27: 2015
A28: Argentina | B28: 2016 | C28: =IF('Dados tratados'!E10="","",'Dados tratados'!E10) -> 43590000 | V28: =IF('Dados tratados'!E2="","",'Dados tratados'!E2) -> 2.2730474e+12 | W28: =IF('Dados tratados'!G2="","",'Dados tratados'!G2) -> 2.268147e+14 | X28: =IF('Dados tratados'!I2="","",'Dados tratados'!I2) -> 5203365.4 | Y28: =IF('Dados tratados'!J11="","",'Dados tratados'!J11) -> 1120751.4 | Z28: =IF('Dados tratados'!J6="","",'Dados tratados'!J6) -> 41.522021 | AA28: =IF('Dados tratados'!J9="","",'Dados tratados'!J9) -> -6.654669 | AB28: =IF('Dados tratados'!J7="","",'Dados tratados'!J7) -> 53.1 | AC28: =IF('Dados tratados'!J5="","",'Dados tratados'!J5) -> -2.1 | AD28: =IF('Dados tratados'!J4="","",'Dados tratados'!J4) -> 556.774 | AE28: =IF('Dados tratados'!J3="","",'Dados tratados'!J3) | AF28: =IF('Dados tratados'!D13="","",'Dados tratados'!D13) | AG28: =IF('Dados tratados'!D12="","",'Dados tratados'!D12)
A29: Argentina | B29: 2017 | C29: =IF('Dados tratados'!E22="","",'Dados tratados'!E22) -> 44045000 | V29: =IF('Dados tratados'!E14="","",'Dados tratados'!E14) -> 2.8422167e+12 | W29: =IF('Dados tratados'!G14="","",'Dados tratados'!G14) -> 2.2562365e+14 | X29: =IF('Dados tratados'!I14="","",'Dados tratados'!I14) -> 5122571.1 | Y29: =IF('Dados tratados'!J23="","",'Dados tratados'!J23) -> 1457199.8 | Z29: =IF('Dados tratados'!J18="","",'Dados tratados'!J18) -> 41.121454 | AA29: =IF('Dados tratados'!J21="","",'Dados tratados'!J21) -> -6.6933411 | AB29: =IF('Dados tratados'!J19="","",'Dados tratados'!J19) -> 57 | AC29: =IF('Dados tratados'!J17="","",'Dados tratados'!J17) -> 2.8 | AD29: =IF('Dados tratados'!J16="","",'Dados tratados'!J16) -> 643.861 | AE29: =IF('Dados tratados'!J15="","",'Dados tratados'!J15) -> 25.7 | AF29: =IF('Dados tratados'!D25="","",'Dados tratados'!D25) | AG29: =IF('Dados tratados'!D24="","",'Dados tratados'!D24)
A30: Argentina | B30: 2018 | C30: =IF('Dados tratados'!E34="","",'Dados tratados'!E34) -> 44495000 | V30: =IF('Dados tratados'!E26="","",'Dados tratados'!E26) -> 3.7134091e+12 | W30: =IF('Dados tratados'!G26="","",'Dados tratados'!G26) -> 219494786934247 | X30: =IF('Dados tratados'!I26="","",'Dados tratados'!I26) -> 4933021.4 | Y30: =IF('Dados tratados'!J35="","",'Dados tratados'!J35) -> 1924313.8 | Z30: =IF('Dados tratados'!J30="","",'Dados tratados'!J30) -> 38.949208 | AA30: =IF('Dados tratados'!J33="","",'Dados tratados'!J33) -> -5.4411455 | AB30: =IF('Dados tratados'!J31="","",'Dados tratados'!J31) -> 85.2 | AC30: =IF('Dados tratados'!J29="","",'Dados tratados'!J29) -> -2.6 | AD30: =IF('Dados tratados'!J28="","",'Dados tratados'!J28) -> 524.431 | AE30: =IF('Dados tratados'!J27="","",'Dados tratados'!J27) -> 34.3 | AF30: =IF('Dados tratados'!D37="","",'Dados tratados'!D37) | AG30: =IF('Dados tratados'!D36="","",'Dados tratados'!D36)
A31: Argentina | B31: 2019 | C31: =IF('Dados tratados'!E46="","",'Dados tratados'!E46) -> 44939000 | V31: =IF('Dados tratados'!E38="","",'Dados tratados'!E38) -> 5.4735379e+12 | W31: =IF('Dados tratados'!G38="","",'Dados tratados'!G38) -> 210771147006548 | X31: =IF('Dados tratados'!I38="","",'Dados tratados'!I38) -> 4690161 | Y31: =IF('Dados tratados'!J47="","",'Dados tratados'!J47) -> 2754645.6 | Z31: =IF('Dados tratados'!J42="","",'Dados tratados'!J42) -> 38.129058 | AA31: =IF('Dados tratados'!J45="","",'Dados tratados'!J45) -> -4.4447575 | AB31: =IF('Dados tratados'!J43="","",'Dados tratados'!J43) -> 89.8 | AC31: =IF('Dados tratados'!J41="","",'Dados tratados'!J41) -> -2 | AD31: =IF('Dados tratados'!J40="","",'Dados tratados'!J40) -> 446.762 | AE31: =IF('Dados tratados'!J39="","",'Dados tratados'!J39) -> 53.5 | AF31: =IF('Dados tratados'!D49="","",'Dados tratados'!D49) | AG31: =IF('Dados tratados'!D48="","",'Dados tratados'!D48)
A32: Argentina | B32: 2020 | C32: =IF('Dados tratados'!E58="","",'Dados tratados'!E58) -> 45377000 | V32: =IF('Dados tratados'!E50="","",'Dados tratados'!E50) -> 7.2374102e+12 | W32: =IF('Dados tratados'!G50="","",'Dados tratados'!G50) -> 1.9626275e+14 | X32: =IF('Dados tratados'!I50="","",'Dados tratados'!I50) -> 4325159.2 | Y32: =IF('Dados tratados'!J59="","",'Dados tratados'!J59) -> 3742115.7 | Z32: =IF('Dados tratados'!J54="","",'Dados tratados'!J54) -> 42.47924 | AA32: =IF('Dados tratados'!J57="","",'Dados tratados'!J57) -> -8.6740712 | AB32: =IF('Dados tratados'!J55="","",'Dados tratados'!J55) -> 103.8 | AC32: =IF('Dados tratados'!J53="","",'Dados tratados'!J53) -> -9.9 | AD32: =IF('Dados tratados'!J52="","",'Dados tratados'!J52) -> 385.218 | AE32: =IF('Dados tratados'!J51="","",'Dados tratados'!J51) -> 42 | AF32: =IF('Dados tratados'!D61="","",'Dados tratados'!D61) | AG32: =IF('Dados tratados'!D60="","",'Dados tratados'!D60)
A33: Argentina | B33: 2021 | C33: =IF('Dados tratados'!E70="","",'Dados tratados'!E70) -> 45809000 | V33: =IF('Dados tratados'!E62="","",'Dados tratados'!E62) -> 11906730771054 | W33: =IF('Dados tratados'!G62="","",'Dados tratados'!G62) -> 2.1757717e+14 | X33: =IF('Dados tratados'!I62="","",'Dados tratados'!I62) -> 4749659.8 | Y33: =IF('Dados tratados'!J71="","",'Dados tratados'!J71) -> 6116121.7 | Z33: =IF('Dados tratados'!J66="","",'Dados tratados'!J66) -> 37.883365 | AA33: =IF('Dados tratados'!J69="","",'Dados tratados'!J69) -> -4.332952 | AB33: =IF('Dados tratados'!J67="","",'Dados tratados'!J67) -> 81 | AC33: =IF('Dados tratados'!J65="","",'Dados tratados'!J65) -> 10.4 | AD33: =IF('Dados tratados'!J64="","",'Dados tratados'!J64) -> 486.04 | AE33: =IF('Dados tratados'!J63="","",'Dados tratados'!J63) -> 48.4 | AF33: =IF('Dados tratados'!D73="","",'Dados tratados'!D73) | AG33: =IF('Dados tratados'!D72="","",'Dados tratados'!D72)
A34: Argentina | B34: 2022 | C34: =IF('Dados tratados'!E82="","",'Dados tratados'!E82) -> 46235000 | V34: =IF('Dados tratados'!E74="","",'Dados tratados'!E74) -> 2.1540626e+13 | W34: =IF('Dados tratados'!G74="","",'Dados tratados'!G74) -> 2.2831889e+14 | X34: =IF('Dados tratados'!I74="","",'Dados tratados'!I74) -> 4938226.3 | Y34: =IF('Dados tratados'!J83="","",'Dados tratados'!J83) -> 11276057 | Z34: =IF('Dados tratados'!J78="","",'Dados tratados'!J78) -> 37.643123 | AA34: =IF('Dados tratados'!J81="","",'Dados tratados'!J81) -> -3.8363851 | AB34: =IF('Dados tratados'!J79="","",'Dados tratados'!J79) -> 84.3 | AC34: =IF('Dados tratados'!J77="","",'Dados tratados'!J77) -> 6 | AD34: =IF('Dados tratados'!J76="","",'Dados tratados'!J76) -> 633.52 | AE34: =IF('Dados tratados'!J75="","",'Dados tratados'!J75) -> 72.4 | AF34: =IF('Dados tratados'!D85="","",'Dados tratados'!D85) | AG34: =IF('Dados tratados'!D84="","",'Dados tratados'!D84)
A35: Argentina | B35: 2023 | C35: =IF('Dados tratados'!E94="","",'Dados tratados'!E94) -> 46655000 | V35: =IF('Dados tratados'!E86="","",'Dados tratados'!E86) -> 4.6463191e+13 | W35: =IF('Dados tratados'!G86="","",'Dados tratados'!G86) -> 2.1091413e+14 | X35: =IF('Dados tratados'!I86="","",'Dados tratados'!I86) -> 4520718.6 | Y35: =IF('Dados tratados'!J95="","",'Dados tratados'!J95) -> 25030205 | Z35: =IF('Dados tratados'!J90="","",'Dados tratados'!J90) -> 37.637348 | AA35: =IF('Dados tratados'!J93="","",'Dados tratados'!J93) -> -5.2809834 | AB35: =IF('Dados tratados'!J91="","",'Dados tratados'!J91) -> 153.4 | AC35: =IF('Dados tratados'!J89="","",'Dados tratados'!J89) -> -1.9 | AD35: =IF('Dados tratados'!J88="","",'Dados tratados'!J88) -> 654.081 | AE35: =IF('Dados tratados'!J87="","",'Dados tratados'!J87) -> 133.5 | AF35: =IF('Dados tratados'!D97="","",'Dados tratados'!D97) | AG35: =IF('Dados tratados'!D96="","",'Dados tratados'!D96)
A36: Argentina | B36: 2024 | C36: =IF('Dados tratados'!E106="","",'Dados tratados'!E106) -> 47068000 | V36: =IF('Dados tratados'!E98="","",'Dados tratados'!E98) -> 142031453049165 | W36: =IF('Dados tratados'!G98="","",'Dados tratados'!G98) -> 2.0154263e+14 | X36: =IF('Dados tratados'!I98="","",'Dados tratados'!I98) -> 4281945.9 | Y36: =IF('Dados tratados'!J107="","",'Dados tratados'!J107) -> 73874240 | Z36: =IF('Dados tratados'!J102="","",'Dados tratados'!J102) -> 31.019182 | AA36: =IF('Dados tratados'!J105="","",'Dados tratados'!J105) -> 0.45837829 | AB36: =IF('Dados tratados'!J103="","",'Dados tratados'!J103) -> 84.6 | AC36: =IF('Dados tratados'!J101="","",'Dados tratados'!J101) -> -1.4 | AD36: =IF('Dados tratados'!J100="","",'Dados tratados'!J100) -> 637.744 | AE36: =IF('Dados tratados'!J99="","",'Dados tratados'!J99) -> 219.9 | AF36: =IF('Dados tratados'!D109="","",'Dados tratados'!D109) | AG36: =IF('Dados tratados'!D108="","",'Dados tratados'!D108)
A37: Argentina | B37: 2025 | C37: =IF('Dados tratados'!E118="","",'Dados tratados'!E118) -> 47474000 | V37: =IF('Dados tratados'!E110="","",'Dados tratados'!E110) -> 200448446615565 | W37: =IF('Dados tratados'!G110="","",'Dados tratados'!G110) -> 200448446615565 | X37: =IF('Dados tratados'!I110="","",'Dados tratados'!I110) -> 4222278.4 | Y37: =IF('Dados tratados'!J119="","",'Dados tratados'!J119) -> 1.0397413e+08 | Z37: =IF('Dados tratados'!J114="","",'Dados tratados'!J114) | AA37: =IF('Dados tratados'!J117="","",'Dados tratados'!J117) -> -0.15602149 | AB37: =IF('Dados tratados'!J115="","",'Dados tratados'!J115) -> 80.1 | AC37: =IF('Dados tratados'!J113="","",'Dados tratados'!J113) -> 4.5 | AD37: =IF('Dados tratados'!J112="","",'Dados tratados'!J112) -> 683.589 | AE37: =IF('Dados tratados'!J111="","",'Dados tratados'!J111) -> 41.9 | AF37: =IF('Dados tratados'!D121="","",'Dados tratados'!D121) -> 11769219 | AG37: =IF('Dados tratados'!D120="","",'Dados tratados'!D120) -> 1453819

Sheet Dados brutos atualizados
A1: Entidade | B1: Ano | C1: Período/competência | D1: Variável | E1: Valor na fonte | F1: Unidade publicada | G1: Fator para unidade padrão | H1: Campo/linha de origem | I1: Código/variável-fonte | J1: Status de observação | K1: Observação/metadado | L1: URL da fonte
A2: Argentina | B2: 2016 | C2: 2016 | D2: Arrecadação federal total ARCA (TOTAL GENERAL) | E2: 2.2730474e+09 | F2: mil pesos argentinos (ARS) | G2: 1000 | H2: linha 8; coluna TOTAL; cabeçalho: Miles de pesos | I2: Serie anual 2016 | J2: Publicado | K2: Total de tributos, recursos da seguridade social e aduanas; não é receita total de todo o governo. | L2: https://contenidos.afip.gob.ar/institucional/estudios/archivos/serie2016.xls
A3: Argentina | B3: 2016 | C3: 2016 | D3: CPI inflation annual average (%) | F3: Annual percent change | G3: 1 | H3: PCPIPCH | I3: World Economic Outlook (October 2026) | J3: Sem dado no endpoint/vintage; mantido ausente | K3: Indicador PCPIPCH; fonte IMF: World Economic Outlook (October 2026); metadado do endpoint preservado. | L3: https://www.imf.org/external/datamapper/api/v2/PCPIPCH/ARG?periods=2016,2017,2018,2019,2020,2021,2022,2023,2024,2025
A4: Argentina | B4: 2016 | C4: 2016 | D4: GDP nominal current (USD billion) | E4: 556.774 | F4: Billions of U.S. dollars | G4: 1 | H4: NGDPD | I4: World Economic Outlook (October 2026) | J4: WEO October 2026; latest history/vintage, subject to revision | K4: Indicador NGDPD; fonte IMF: World Economic Outlook (October 2026); metadado do endpoint preservado. | L4: https://www.imf.org/external/datamapper/api/v2/NGDPD/ARG?periods=2016,2017,2018,2019,2020,2021,2022,2023,2024,2025
A5: Argentina | B5: 2016 | C5: 2016 | D5: GDP real growth (%) | E5: -2.1 | F5: Annual percent change | G5: 1 | H5: NGDP_RPCH | I5: World Economic Outlook (October 2026) | J5: WEO October 2026; latest history/vintage, subject to revision | K5: Indicador NGDP_RPCH; fonte IMF: World Economic Outlook (October 2026); metadado do endpoint preservado. | L5: https://www.imf.org/external/datamapper/api/v2/NGDP_RPCH/ARG?periods=2016,2017,2018,2019,2020,2021,2022,2023,2024,2025
A6: Argentina | B6: 2016 | C6: 2016 | D6: Government expenditure (% GDP, FPP) | E6: 41.522021 | F6: % of GDP | G6: 1 | H6: exp | I6: Public Finances in Modern History Database (Dec 2025) | J6: FPP Dec 2025; 2025 not published in this series | K6: Indicador exp; fonte IMF: Public Finances in Modern History Database (Dec 2025); metadado do endpoint preservado. | L6: https://www.imf.org/external/datamapper/api/v2/exp/ARG?periods=2016,2017,2018,2019,2020,2021,2022,2023,2024,2025
A7: Argentina | B7: 2016 | C7: 2016 | D7: Gross debt (% GDP) | E7: 53.1 | F7: Percent of GDP | G7: 1 | H7: GGXWDG_NGDP | I7: World Economic Outlook (October 2026) | J7: WEO October 2026; latest history/vintage, subject to revision | K7: Indicador GGXWDG_NGDP; fonte IMF: World Economic Outlook (October 2026); metadado do endpoint preservado. | L7: https://www.imf.org/external/datamapper/api/v2/GGXWDG_NGDP/ARG?periods=2016,2017,2018,2019,2020,2021,2022,2023,2024,2025
A8: Argentina | B8: 2016 | C8: 2016 | D8: Juros líquidos intra-SPN, base caja (2025) | F8: millones de pesos argentinos (ARS) | G8: 1000000 | H8: nota oficial; fechamento anual 2025 | I8: Hacienda/SPN Base Caja | J8: Publicado somente para 2025; anos anteriores não preenchidos nesta observação de fonte | K8: Resultado primário e financeiro do SPN base caixa; perímetro distinto das contas de governo geral IMF. | L8: https://www.argentina.gob.ar/noticias/en-el-ano-2025-el-sector-publico-nacional-registro-un-superavit-financiero-de-1453819
A9: Argentina | B9: 2016 | C9: 2016 | D9: Net lending/borrowing (% GDP) | E9: -6.654669 | F9: % of GDP | G9: 1 | H9: GGXCNL_G01_GDP_PT | I9: Fiscal Monitor (October 2026) | J9: WEO October 2026; latest history/vintage, subject to revision | K9: Indicador GGXCNL_G01_GDP_PT; fonte IMF: Fiscal Monitor (October 2026); metadado do endpoint preservado. | L9: https://www.imf.org/external/datamapper/api/v2/GGXCNL_G01_GDP_PT/ARG?periods=2016,2017,2018,2019,2020,2021,2022,2023,2024,2025
A10: Argentina | B10: 2016 | C10: 2016 | D10: Population (IMF WEO) | E10: 43.59 | F10: millions of persons | G10: 1000000 | H10: LP | I10: World Economic Outlook (October 2026) | J10: WEO October 2026; latest history/vintage, subject to revision | K10: Indicador LP; fonte IMF: World Economic Outlook (October 2026); metadado do endpoint preservado. | L10: https://www.imf.org/external/datamapper/api/v2/LP/ARG?periods=2016,2017,2018,2019,2020,2021,2022,2023,2024,2025
A11: Argentina | B11: 2016 | C11: 2016 | D11: RON transferências a províncias/CABA (monto publicado) | E11: 1120751.4 | F11: monto conforme CSV; unidade/escala não declarada | H11: soma de monto por ano (27 jurisdições), agregando imposto e regime | I11: ano/provincia/impuesto/regimen/monto | J11: Publicado em unidade reportada; não convertida | K11: RON inclui coparticipação e outros regimes distribuídos; o arquivo não declara unidade monetária. Valores nominais não foram deflacionados nem usados em comparações de nível. | L11: https://www.argentina.gob.ar/sites/default/files/serie_ron_2003_2025.csv
A12: Argentina | B12: 2016 | C12: 2016 | D12: Resultado financeiro SPN, base caja (2025) | F12: millones de pesos argentinos (ARS) | G12: 1000000 | H12: nota oficial; fechamento anual 2025 | I12: Hacienda/SPN Base Caja | J12: Publicado somente para 2025; anos anteriores não preenchidos nesta observação de fonte | K12: Resultado primário e financeiro do SPN base caixa; perímetro distinto das contas de governo geral IMF. | L12: https://www.argentina.gob.ar/noticias/en-el-ano-2025-el-sector-publico-nacional-registro-un-superavit-financiero-de-1453819
A13: Argentina | B13: 2016 | C13: 2016 | D13: Resultado primário SPN, base caja (2025) | F13: millones de pesos argentinos (ARS) | G13: 1000000 | H13: nota oficial; fechamento anual 2025 | I13: Hacienda/SPN Base Caja | J13: Publicado somente para 2025; anos anteriores não preenchidos nesta observação de fonte | K13: Resultado primário e financeiro do SPN base caixa; perímetro distinto das contas de governo geral IMF. | L13: https://www.argentina.gob.ar/noticias/en-el-ano-2025-el-sector-publico-nacional-registro-un-superavit-financiero-de-1453819
A14: Argentina | B14: 2017 | C14: 2017 | D14: Arrecadação federal total ARCA (TOTAL GENERAL) | E14: 2.8422167e+09 | F14: mil pesos argentinos (ARS) | G14: 1000 | H14: linha 8; coluna TOTAL; cabeçalho: Miles de pesos | I14: Serie anual 2017 | J14: Publicado | K14: Total de tributos, recursos da seguridade social e aduanas; não é receita total de todo o governo. | L14: https://contenidos.afip.gob.ar/institucional/estudios/archivos/serie2017.xls
A15: Argentina | B15: 2017 | C15: 2017 | D15: CPI inflation annual average (%) | E15: 25.7 | F15: Annual percent change | G15: 1 | H15: PCPIPCH | I15: World Economic Outlook (October 2026) | J15: WEO October 2026; latest history/vintage, subject to revision | K15: Indicador PCPIPCH; fonte IMF: World Economic Outlook (October 2026); metadado do endpoint preservado. | L15: https://www.imf.org/external/datamapper/api/v2/PCPIPCH/ARG?periods=2016,2017,2018,2019,2020,2021,2022,2023,2024,2025
A16: Argentina | B16: 2017 | C16: 2017 | D16: GDP nominal current (USD billion) | E16: 643.861 | F16: Billions of U.S. dollars | G16: 1 | H16: NGDPD | I16: World Economic Outlook (October 2026) | J16: WEO October 2026; latest history/vintage, subject to revision | K16: Indicador NGDPD; fonte IMF: World Economic Outlook (October 2026); metadado do endpoint preservado. | L16: https://www.imf.org/external/datamapper/api/v2/NGDPD/ARG?periods=2016,2017,2018,2019,2020,2021,2022,2023,2024,2025
A17: Argentina | B17: 2017 | C17: 2017 | D17: GDP real growth (%) | E17: 2.8 | F17: Annual percent change | G17: 1 | H17: NGDP_RPCH | I17: World Economic Outlook (October 2026) | J17: WEO October 2026; latest history/vintage, subject to revision | K17: Indicador NGDP_RPCH; fonte IMF: World Economic Outlook (October 2026); metadado do endpoint preservado. | L17: https://www.imf.org/external/datamapper/api/v2/NGDP_RPCH/ARG?periods=2016,2017,2018,2019,2020,2021,2022,2023,2024,2025
A18: Argentina | B18: 2017 | C18: 2017 | D18: Government expenditure (% GDP, FPP) | E18: 41.121454 | F18: % of GDP | G18: 1 | H18: exp | I18: Public Finances in Modern History Database (Dec 2025) | J18: FPP Dec 2025; 2025 not published in this series | K18: Indicador exp; fonte IMF: Public Finances in Modern History Database (Dec 2025); metadado do endpoint preservado. | L18: https://www.imf.org/external/datamapper/api/v2/exp/ARG?periods=2016,2017,2018,2019,2020,2021,2022,2023,2024,2025
A19: Argentina | B19: 2017 | C19: 2017 | D19: Gross debt (% GDP) | E19: 57 | F19: Percent of GDP | G19: 1 | H19: GGXWDG_NGDP | I19: World Economic Outlook (October 2026) | J19: WEO October 2026; latest history/vintage, subject to revision | K19: Indicador GGXWDG_NGDP; fonte IMF: World Economic Outlook (October 2026); metadado do endpoint preservado. | L19: https://www.imf.org/external/datamapper/api/v2/GGXWDG_NGDP/ARG?periods=2016,2017,2018,2019,2020,2021,2022,2023,2024,2025
A20: Argentina | B20: 2017 | C20: 2017 | D20: Juros líquidos intra-SPN, base caja (2025) | F20: millones de pesos argentinos (ARS) | G20: 1000000 | H20: nota oficial; fechamento anual 2025 | I20: Hacienda/SPN Base Caja | J20: Publicado somente para 2025; anos anteriores não preenchidos nesta observação de fonte | K20: Resultado primário e financeiro do SPN base caixa; perímetro distinto das contas de governo geral IMF. | L20: https://www.argentina.gob.ar/noticias/en-el-ano-2025-el-sector-publico-nacional-registro-un-superavit-financiero-de-1453819
A21: Argentina | B21: 2017 | C21: 2017 | D21: Net lending/borrowing (% GDP) | E21: -6.6933411 | F21: % of GDP | G21: 1 | H21: GGXCNL_G01_GDP_PT | I21: Fiscal Monitor (October 2026) | J21: WEO October 2026; latest history/vintage, subject to revision | K21: Indicador GGXCNL_G01_GDP_PT; fonte IMF: Fiscal Monitor (October 2026); metadado do endpoint preservado. | L21: https://www.imf.org/external/datamapper/api/v2/GGXCNL_G01_GDP_PT/ARG?periods=2016,2017,2018,2019,2020,2021,2022,2023,2024,2025
A22: Argentina | B22: 2017 | C22: 2017 | D22: Population (IMF WEO) | E22: 44.045 | F22: millions of persons | G22: 1000000 | H22: LP | I22: World Economic Outlook (October 2026) | J22: WEO October 2026; latest history/vintage, subject to revision | K22: Indicador LP; fonte IMF: World Economic Outlook (October 2026); metadado do endpoint preservado. | L22: https://www.imf.org/external/datamapper/api/v2/LP/ARG?periods=2016,2017,2018,2019,2020,2021,2022,2023,2024,2025
A23: Argentina | B23: 2017 | C23: 2017 | D23: RON transferências a províncias/CABA (monto publicado) | E23: 1457199.8 | F23: monto conforme CSV; unidade/escala não declarada | H23: soma de monto por ano (27 jurisdições), agregando imposto e regime | I23: ano/provincia/impuesto/regimen/monto | J23: Publicado em unidade reportada; não convertida | K23: RON inclui coparticipação e outros regimes distribuídos; o arquivo não declara unidade monetária. Valores nominais não foram deflacionados nem usados em comparações de nível. | L23: https://www.argentina.gob.ar/sites/default/files/serie_ron_2003_2025.csv
A24: Argentina | B24: 2017 | C24: 2017 | D24: Resultado financeiro SPN, base caja (2025) | F24: millones de pesos argentinos (ARS) | G24: 1000000 | H24: nota oficial; fechamento anual 2025 | I24: Hacienda/SPN Base Caja | J24: Publicado somente para 2025; anos anteriores não preenchidos nesta observação de fonte | K24: Resultado primário e financeiro do SPN base caixa; perímetro distinto das contas de governo geral IMF. | L24: https://www.argentina.gob.ar/noticias/en-el-ano-2025-el-sector-publico-nacional-registro-un-superavit-financiero-de-1453819
A25: Argentina | B25: 2017 | C25: 2017 | D25: Resultado primário SPN, base caja (2025) | F25: millones de pesos argentinos (ARS) | G25: 1000000 | H25: nota oficial; fechamento anual 2025 | I25: Hacienda/SPN Base Caja | J25: Publicado somente para 2025; anos anteriores não preenchidos nesta observação de fonte | K25: Resultado primário e financeiro do SPN base caixa; perímetro distinto das contas de governo geral IMF. | L25: https://www.argentina.gob.ar/noticias/en-el-ano-2025-el-sector-publico-nacional-registro-un-superavit-financiero-de-1453819
A26: Argentina | B26: 2018 | C26: 2018 | D26: Arrecadação federal total ARCA (TOTAL GENERAL) | E26: 3.7134091e+09 | F26: mil pesos argentinos (ARS) | G26: 1000 | H26: linha 8; coluna TOTAL; cabeçalho: Miles de pesos | I26: Serie anual 2018 | J26: Publicado | K26: Total de tributos, recursos da seguridade social e aduanas; não é receita total de todo o governo. | L26: https://contenidos.afip.gob.ar/institucional/estudios/archivos/serie2018.xls
A27: Argentina | B27: 2018 | C27: 2018 | D27: CPI inflation annual average (%) | E27: 34.3 | F27: Annual percent change | G27: 1 | H27: PCPIPCH | I27: World Economic Outlook (October 2026) | J27: WEO October 2026; latest history/vintage, subject to revision | K27: Indicador PCPIPCH; fonte IMF: World Economic Outlook (October 2026); metadado do endpoint preservado. | L27: https://www.imf.org/external/datamapper/api/v2/PCPIPCH/ARG?periods=2016,2017,2018,2019,2020,2021,2022,2023,2024,2025
A28: Argentina | B28: 2018 | C28: 2018 | D28: GDP nominal current (USD billion) | E28: 524.431 | F28: Billions of U.S. dollars | G28: 1 | H28: NGDPD | I28: World Economic Outlook (October 2026) | J28: WEO October 2026; latest history/vintage, subject to revision | K28: Indicador NGDPD; fonte IMF: World Economic Outlook (October 2026); metadado do endpoint preservado. | L28: https://www.imf.org/external/datamapper/api/v2/NGDPD/ARG?periods=2016,2017,2018,2019,2020,2021,2022,2023,2024,2025
A29: Argentina | B29: 2018 | C29: 2018 | D29: GDP real growth (%) | E29: -2.6 | F29: Annual percent change | G29: 1 | H29: NGDP_RPCH | I29: World Economic Outlook (October 2026) | J29: WEO October 2026; latest history/vintage, subject to revision | K29: Indicador NGDP_RPCH; fonte IMF: World Economic Outlook (October 2026); metadado do endpoint preservado. | L29: https://www.imf.org/external/datamapper/api/v2/NGDP_RPCH/ARG?periods=2016,2017,2018,2019,2020,2021,2022,2023,2024,2025
A30: Argentina | B30: 2018 | C30: 2018 | D30: Government expenditure (% GDP, FPP) | E30: 38.949208 | F30: % of GDP | G30: 1 | H30: exp | I30: Public Finances in Modern History Database (Dec 2025) | J30: FPP Dec 2025; 2025 not published in this series | K30: Indicador exp; fonte IMF: Public Finances in Modern History Database (Dec 2025); metadado do endpoint preservado. | L30: https://www.imf.org/external/datamapper/api/v2/exp/ARG?periods=2016,2017,2018,2019,2020,2021,2022,2023,2024,2025
A31: Argentina | B31: 2018 | C31: 2018 | D31: Gross debt (% GDP) | E31: 85.2 | F31: Percent of GDP | G31: 1 | H31: GGXWDG_NGDP | I31: World Economic Outlook (October 2026) | J31: WEO October 2026; latest history/vintage, subject to revision | K31: Indicador GGXWDG_NGDP; fonte IMF: World Economic Outlook (October 2026); metadado do endpoint preservado. | L31: https://www.imf.org/external/datamapper/api/v2/GGXWDG_NGDP/ARG?periods=2016,2017,2018,2019,2020,2021,2022,2023,2024,2025
A32: Argentina | B32: 2018 | C32: 2018 | D32: Juros líquidos intra-SPN, base caja (2025) | F32: millones de pesos argentinos (ARS) | G32: 1000000 | H32: nota oficial; fechamento anual 2025 | I32: Hacienda/SPN Base Caja | J32: Publicado somente para 2025; anos anteriores não preenchidos nesta observação de fonte | K32: Resultado primário e financeiro do SPN base caixa; perímetro distinto das contas de governo geral IMF. | L32: https://www.argentina.gob.ar/noticias/en-el-ano-2025-el-sector-publico-nacional-registro-un-superavit-financiero-de-1453819
A33: Argentina | B33: 2018 | C33: 2018 | D33: Net lending/borrowing (% GDP) | E33: -5.4411455 | F33: % of GDP | G33: 1 | H33: GGXCNL_G01_GDP_PT | I33: Fiscal Monitor (October 2026) | J33: WEO October 2026; latest history/vintage, subject to revision | K33: Indicador GGXCNL_G01_GDP_PT; fonte IMF: Fiscal Monitor (October 2026); metadado do endpoint preservado. | L33: https://www.imf.org/external/datamapper/api/v2/GGXCNL_G01_GDP_PT/ARG?periods=2016,2017,2018,2019,2020,2021,2022,2023,2024,2025
A34: Argentina | B34: 2018 | C34: 2018 | D34: Population (IMF WEO) | E34: 44.495 | F34: millions of persons | G34: 1000000 | H34: LP | I34: World Economic Outlook (October 2026) | J34: WEO October 2026; latest history/vintage, subject to revision | K34: Indicador LP; fonte IMF: World Economic Outlook (October 2026); metadado do endpoint preservado. | L34: https://www.imf.org/external/datamapper/api/v2/LP/ARG?periods=2016,2017,2018,2019,2020,2021,2022,2023,2024,2025
A35: Argentina | B35: 2018 | C35: 2018 | D35: RON transferências a províncias/CABA (monto publicado) | E35: 1924313.8 | F35: monto conforme CSV; unidade/escala não declarada | H35: soma de monto por ano (27 jurisdições), agregando imposto e regime | I35: ano/provincia/impuesto/regimen/monto | J35: Publicado em unidade reportada; não convertida | K35: RON inclui coparticipação e outros regimes distribuídos; o arquivo não declara unidade monetária. Valores nominais não foram deflacionados nem usados em comparações de nível. | L35: https://www.argentina.gob.ar/sites/default/files/serie_ron_2003_2025.csv
A36: Argentina | B36: 2018 | C36: 2018 | D36: Resultado financeiro SPN, base caja (2025) | F36: millones de pesos argentinos (ARS) | G36: 1000000 | H36: nota oficial; fechamento anual 2025 | I36: Hacienda/SPN Base Caja | J36: Publicado somente para 2025; anos anteriores não preenchidos nesta observação de fonte | K36: Resultado primário e financeiro do SPN base caixa; perímetro distinto das contas de governo geral IMF. | L36: https://www.argentina.gob.ar/noticias/en-el-ano-2025-el-sector-publico-nacional-registro-un-superavit-financiero-de-1453819
A37: Argentina | B37: 2018 | C37: 2018 | D37: Resultado primário SPN, base caja (2025) | F37: millones de pesos argentinos (ARS) | G37: 1000000 | H37: nota oficial; fechamento anual 2025 | I37: Hacienda/SPN Base Caja | J37: Publicado somente para 2025; anos anteriores não preenchidos nesta observação de fonte | K37: Resultado primário e financeiro do SPN base caixa; perímetro distinto das contas de governo geral IMF. | L37: https://www.argentina.gob.ar/noticias/en-el-ano-2025-el-sector-publico-nacional-registro-un-superavit-financiero-de-1453819
A38: Argentina | B38: 2019 | C38: 2019 | D38: Arrecadação federal total ARCA (TOTAL GENERAL) | E38: 5.4735379e+09 | F38: mil pesos argentinos (ARS) | G38: 1000 | H38: linha 8; coluna TOTAL; cabeçalho: Miles de pesos | I38: Serie anual 2019 | J38: Publicado | K38: Total de tributos, recursos da seguridade social e aduanas; não é receita total de todo o governo. | L38: https://contenidos.afip.gob.ar/institucional/estudios/archivos/serie2019.xls
A39: Argentina | B39: 2019 | C39: 2019 | D39: CPI inflation annual average (%) | E39: 53.5 | F39: Annual percent change | G39: 1 | H39: PCPIPCH | I39: World Economic Outlook (October 2026) | J39: WEO October 2026; latest history/vintage, subject to revision | K39: Indicador PCPIPCH; fonte IMF: World Economic Outlook (October 2026); metadado do endpoint preservado. | L39: https://www.imf.org/external/datamapper/api/v2/PCPIPCH/ARG?periods=2016,2017,2018,2019,2020,2021,2022,2023,2024,2025
A40: Argentina | B40: 2019 | C40: 2019 | D40: GDP nominal current (USD billion) | E40: 446.762 | F40: Billions of U.S. dollars | G40: 1 | H40: NGDPD | I40: World Economic Outlook (October 2026) | J40: WEO October 2026; latest history/vintage, subject to revision | K40: Indicador NGDPD; fonte IMF: World Economic Outlook (October 2026); metadado do endpoint preservado. | L40: https://www.imf.org/external/datamapper/api/v2/NGDPD/ARG?periods=2016,2017,2018,2019,2020,2021,2022,2023,2024,2025
A41: Argentina | B41: 2019 | C41: 2019 | D41: GDP real growth (%) | E41: -2 | F41: Annual percent change | G41: 1 | H41: NGDP_RPCH | I41: World Economic Outlook (October 2026) | J41: WEO October 2026; latest history/vintage, subject to revision | K41: Indicador NGDP_RPCH; fonte IMF: World Economic Outlook (October 2026); metadado do endpoint preservado. | L41: https://www.imf.org/external/datamapper/api/v2/NGDP_RPCH/ARG?periods=2016,2017,2018,2019,2020,2021,2022,2023,2024,2025
A42: Argentina | B42: 2019 | C42: 2019 | D42: Government expenditure (% GDP, FPP) | E42: 38.129058 | F42: % of GDP | G42: 1 | H42: exp | I42: Public Finances in Modern History Database (Dec 2025) | J42: FPP Dec 2025; 2025 not published in this series | K42: Indicador exp; fonte IMF: Public Finances in Modern History Database (Dec 2025); metadado do endpoint preservado. | L42: https://www.imf.org/external/datamapper/api/v2/exp/ARG?periods=2016,2017,2018,2019,2020,2021,2022,2023,2024,2025
A43: Argentina | B43: 2019 | C43: 2019 | D43: Gross debt (% GDP) | E43: 89.8 | F43: Percent of GDP | G43: 1 | H43: GGXWDG_NGDP | I43: World Economic Outlook (October 2026) | J43: WEO October 2026; latest history/vintage, subject to revision | K43: Indicador GGXWDG_NGDP; fonte IMF: World Economic Outlook (October 2026); metadado do endpoint preservado. | L43: https://www.imf.org/external/datamapper/api/v2/GGXWDG_NGDP/ARG?periods=2016,2017,2018,2019,2020,2021,2022,2023,2024,2025
A44: Argentina | B44: 2019 | C44: 2019 | D44: Juros líquidos intra-SPN, base caja (2025) | F44: millones de pesos argentinos (ARS) | G44: 1000000 | H44: nota oficial; fechamento anual 2025 | I44: Hacienda/SPN Base Caja | J44: Publicado somente para 2025; anos anteriores não preenchidos nesta observação de fonte | K44: Resultado primário e financeiro do SPN base caixa; perímetro distinto das contas de governo geral IMF. | L44: https://www.argentina.gob.ar/noticias/en-el-ano-2025-el-sector-publico-nacional-registro-un-superavit-financiero-de-1453819
A45: Argentina | B45: 2019 | C45: 2019 | D45: Net lending/borrowing (% GDP) | E45: -4.4447575 | F45: % of GDP | G45: 1 | H45: GGXCNL_G01_GDP_PT | I45: Fiscal Monitor (October 2026) | J45: WEO October 2026; latest history/vintage, subject to revision | K45: Indicador GGXCNL_G01_GDP_PT; fonte IMF: Fiscal Monitor (October 2026); metadado do endpoint preservado. | L45: https://www.imf.org/external/datamapper/api/v2/GGXCNL_G01_GDP_PT/ARG?periods=2016,2017,2018,2019,2020,2021,2022,2023,2024,2025
A46: Argentina | B46: 2019 | C46: 2019 | D46: Population (IMF WEO) | E46: 44.939 | F46: millions of persons | G46: 1000000 | H46: LP | I46: World Economic Outlook (October 2026) | J46: WEO October 2026; latest history/vintage, subject to revision | K46: Indicador LP; fonte IMF: World Economic Outlook (October 2026); metadado do endpoint preservado. | L46: https://www.imf.org/external/datamapper/api/v2/LP/ARG?periods=2016,2017,2018,2019,2020,2021,2022,2023,2024,2025
A47: Argentina | B47: 2019 | C47: 2019 | D47: RON transferências a províncias/CABA (monto publicado) | E47: 2754645.6 | F47: monto conforme CSV; unidade/escala não declarada | H47: soma de monto por ano (27 jurisdições), agregando imposto e regime | I47: ano/provincia/impuesto/regimen/monto | J47: Publicado em unidade reportada; não convertida | K47: RON inclui coparticipação e outros regimes distribuídos; o arquivo não declara unidade monetária. Valores nominais não foram deflacionados nem usados em comparações de nível. | L47: https://www.argentina.gob.ar/sites/default/files/serie_ron_2003_2025.csv
A48: Argentina | B48: 2019 | C48: 2019 | D48: Resultado financeiro SPN, base caja (2025) | F48: millones de pesos argentinos (ARS) | G48: 1000000 | H48: nota oficial; fechamento anual 2025 | I48: Hacienda/SPN Base Caja | J48: Publicado somente para 2025; anos anteriores não preenchidos nesta observação de fonte | K48: Resultado primário e financeiro do SPN base caixa; perímetro distinto das contas de governo geral IMF. | L48: https://www.argentina.gob.ar/noticias/en-el-ano-2025-el-sector-publico-nacional-registro-un-superavit-financiero-de-1453819
A49: Argentina | B49: 2019 | C49: 2019 | D49: Resultado primário SPN, base caja (2025) | F49: millones de pesos argentinos (ARS) | G49: 1000000 | H49: nota oficial; fechamento anual 2025 | I49: Hacienda/SPN Base Caja | J49: Publicado somente para 2025; anos anteriores não preenchidos nesta observação de fonte | K49: Resultado primário e financeiro do SPN base caixa; perímetro distinto das contas de governo geral IMF. | L49: https://www.argentina.gob.ar/noticias/en-el-ano-2025-el-sector-publico-nacional-registro-un-superavit-financiero-de-1453819
A50: Argentina | B50: 2020 | C50: 2020 | D50: Arrecadação federal total ARCA (TOTAL GENERAL) | E50: 7.2374102e+09 | F50: mil pesos argentinos (ARS) | G50: 1000 | H50: linha 8; coluna TOTAL; cabeçalho: Miles de pesos | I50: Serie anual 2020 | J50: Publicado | K50: Total de tributos, recursos da seguridade social e aduanas; não é receita total de todo o governo. | L50: https://contenidos.afip.gob.ar/institucional/estudios/archivos/serie2020.xls
A51: Argentina | B51: 2020 | C51: 2020 | D51: CPI inflation annual average (%) | E51: 42 | F51: Annual percent change | G51: 1 | H51: PCPIPCH | I51: World Economic Outlook (October 2026) | J51: WEO October 2026; latest history/vintage, subject to revision | K51: Indicador PCPIPCH; fonte IMF: World Economic Outlook (October 2026); metadado do endpoint preservado. | L51: https://www.imf.org/external/datamapper/api/v2/PCPIPCH/ARG?periods=2016,2017,2018,2019,2020,2021,2022,2023,2024,2025
A52: Argentina | B52: 2020 | C52: 2020 | D52: GDP nominal current (USD billion) | E52: 385.218 | F52: Billions of U.S. dollars | G52: 1 | H52: NGDPD | I52: World Economic Outlook (October 2026) | J52: WEO October 2026; latest history/vintage, subject to revision | K52: Indicador NGDPD; fonte IMF: World Economic Outlook (October 2026); metadado do endpoint preservado. | L52: https://www.imf.org/external/datamapper/api/v2/NGDPD/ARG?periods=2016,2017,2018,2019,2020,2021,2022,2023,2024,2025
A53: Argentina | B53: 2020 | C53: 2020 | D53: GDP real growth (%) | E53: -9.9 | F53: Annual percent change | G53: 1 | H53: NGDP_RPCH | I53: World Economic Outlook (October 2026) | J53: WEO October 2026; latest history/vintage, subject to revision | K53: Indicador NGDP_RPCH; fonte IMF: World Economic Outlook (October 2026); metadado do endpoint preservado. | L53: https://www.imf.org/external/datamapper/api/v2/NGDP_RPCH/ARG?periods=2016,2017,2018,2019,2020,2021,2022,2023,2024,2025
A54: Argentina | B54: 2020 | C54: 2020 | D54: Government expenditure (% GDP, FPP) | E54: 42.47924 | F54: % of GDP | G54: 1 | H54: exp | I54: Public Finances in Modern History Database (Dec 2025) | J54: FPP Dec 2025; 2025 not published in this series | K54: Indicador exp; fonte IMF: Public Finances in Modern History Database (Dec 2025); metadado do endpoint preservado. | L54: https://www.imf.org/external/datamapper/api/v2/exp/ARG?periods=2016,2017,2018,2019,2020,2021,2022,2023,2024,2025
A55: Argentina | B55: 2020 | C55: 2020 | D55: Gross debt (% GDP) | E55: 103.8 | F55: Percent of GDP | G55: 1 | H55: GGXWDG_NGDP | I55: World Economic Outlook (October 2026) | J55: WEO October 2026; latest history/vintage, subject to revision | K55: Indicador GGXWDG_NGDP; fonte IMF: World Economic Outlook (October 2026); metadado do endpoint preservado. | L55: https://www.imf.org/external/datamapper/api/v2/GGXWDG_NGDP/ARG?periods=2016,2017,2018,2019,2020,2021,2022,2023,2024,2025
A56: Argentina | B56: 2020 | C56: 2020 | D56: Juros líquidos intra-SPN, base caja (2025) | F56: millones de pesos argentinos (ARS) | G56: 1000000 | H56: nota oficial; fechamento anual 2025 | I56: Hacienda/SPN Base Caja | J56: Publicado somente para 2025; anos anteriores não preenchidos nesta observação de fonte | K56: Resultado primário e financeiro do SPN base caixa; perímetro distinto das contas de governo geral IMF. | L56: https://www.argentina.gob.ar/noticias/en-el-ano-2025-el-sector-publico-nacional-registro-un-superavit-financiero-de-1453819
A57: Argentina | B57: 2020 | C57: 2020 | D57: Net lending/borrowing (% GDP) | E57: -8.6740712 | F57: % of GDP | G57: 1 | H57: GGXCNL_G01_GDP_PT | I57: Fiscal Monitor (October 2026) | J57: WEO October 2026; latest history/vintage, subject to revision | K57: Indicador GGXCNL_G01_GDP_PT; fonte IMF: Fiscal Monitor (October 2026); metadado do endpoint preservado. | L57: https://www.imf.org/external/datamapper/api/v2/GGXCNL_G01_GDP_PT/ARG?periods=2016,2017,2018,2019,2020,2021,2022,2023,2024,2025
A58: Argentina | B58: 2020 | C58: 2020 | D58: Population (IMF WEO) | E58: 45.377 | F58: millions of persons | G58: 1000000 | H58: LP | I58: World Economic Outlook (October 2026) | J58: WEO October 2026; latest history/vintage, subject to revision | K58: Indicador LP; fonte IMF: World Economic Outlook (October 2026); metadado do endpoint preservado. | L58: https://www.imf.org/external/datamapper/api/v2/LP/ARG?periods=2016,2017,2018,2019,2020,2021,2022,2023,2024,2025
A59: Argentina | B59: 2020 | C59: 2020 | D59: RON transferências a províncias/CABA (monto publicado) | E59: 3742115.7 | F59: monto conforme CSV; unidade/escala não declarada | H59: soma de monto por ano (27 jurisdições), agregando imposto e regime | I59: ano/provincia/impuesto/regimen/monto | J59: Publicado em unidade reportada; não convertida | K59: RON inclui coparticipação e outros regimes distribuídos; o arquivo não declara unidade monetária. Valores nominais não foram deflacionados nem usados em comparações de nível. | L59: https://www.argentina.gob.ar/sites/default/files/serie_ron_2003_2025.csv
A60: Argentina | B60: 2020 | C60: 2020 | D60: Resultado financeiro SPN, base caja (2025) | F60: millones de pesos argentinos (ARS) | G60: 1000000 | H60: nota oficial; fechamento anual 2025 | I60: Hacienda/SPN Base Caja | J60: Publicado somente para 2025; anos anteriores não preenchidos nesta observação de fonte | K60: Resultado primário e financeiro do SPN base caixa; perímetro distinto das contas de governo geral IMF. | L60: https://www.argentina.gob.ar/noticias/en-el-ano-2025-el-sector-publico-nacional-registro-un-superavit-financiero-de-1453819
A61: Argentina | B61: 2020 | C61: 2020 | D61: Resultado primário SPN, base caja (2025) | F61: millones de pesos argentinos (ARS) | G61: 1000000 | H61: nota oficial; fechamento anual 2025 | I61: Hacienda/SPN Base Caja | J61: Publicado somente para 2025; anos anteriores não preenchidos nesta observação de fonte | K61: Resultado primário e financeiro do SPN base caixa; perímetro distinto das contas de governo geral IMF. | L61: https://www.argentina.gob.ar/noticias/en-el-ano-2025-el-sector-publico-nacional-registro-un-superavit-financiero-de-1453819
A62: Argentina | B62: 2021 | C62: 2021 | D62: Arrecadação federal total ARCA (TOTAL GENERAL) | E62: 11906731 | F62: millones de pesos argentinos (ARS) | G62: 1000000 | H62: linha 8; coluna TOTAL; cabeçalho: Millones de pesos | I62: Serie anual 2021 | J62: Publicado | K62: Total de tributos, recursos da seguridade social e aduanas; não é receita total de todo o governo. | L62: https://contenidos.afip.gob.ar/institucional/estudios/archivos/serie2021.xls
A63: Argentina | B63: 2021 | C63: 2021 | D63: CPI inflation annual average (%) | E63: 48.4 | F63: Annual percent change | G63: 1 | H63: PCPIPCH | I63: World Economic Outlook (October 2026) | J63: WEO October 2026; latest history/vintage, subject to revision | K63: Indicador PCPIPCH; fonte IMF: World Economic Outlook (October 2026); metadado do endpoint preservado. | L63: https://www.imf.org/external/datamapper/api/v2/PCPIPCH/ARG?periods=2016,2017,2018,2019,2020,2021,2022,2023,2024,2025
A64: Argentina | B64: 2021 | C64: 2021 | D64: GDP nominal current (USD billion) | E64: 486.04 | F64: Billions of U.S. dollars | G64: 1 | H64: NGDPD | I64: World Economic Outlook (October 2026) | J64: WEO October 2026; latest history/vintage, subject to revision | K64: Indicador NGDPD; fonte IMF: World Economic Outlook (October 2026); metadado do endpoint preservado. | L64: https://www.imf.org/external/datamapper/api/v2/NGDPD/ARG?periods=2016,2017,2018,2019,2020,2021,2022,2023,2024,2025
A65: Argentina | B65: 2021 | C65: 2021 | D65: GDP real growth (%) | E65: 10.4 | F65: Annual percent change | G65: 1 | H65: NGDP_RPCH | I65: World Economic Outlook (October 2026) | J65: WEO October 2026; latest history/vintage, subject to revision | K65: Indicador NGDP_RPCH; fonte IMF: World Economic Outlook (October 2026); metadado do endpoint preservado. | L65: https://www.imf.org/external/datamapper/api/v2/NGDP_RPCH/ARG?periods=2016,2017,2018,2019,2020,2021,2022,2023,2024,2025
A66: Argentina | B66: 2021 | C66: 2021 | D66: Government expenditure (% GDP, FPP) | E66: 37.883365 | F66: % of GDP | G66: 1 | H66: exp | I66: Public Finances in Modern History Database (Dec 2025) | J66: FPP Dec 2025; 2025 not published in this series | K66: Indicador exp; fonte IMF: Public Finances in Modern History Database (Dec 2025); metadado do endpoint preservado. | L66: https://www.imf.org/external/datamapper/api/v2/exp/ARG?periods=2016,2017,2018,2019,2020,2021,2022,2023,2024,2025
A67: Argentina | B67: 2021 | C67: 2021 | D67: Gross debt (% GDP) | E67: 81 | F67: Percent of GDP | G67: 1 | H67: GGXWDG_NGDP | I67: World Economic Outlook (October 2026) | J67: WEO October 2026; latest history/vintage, subject to revision | K67: Indicador GGXWDG_NGDP; fonte IMF: World Economic Outlook (October 2026); metadado do endpoint preservado. | L67: https://www.imf.org/external/datamapper/api/v2/GGXWDG_NGDP/ARG?periods=2016,2017,2018,2019,2020,2021,2022,2023,2024,2025
A68: Argentina | B68: 2021 | C68: 2021 | D68: Juros líquidos intra-SPN, base caja (2025) | F68: millones de pesos argentinos (ARS) | G68: 1000000 | H68: nota oficial; fechamento anual 2025 | I68: Hacienda/SPN Base Caja | J68: Publicado somente para 2025; anos anteriores não preenchidos nesta observação de fonte | K68: Resultado primário e financeiro do SPN base caixa; perímetro distinto das contas de governo geral IMF. | L68: https://www.argentina.gob.ar/noticias/en-el-ano-2025-el-sector-publico-nacional-registro-un-superavit-financiero-de-1453819
A69: Argentina | B69: 2021 | C69: 2021 | D69: Net lending/borrowing (% GDP) | E69: -4.332952 | F69: % of GDP | G69: 1 | H69: GGXCNL_G01_GDP_PT | I69: Fiscal Monitor (October 2026) | J69: WEO October 2026; latest history/vintage, subject to revision | K69: Indicador GGXCNL_G01_GDP_PT; fonte IMF: Fiscal Monitor (October 2026); metadado do endpoint preservado. | L69: https://www.imf.org/external/datamapper/api/v2/GGXCNL_G01_GDP_PT/ARG?periods=2016,2017,2018,2019,2020,2021,2022,2023,2024,2025
A70: Argentina | B70: 2021 | C70: 2021 | D70: Population (IMF WEO) | E70: 45.809 | F70: millions of persons | G70: 1000000 | H70: LP | I70: World Economic Outlook (October 2026) | J70: WEO October 2026; latest history/vintage, subject to revision | K70: Indicador LP; fonte IMF: World Economic Outlook (October 2026); metadado do endpoint preservado. | L70: https://www.imf.org/external/datamapper/api/v2/LP/ARG?periods=2016,2017,2018,2019,2020,2021,2022,2023,2024,2025
A71: Argentina | B71: 2021 | C71: 2021 | D71: RON transferências a províncias/CABA (monto publicado) | E71: 6116121.7 | F71: monto conforme CSV; unidade/escala não declarada | H71: soma de monto por ano (27 jurisdições), agregando imposto e regime | I71: ano/provincia/impuesto/regimen/monto | J71: Publicado em unidade reportada; não convertida | K71: RON inclui coparticipação e outros regimes distribuídos; o arquivo não declara unidade monetária. Valores nominais não foram deflacionados nem usados em comparações de nível. | L71: https://www.argentina.gob.ar/sites/default/files/serie_ron_2003_2025.csv
A72: Argentina | B72: 2021 | C72: 2021 | D72: Resultado financeiro SPN, base caja (2025) | F72: millones de pesos argentinos (ARS) | G72: 1000000 | H72: nota oficial; fechamento anual 2025 | I72: Hacienda/SPN Base Caja | J72: Publicado somente para 2025; anos anteriores não preenchidos nesta observação de fonte | K72: Resultado primário e financeiro do SPN base caixa; perímetro distinto das contas de governo geral IMF. | L72: https://www.argentina.gob.ar/noticias/en-el-ano-2025-el-sector-publico-nacional-registro-un-superavit-financiero-de-1453819
A73: Argentina | B73: 2021 | C73: 2021 | D73: Resultado primário SPN, base caja (2025) | F73: millones de pesos argentinos (ARS) | G73: 1000000 | H73: nota oficial; fechamento anual 2025 | I73: Hacienda/SPN Base Caja | J73: Publicado somente para 2025; anos anteriores não preenchidos nesta observação de fonte | K73: Resultado primário e financeiro do SPN base caixa; perímetro distinto das contas de governo geral IMF. | L73: https://www.argentina.gob.ar/noticias/en-el-ano-2025-el-sector-publico-nacional-registro-un-superavit-financiero-de-1453819
A74: Argentina | B74: 2022 | C74: 2022 | D74: Arrecadação federal total ARCA (TOTAL GENERAL) | E74: 21540626 | F74: millones de pesos argentinos (ARS) | G74: 1000000 | H74: linha 8; coluna TOTAL; cabeçalho: Millones de pesos | I74: Serie anual 2022 | J74: Publicado | K74: Total de tributos, recursos da seguridade social e aduanas; não é receita total de todo o governo. | L74: https://contenidos.afip.gob.ar/institucional/estudios/archivos/serie2022.xls
A75: Argentina | B75: 2022 | C75: 2022 | D75: CPI inflation annual average (%) | E75: 72.4 | F75: Annual percent change | G75: 1 | H75: PCPIPCH | I75: World Economic Outlook (October 2026) | J75: WEO October 2026; latest history/vintage, subject to revision | K75: Indicador PCPIPCH; fonte IMF: World Economic Outlook (October 2026); metadado do endpoint preservado. | L75: https://www.imf.org/external/datamapper/api/v2/PCPIPCH/ARG?periods=2016,2017,2018,2019,2020,2021,2022,2023,2024,2025
A76: Argentina | B76: 2022 | C76: 2022 | D76: GDP nominal current (USD billion) | E76: 633.52 | F76: Billions of U.S. dollars | G76: 1 | H76: NGDPD | I76: World Economic Outlook (October 2026) | J76: WEO October 2026; latest history/vintage, subject to revision | K76: Indicador NGDPD; fonte IMF: World Economic Outlook (October 2026); metadado do endpoint preservado. | L76: https://www.imf.org/external/datamapper/api/v2/NGDPD/ARG?periods=2016,2017,2018,2019,2020,2021,2022,2023,2024,2025
A77: Argentina | B77: 2022 | C77: 2022 | D77: GDP real growth (%) | E77: 6 | F77: Annual percent change | G77: 1 | H77: NGDP_RPCH | I77: World Economic Outlook (October 2026) | J77: WEO October 2026; latest history/vintage, subject to revision | K77: Indicador NGDP_RPCH; fonte IMF: World Economic Outlook (October 2026); metadado do endpoint preservado. | L77: https://www.imf.org/external/datamapper/api/v2/NGDP_RPCH/ARG?periods=2016,2017,2018,2019,2020,2021,2022,2023,2024,2025
A78: Argentina | B78: 2022 | C78: 2022 | D78: Government expenditure (% GDP, FPP) | E78: 37.643123 | F78: % of GDP | G78: 1 | H78: exp | I78: Public Finances in Modern History Database (Dec 2025) | J78: FPP Dec 2025; 2025 not published in this series | K78: Indicador exp; fonte IMF: Public Finances in Modern History Database (Dec 2025); metadado do endpoint preservado. | L78: https://www.imf.org/external/datamapper/api/v2/exp/ARG?periods=2016,2017,2018,2019,2020,2021,2022,2023,2024,2025
A79: Argentina | B79: 2022 | C79: 2022 | D79: Gross debt (% GDP) | E79: 84.3 | F79: Percent of GDP | G79: 1 | H79: GGXWDG_NGDP | I79: World Economic Outlook (October 2026) | J79: WEO October 2026; latest history/vintage, subject to revision | K79: Indicador GGXWDG_NGDP; fonte IMF: World Economic Outlook (October 2026); metadado do endpoint preservado. | L79: https://www.imf.org/external/datamapper/api/v2/GGXWDG_NGDP/ARG?periods=2016,2017,2018,2019,2020,2021,2022,2023,2024,2025
A80: Argentina | B80: 2022 | C80: 2022 | D80: Juros líquidos intra-SPN, base caja (2025) | F80: millones de pesos argentinos (ARS) | G80: 1000000 | H80: nota oficial; fechamento anual 2025 | I80: Hacienda/SPN Base Caja | J80: Publicado somente para 2025; anos anteriores não preenchidos nesta observação de fonte | K80: Resultado primário e financeiro do SPN base caixa; perímetro distinto das contas de governo geral IMF. | L80: https://www.argentina.gob.ar/noticias/en-el-ano-2025-el-sector-publico-nacional-registro-un-superavit-financiero-de-1453819
A81: Argentina | B81: 2022 | C81: 2022 | D81: Net lending/borrowing (% GDP) | E81: -3.8363851 | F81: % of GDP | G81: 1 | H81: GGXCNL_G01_GDP_PT | I81: Fiscal Monitor (October 2026) | J81: WEO October 2026; latest history/vintage, subject to revision | K81: Indicador GGXCNL_G01_GDP_PT; fonte IMF: Fiscal Monitor (October 2026); metadado do endpoint preservado. | L81: https://www.imf.org/external/datamapper/api/v2/GGXCNL_G01_GDP_PT/ARG?periods=2016,2017,2018,2019,2020,2021,2022,2023,2024,2025
A82: Argentina | B82: 2022 | C82: 2022 | D82: Population (IMF WEO) | E82: 46.235 | F82: millions of persons | G82: 1000000 | H82: LP | I82: World Economic Outlook (October 2026) | J82: WEO October 2026; latest history/vintage, subject to revision | K82: Indicador LP; fonte IMF: World Economic Outlook (October 2026); metadado do endpoint preservado. | L82: https://www.imf.org/external/datamapper/api/v2/LP/ARG?periods=2016,2017,2018,2019,2020,2021,2022,2023,2024,2025
A83: Argentina | B83: 2022 | C83: 2022 | D83: RON transferências a províncias/CABA (monto publicado) | E83: 11276057 | F83: monto conforme CSV; unidade/escala não declarada | H83: soma de monto por ano (27 jurisdições), agregando imposto e regime | I83: ano/provincia/impuesto/regimen/monto | J83: Publicado em unidade reportada; não convertida | K83: RON inclui coparticipação e outros regimes distribuídos; o arquivo não declara unidade monetária. Valores nominais não foram deflacionados nem usados em comparações de nível. | L83: https://www.argentina.gob.ar/sites/default/files/serie_ron_2003_2025.csv
A84: Argentina | B84: 2022 | C84: 2022 | D84: Resultado financeiro SPN, base caja (2025) | F84: millones de pesos argentinos (ARS) | G84: 1000000 | H84: nota oficial; fechamento anual 2025 | I84: Hacienda/SPN Base Caja | J84: Publicado somente para 2025; anos anteriores não preenchidos nesta observação de fonte | K84: Resultado primário e financeiro do SPN base caixa; perímetro distinto das contas de governo geral IMF. | L84: https://www.argentina.gob.ar/noticias/en-el-ano-2025-el-sector-publico-nacional-registro-un-superavit-financiero-de-1453819
A85: Argentina | B85: 2022 | C85: 2022 | D85: Resultado primário SPN, base caja (2025) | F85: millones de pesos argentinos (ARS) | G85: 1000000 | H85: nota oficial; fechamento anual 2025 | I85: Hacienda/SPN Base Caja | J85: Publicado somente para 2025; anos anteriores não preenchidos nesta observação de fonte | K85: Resultado primário e financeiro do SPN base caixa; perímetro distinto das contas de governo geral IMF. | L85: https://www.argentina.gob.ar/noticias/en-el-ano-2025-el-sector-publico-nacional-registro-un-superavit-financiero-de-1453819
A86: Argentina | B86: 2023 | C86: 2023 | D86: Arrecadação federal total ARCA (TOTAL GENERAL) | E86: 46463191 | F86: millones de pesos argentinos (ARS) | G86: 1000000 | H86: linha 8; coluna TOTAL; cabeçalho: Millones de pesos | I86: Serie anual 2023 | J86: Publicado | K86: Total de tributos, recursos da seguridade social e aduanas; não é receita total de todo o governo. | L86: https://contenidos.afip.gob.ar/institucional/estudios/archivos/serie2023.xls
A87: Argentina | B87: 2023 | C87: 2023 | D87: CPI inflation annual average (%) | E87: 133.5 | F87: Annual percent change | G87: 1 | H87: PCPIPCH | I87: World Economic Outlook (October 2026) | J87: WEO October 2026; latest history/vintage, subject to revision | K87: Indicador PCPIPCH; fonte IMF: World Economic Outlook (October 2026); metadado do endpoint preservado. | L87: https://www.imf.org/external/datamapper/api/v2/PCPIPCH/ARG?periods=2016,2017,2018,2019,2020,2021,2022,2023,2024,2025
A88: Argentina | B88: 2023 | C88: 2023 | D88: GDP nominal current (USD billion) | E88: 654.081 | F88: Billions of U.S. dollars | G88: 1 | H88: NGDPD | I88: World Economic Outlook (October 2026) | J88: WEO October 2026; latest history/vintage, subject to revision | K88: Indicador NGDPD; fonte IMF: World Economic Outlook (October 2026); metadado do endpoint preservado. | L88: https://www.imf.org/external/datamapper/api/v2/NGDPD/ARG?periods=2016,2017,2018,2019,2020,2021,2022,2023,2024,2025
A89: Argentina | B89: 2023 | C89: 2023 | D89: GDP real growth (%) | E89: -1.9 | F89: Annual percent change | G89: 1 | H89: NGDP_RPCH | I89: World Economic Outlook (October 2026) | J89: WEO October 2026; latest history/vintage, subject to revision | K89: Indicador NGDP_RPCH; fonte IMF: World Economic Outlook (October 2026); metadado do endpoint preservado. | L89: https://www.imf.org/external/datamapper/api/v2/NGDP_RPCH/ARG?periods=2016,2017,2018,2019,2020,2021,2022,2023,2024,2025
A90: Argentina | B90: 2023 | C90: 2023 | D90: Government expenditure (% GDP, FPP) | E90: 37.637348 | F90: % of GDP | G90: 1 | H90: exp | I90: Public Finances in Modern History Database (Dec 2025) | J90: FPP Dec 2025; 2025 not published in this series | K90: Indicador exp; fonte IMF: Public Finances in Modern History Database (Dec 2025); metadado do endpoint preservado. | L90: https://www.imf.org/external/datamapper/api/v2/exp/ARG?periods=2016,2017,2018,2019,2020,2021,2022,2023,2024,2025
A91: Argentina | B91: 2023 | C91: 2023 | D91: Gross debt (% GDP) | E91: 153.4 | F91: Percent of GDP | G91: 1 | H91: GGXWDG_NGDP | I91: World Economic Outlook (October 2026) | J91: WEO October 2026; latest history/vintage, subject to revision | K91: Indicador GGXWDG_NGDP; fonte IMF: World Economic Outlook (October 2026); metadado do endpoint preservado. | L91: https://www.imf.org/external/datamapper/api/v2/GGXWDG_NGDP/ARG?periods=2016,2017,2018,2019,2020,2021,2022,2023,2024,2025
A92: Argentina | B92: 2023 | C92: 2023 | D92: Juros líquidos intra-SPN, base caja (2025) | F92: millones de pesos argentinos (ARS) | G92: 1000000 | H92: nota oficial; fechamento anual 2025 | I92: Hacienda/SPN Base Caja | J92: Publicado somente para 2025; anos anteriores não preenchidos nesta observação de fonte | K92: Resultado primário e financeiro do SPN base caixa; perímetro distinto das contas de governo geral IMF. | L92: https://www.argentina.gob.ar/noticias/en-el-ano-2025-el-sector-publico-nacional-registro-un-superavit-financiero-de-1453819
A93: Argentina | B93: 2023 | C93: 2023 | D93: Net lending/borrowing (% GDP) | E93: -5.2809834 | F93: % of GDP | G93: 1 | H93: GGXCNL_G01_GDP_PT | I93: Fiscal Monitor (October 2026) | J93: WEO October 2026; latest history/vintage, subject to revision | K93: Indicador GGXCNL_G01_GDP_PT; fonte IMF: Fiscal Monitor (October 2026); metadado do endpoint preservado. | L93: https://www.imf.org/external/datamapper/api/v2/GGXCNL_G01_GDP_PT/ARG?periods=2016,2017,2018,2019,2020,2021,2022,2023,2024,2025
A94: Argentina | B94: 2023 | C94: 2023 | D94: Population (IMF WEO) | E94: 46.655 | F94: millions of persons | G94: 1000000 | H94: LP | I94: World Economic Outlook (October 2026) | J94: WEO October 2026; latest history/vintage, subject to revision | K94: Indicador LP; fonte IMF: World Economic Outlook (October 2026); metadado do endpoint preservado. | L94: https://www.imf.org/external/datamapper/api/v2/LP/ARG?periods=2016,2017,2018,2019,2020,2021,2022,2023,2024,2025
A95: Argentina | B95: 2023 | C95: 2023 | D95: RON transferências a províncias/CABA (monto publicado) | E95: 25030205 | F95: monto conforme CSV; unidade/escala não declarada | H95: soma de monto por ano (27 jurisdições), agregando imposto e regime | I95: ano/provincia/impuesto/regimen/monto | J95: Publicado em unidade reportada; não convertida | K95: RON inclui coparticipação e outros regimes distribuídos; o arquivo não declara unidade monetária. Valores nominais não foram deflacionados nem usados em comparações de nível. | L95: https://www.argentina.gob.ar/sites/default/files/serie_ron_2003_2025.csv
A96: Argentina | B96: 2023 | C96: 2023 | D96: Resultado financeiro SPN, base caja (2025) | F96: millones de pesos argentinos (ARS) | G96: 1000000 | H96: nota oficial; fechamento anual 2025 | I96: Hacienda/SPN Base Caja | J96: Publicado somente para 2025; anos anteriores não preenchidos nesta observação de fonte | K96: Resultado primário e financeiro do SPN base caixa; perímetro distinto das contas de governo geral IMF. | L96: https://www.argentina.gob.ar/noticias/en-el-ano-2025-el-sector-publico-nacional-registro-un-superavit-financiero-de-1453819
A97: Argentina | B97: 2023 | C97: 2023 | D97: Resultado primário SPN, base caja (2025) | F97: millones de pesos argentinos (ARS) | G97: 1000000 | H97: nota oficial; fechamento anual 2025 | I97: Hacienda/SPN Base Caja | J97: Publicado somente para 2025; anos anteriores não preenchidos nesta observação de fonte | K97: Resultado primário e financeiro do SPN base caixa; perímetro distinto das contas de governo geral IMF. | L97: https://www.argentina.gob.ar/noticias/en-el-ano-2025-el-sector-publico-nacional-registro-un-superavit-financiero-de-1453819
A98: Argentina | B98: 2024 | C98: 2024 | D98: Arrecadação federal total ARCA (TOTAL GENERAL) | E98: 1.4203145e+08 | F98: millones de pesos argentinos (ARS) | G98: 1000000 | H98: linha 8; coluna TOTAL; cabeçalho: Millones de pesos | I98: Serie anual 2024 | J98: Publicado | K98: Total de tributos, recursos da seguridade social e aduanas; não é receita total de todo o governo. | L98: https://contenidos.afip.gob.ar/institucional/estudios/archivos/serie2024.xls
A99: Argentina | B99: 2024 | C99: 2024 | D99: CPI inflation annual average (%) | E99: 219.9 | F99: Annual percent change | G99: 1 | H99: PCPIPCH | I99: World Economic Outlook (October 2026) | J99: WEO October 2026; latest history/vintage, subject to revision | K99: Indicador PCPIPCH; fonte IMF: World Economic Outlook (October 2026); metadado do endpoint preservado. | L99: https://www.imf.org/external/datamapper/api/v2/PCPIPCH/ARG?periods=2016,2017,2018,2019,2020,2021,2022,2023,2024,2025
A100: Argentina | B100: 2024 | C100: 2024 | D100: GDP nominal current (USD billion) | E100: 637.744 | F100: Billions of U.S. dollars | G100: 1 | H100: NGDPD | I100: World Economic Outlook (October 2026) | J100: WEO October 2026; latest history/vintage, subject to revision | K100: Indicador NGDPD; fonte IMF: World Economic Outlook (October 2026); metadado do endpoint preservado. | L100: https://www.imf.org/external/datamapper/api/v2/NGDPD/ARG?periods=2016,2017,2018,2019,2020,2021,2022,2023,2024,2025
...

Sheet Deflatores
A1: País/território | B1: Ano | C1: Índice de preços usado | D1: Inflação média anual (%) | E1: Fator para preços 2025 | F1: Ano-base | G1: Fonte e regra
A2: Brasil | B2: 2014 | C2: 3953.1533 | E2: =IFERROR($C$13/C2,"") -> 1.84684 | F2: 2025 | G2: Média dos 12 números-índice mensais do IPCA; base 2025.
A3: Brasil | B3: 2015 | C3: 4310.1192 | E3: =IFERROR($C$13/C3,"") -> 1.6938839 | F3: 2025 | G3: Média dos 12 números-índice mensais do IPCA; base 2025.
A4: Brasil | B4: 2016 | C4: 4686.7867 | E4: =IFERROR($C$13/C4,"") -> 1.5577499 | F4: 2025 | G4: Média dos 12 números-índice mensais do IPCA; base 2025.
A5: Brasil | B5: 2017 | C5: 4848.3108 | E5: =IFERROR($C$13/C5,"") -> 1.5058526 | F5: 2025 | G5: Média dos 12 números-índice mensais do IPCA; base 2025.
A6: Brasil | B6: 2018 | C6: 5025.9942 | E6: =IFERROR($C$13/C6,"") -> 1.4526164 | F6: 2025 | G6: Média dos 12 números-índice mensais do IPCA; base 2025.
A7: Brasil | B7: 2019 | C7: 5213.6133 | E7: =IFERROR($C$13/C7,"") -> 1.400342 | F7: 2025 | G7: Média dos 12 números-índice mensais do IPCA; base 2025.
A8: Brasil | B8: 2020 | C8: 5381.0625 | E8: =IFERROR($C$13/C8,"") -> 1.3567658 | F8: 2025 | G8: Média dos 12 números-índice mensais do IPCA; base 2025.
A9: Brasil | B9: 2021 | C9: 5827.78 | E9: =IFERROR($C$13/C9,"") -> 1.2527655 | F9: 2025 | G9: Média dos 12 números-índice mensais do IPCA; base 2025.
A10: Brasil | B10: 2022 | C10: 6368.6042 | E10: =IFERROR($C$13/C10,"") -> 1.1463802 | F10: 2025 | G10: Média dos 12 números-índice mensais do IPCA; base 2025.
A11: Brasil | B11: 2023 | C11: 6661.15 | E11: =IFERROR($C$13/C11,"") -> 1.0960332 | F11: 2025 | G11: Média dos 12 números-índice mensais do IPCA; base 2025.
A12: Brasil | B12: 2024 | C12: 6952.0733 | E12: =IFERROR($C$13/C12,"") -> 1.0501675 | F12: 2025 | G12: Média dos 12 números-índice mensais do IPCA; base 2025.
A13: Brasil | B13: 2025 | C13: 7300.8417 | E13: =IFERROR($C$13/C13,"") -> 1 | F13: 2025 | G13: Média dos 12 números-índice mensais do IPCA; base 2025.
A14: Argentina | B14: 2016 | C14: 100 | E14: =IFERROR($C$23/C14,"") -> 99.784411 | F14: 2025 | G14: Índice relativo: CPI médio 2016=100; encadeado pelas taxas de inflação média anual WEO.
A15: Argentina | B15: 2017 | C15: =IF(OR(D15="",C14=""),"",C14*(1+D15/100)) -> 125.7 | D15: 25.7 | E15: =IFERROR($C$23/C15,"") -> 79.382984 | F15: 2025 | G15: Índice relativo: CPI médio 2016=100; encadeado pelas taxas de inflação média anual WEO.
A16: Argentina | B16: 2018 | C16: =IF(OR(D16="",C15=""),"",C15*(1+D16/100)) -> 168.8151 | D16: 34.3 | E16: =IFERROR($C$23/C16,"") -> 59.1087 | F16: 2025 | G16: Índice relativo: CPI médio 2016=100; encadeado pelas taxas de inflação média anual WEO.
A17: Argentina | B17: 2019 | C17: =IF(OR(D17="",C16=""),"",C16*(1+D17/100)) -> 259.13118 | D17: 53.5 | E17: =IFERROR($C$23/C17,"") -> 38.507296 | F17: 2025 | G17: Índice relativo: CPI médio 2016=100; encadeado pelas taxas de inflação média anual WEO.
A18: Argentina | B18: 2020 | C18: =IF(OR(D18="",C17=""),"",C17*(1+D18/100)) -> 367.96627 | D18: 42 | E18: =IFERROR($C$23/C18,"") -> 27.117814 | F18: 2025 | G18: Índice relativo: CPI médio 2016=100; encadeado pelas taxas de inflação média anual WEO.
A19: Argentina | B19: 2021 | C19: =IF(OR(D19="",C18=""),"",C18*(1+D19/100)) -> 546.06195 | D19: 48.4 | E19: =IFERROR($C$23/C19,"") -> 18.27346 | F19: 2025 | G19: Índice relativo: CPI médio 2016=100; encadeado pelas taxas de inflação média anual WEO.
A20: Argentina | B20: 2022 | C20: =IF(OR(D20="",C19=""),"",C19*(1+D20/100)) -> 941.4108 | D20: 72.4 | E20: =IFERROR($C$23/C20,"") -> 10.599455 | F20: 2025 | G20: Índice relativo: CPI médio 2016=100; encadeado pelas taxas de inflação média anual WEO.
A21: Argentina | B21: 2023 | C21: =IF(OR(D21="",C20=""),"",C20*(1+D21/100)) -> 2198.1942 | D21: 133.5 | E21: =IFERROR($C$23/C21,"") -> 4.539381 | F21: 2025 | G21: Índice relativo: CPI médio 2016=100; encadeado pelas taxas de inflação média anual WEO.
A22: Argentina | B22: 2024 | C22: =IF(OR(D22="",C21=""),"",C21*(1+D22/100)) -> 7032.0233 | D22: 219.9 | E22: =IFERROR($C$23/C22,"") -> 1.419 | F22: 2025 | G22: Índice relativo: CPI médio 2016=100; encadeado pelas taxas de inflação média anual WEO.
A23: Argentina | B23: 2025 | C23: =IF(OR(D23="",C22=""),"",C22*(1+D23/100)) -> 9978.4411 | D23: 41.9 | E23: =IFERROR($C$23/C23,"") -> 1 | F23: 2025 | G23: Índice relativo: CPI médio 2016=100; encadeado pelas taxas de inflação média anual WEO.

Sheet Dados tratados
A1: Entidade | B1: Ano | C1: Variável | D1: Valor bruto/entrada (fórmula) | E1: Valor nominal em unidade padrão | F1: Fator deflator p/2025 | G1: Valor real/preços 2025 | H1: População usada (pessoas) | I1: Valor real per capita | J1: Indicador/valor não monetário | K1: Unidade de análise | L1: Status/tratamento | M1: URL da fonte | N1: Fórmula/transformação
A2: Argentina | B2: 2016 | C2: Arrecadação federal total ARCA (TOTAL GENERAL) | D2: =IF('Dados brutos atualizados'!E2="","",'Dados brutos atualizados'!E2) -> 2.2730474e+09 | E2: =IF(D2="","",D2*'Dados brutos atualizados'!G2) -> 2.2730474e+12 | F2: =IF(E2="","",Deflatores!E14) -> 99.784411 | G2: =IF(OR(E2="",F2=""),"",E2*F2) -> 2.268147e+14 | H2: =IF('Dados tratados'!E10="","",'Dados tratados'!E10) -> 43590000 | I2: =IF(OR(G2="",H2="",H2=0),"",G2/H2) -> 5203365.4 | K2: mil pesos argentinos (ARS) | L2: Publicado | M2: https://contenidos.afip.gob.ar/institucional/estudios/archivos/serie2016.xls | N2: Total de tributos, recursos da seguridade social e aduanas; não é receita total de todo o governo.
A3: Argentina | B3: 2016 | C3: CPI inflation annual average (%) | D3: =IF('Dados brutos atualizados'!E3="","",'Dados brutos atualizados'!E3) | E3: =IF(D3="","",D3*'Dados brutos atualizados'!G3) | J3: =IF(D3="","",D3) | K3: Annual percent change | L3: Sem dado no endpoint/vintage; mantido ausente | M3: https://www.imf.org/external/datamapper/api/v2/PCPIPCH/ARG?periods=2016,2017,2018,2019,2020,2021,2022,2023,2024,2025 | N3: Indicador PCPIPCH; fonte IMF: World Economic Outlook (October 2026); metadado do endpoint preservado.
A4: Argentina | B4: 2016 | C4: GDP nominal current (USD billion) | D4: =IF('Dados brutos atualizados'!E4="","",'Dados brutos atualizados'!E4) -> 556.774 | E4: =IF(D4="","",D4*'Dados brutos atualizados'!G4) -> 556.774 | J4: =IF(D4="","",D4) -> 556.774 | K4: Billions of U.S. dollars | L4: WEO October 2026; latest history/vintage, subject to revision | M4: https://www.imf.org/external/datamapper/api/v2/NGDPD/ARG?periods=2016,2017,2018,2019,2020,2021,2022,2023,2024,2025 | N4: Indicador NGDPD; fonte IMF: World Economic Outlook (October 2026); metadado do endpoint preservado.
A5: Argentina | B5: 2016 | C5: GDP real growth (%) | D5: =IF('Dados brutos atualizados'!E5="","",'Dados brutos atualizados'!E5) -> -2.1 | E5: =IF(D5="","",D5*'Dados brutos atualizados'!G5) -> -2.1 | J5: =IF(D5="","",D5) -> -2.1 | K5: Annual percent change | L5: WEO October 2026; latest history/vintage, subject to revision | M5: https://www.imf.org/external/datamapper/api/v2/NGDP_RPCH/ARG?periods=2016,2017,2018,2019,2020,2021,2022,2023,2024,2025 | N5: Indicador NGDP_RPCH; fonte IMF: World Economic Outlook (October 2026); metadado do endpoint preservado.
A6: Argentina | B6: 2016 | C6: Government expenditure (% GDP, FPP) | D6: =IF('Dados brutos atualizados'!E6="","",'Dados brutos atualizados'!E6) -> 41.522021 | E6: =IF(D6="","",D6*'Dados brutos atualizados'!G6) -> 41.522021 | J6: =IF(D6="","",D6) -> 41.522021 | K6: % of GDP | L6: FPP Dec 2025; 2025 not published in this series | M6: https://www.imf.org/external/datamapper/api/v2/exp/ARG?periods=2016,2017,2018,2019,2020,2021,2022,2023,2024,2025 | N6: Indicador exp; fonte IMF: Public Finances in Modern History Database (Dec 2025); metadado do endpoint preservado.
A7: Argentina | B7: 2016 | C7: Gross debt (% GDP) | D7: =IF('Dados brutos atualizados'!E7="","",'Dados brutos atualizados'!E7) -> 53.1 | E7: =IF(D7="","",D7*'Dados brutos atualizados'!G7) -> 53.1 | J7: =IF(D7="","",D7) -> 53.1 | K7: Percent of GDP | L7: WEO October 2026; latest history/vintage, subject to revision | M7: https://www.imf.org/external/datamapper/api/v2/GGXWDG_NGDP/ARG?periods=2016,2017,2018,2019,2020,2021,2022,2023,2024,2025 | N7: Indicador GGXWDG_NGDP; fonte IMF: World Economic Outlook (October 2026); metadado do endpoint preservado.
A8: Argentina | B8: 2016 | C8: Juros líquidos intra-SPN, base caja (2025) | D8: =IF('Dados brutos atualizados'!E8="","",'Dados brutos atualizados'!E8) | E8: =IF(D8="","",D8*'Dados brutos atualizados'!G8) | F8: =IF(E8="","",Deflatores!E14) | G8: =IF(OR(E8="",F8=""),"",E8*F8) | H8: =IF('Dados tratados'!E10="","",'Dados tratados'!E10) -> 43590000 | I8: =IF(OR(G8="",H8="",H8=0),"",G8/H8) | K8: millones de pesos argentinos (ARS) | L8: Publicado somente para 2025; anos anteriores não preenchidos nesta observação de fonte | M8: https://www.argentina.gob.ar/noticias/en-el-ano-2025-el-sector-publico-nacional-registro-un-superavit-financiero-de-1453819 | N8: Resultado primário e financeiro do SPN base caixa; perímetro distinto das contas de governo geral IMF.
A9: Argentina | B9: 2016 | C9: Net lending/borrowing (% GDP) | D9: =IF('Dados brutos atualizados'!E9="","",'Dados brutos atualizados'!E9) -> -6.654669 | E9: =IF(D9="","",D9*'Dados brutos atualizados'!G9) -> -6.654669 | J9: =IF(D9="","",D9) -> -6.654669 | K9: % of GDP | L9: WEO October 2026; latest history/vintage, subject to revision | M9: https://www.imf.org/external/datamapper/api/v2/GGXCNL_G01_GDP_PT/ARG?periods=2016,2017,2018,2019,2020,2021,2022,2023,2024,2025 | N9: Indicador GGXCNL_G01_GDP_PT; fonte IMF: Fiscal Monitor (October 2026); metadado do endpoint preservado.
A10: Argentina | B10: 2016 | C10: Population (IMF WEO) | D10: =IF('Dados brutos atualizados'!E10="","",'Dados brutos atualizados'!E10) -> 43.59 | E10: =IF(D10="","",D10*'Dados brutos atualizados'!G10) -> 43590000 | J10: =IF(D10="","",D10) -> 43.59 | K10: millions of persons | L10: WEO October 2026; latest history/vintage, subject to revision | M10: https://www.imf.org/external/datamapper/api/v2/LP/ARG?periods=2016,2017,2018,2019,2020,2021,2022,2023,2024,2025 | N10: Indicador LP; fonte IMF: World Economic Outlook (October 2026); metadado do endpoint preservado.
A11: Argentina | B11: 2016 | C11: RON transferências a províncias/CABA (monto publicado) | D11: =IF('Dados brutos atualizados'!E11="","",'Dados brutos atualizados'!E11) -> 1120751.4 | J11: =IF(D11="","",D11) -> 1120751.4 | K11: monto conforme CSV; unidade/escala não declarada | L11: Publicado em unidade reportada; não convertida | M11: https://www.argentina.gob.ar/sites/default/files/serie_ron_2003_2025.csv | N11: RON inclui coparticipação e outros regimes distribuídos; o arquivo não declara unidade monetária. Valores nominais não foram deflacionados nem usados em comparações de nível.
A12: Argentina | B12: 2016 | C12: Resultado financeiro SPN, base caja (2025) | D12: =IF('Dados brutos atualizados'!E12="","",'Dados brutos atualizados'!E12) | E12: =IF(D12="","",D12*'Dados brutos atualizados'!G12) | F12: =IF(E12="","",Deflatores!E14) | G12: =IF(OR(E12="",F12=""),"",E12*F12) | H12: =IF('Dados tratados'!E10="","",'Dados tratados'!E10) -> 43590000 | I12: =IF(OR(G12="",H12="",H12=0),"",G12/H12) | K12: millones de pesos argentinos (ARS) | L12: Publicado somente para 2025; anos anteriores não preenchidos nesta observação de fonte | M12: https://www.argentina.gob.ar/noticias/en-el-ano-2025-el-sector-publico-nacional-registro-un-superavit-financiero-de-1453819 | N12: Resultado primário e financeiro do SPN base caixa; perímetro distinto das contas de governo geral IMF.
A13: Argentina | B13: 2016 | C13: Resultado primário SPN, base caja (2025) | D13: =IF('Dados brutos atualizados'!E13="","",'Dados brutos atualizados'!E13) | E13: =IF(D13="","",D13*'Dados brutos atualizados'!G13) | F13: =IF(E13="","",Deflatores!E14) | G13: =IF(OR(E13="",F13=""),"",E13*F13) | H13: =IF('Dados tratados'!E10="","",'Dados tratados'!E10) -> 43590000 | I13: =IF(OR(G13="",H13="",H13=0),"",G13/H13) | K13: millones de pesos argentinos (ARS) | L13: Publicado somente para 2025; anos anteriores não preenchidos nesta observação de fonte | M13: https://www.argentina.gob.ar/noticias/en-el-ano-2025-el-sector-publico-nacional-registro-un-superavit-financiero-de-1453819 | N13: Resultado primário e financeiro do SPN base caixa; perímetro distinto das contas de governo geral IMF.
A14: Argentina | B14: 2017 | C14: Arrecadação federal total ARCA (TOTAL GENERAL) | D14: =IF('Dados brutos atualizados'!E14="","",'Dados brutos atualizados'!E14) -> 2.8422167e+09 | E14: =IF(D14="","",D14*'Dados brutos atualizados'!G14) -> 2.8422167e+12 | F14: =IF(E14="","",Deflatores!E15) -> 79.382984 | G14: =IF(OR(E14="",F14=""),"",E14*F14) -> 2.2562365e+14 | H14: =IF('Dados tratados'!E22="","",'Dados tratados'!E22) -> 44045000 | I14: =IF(OR(G14="",H14="",H14=0),"",G14/H14) -> 5122571.1 | K14: mil pesos argentinos (ARS) | L14: Publicado | M14: https://contenidos.afip.gob.ar/institucional/estudios/archivos/serie2017.xls | N14: Total de tributos, recursos da seguridade social e aduanas; não é receita total de todo o governo.
A15: Argentina | B15: 2017 | C15: CPI inflation annual average (%) | D15: =IF('Dados brutos atualizados'!E15="","",'Dados brutos atualizados'!E15) -> 25.7 | E15: =IF(D15="","",D15*'Dados brutos atualizados'!G15) -> 25.7 | J15: =IF(D15="","",D15) -> 25.7 | K15: Annual percent change | L15: WEO October 2026; latest history/vintage, subject to revision | M15: https://www.imf.org/external/datamapper/api/v2/PCPIPCH/ARG?periods=2016,2017,2018,2019,2020,2021,2022,2023,2024,2025 | N15: Indicador PCPIPCH; fonte IMF: World Economic Outlook (October 2026); metadado do endpoint preservado.
A16: Argentina | B16: 2017 | C16: GDP nominal current (USD billion) | D16: =IF('Dados brutos atualizados'!E16="","",'Dados brutos atualizados'!E16) -> 643.861 | E16: =IF(D16="","",D16*'Dados brutos atualizados'!G16) -> 643.861 | J16: =IF(D16="","",D16) -> 643.861 | K16: Billions of U.S. dollars | L16: WEO October 2026; latest history/vintage, subject to revision | M16: https://www.imf.org/external/datamapper/api/v2/NGDPD/ARG?periods=2016,2017,2018,2019,2020,2021,2022,2023,2024,2025 | N16: Indicador NGDPD; fonte IMF: World Economic Outlook (October 2026); metadado do endpoint preservado.
A17: Argentina | B17: 2017 | C17: GDP real growth (%) | D17: =IF('Dados brutos atualizados'!E17="","",'Dados brutos atualizados'!E17) -> 2.8 | E17: =IF(D17="","",D17*'Dados brutos atualizados'!G17) -> 2.8 | J17: =IF(D17="","",D17) -> 2.8 | K17: Annual percent change | L17: WEO October 2026; latest history/vintage, subject to revision | M17: https://www.imf.org/external/datamapper/api/v2/NGDP_RPCH/ARG?periods=2016,2017,2018,2019,2020,2021,2022,2023,2024,2025 | N17: Indicador NGDP_RPCH; fonte IMF: World Economic Outlook (October 2026); metadado do endpoint preservado.
A18: Argentina | B18: 2017 | C18: Government expenditure (% GDP, FPP) | D18: =IF('Dados brutos atualizados'!E18="","",'Dados brutos atualizados'!E18) -> 41.121454 | E18: =IF(D18="","",D18*'Dados brutos atualizados'!G18) -> 41.121454 | J18: =IF(D18="","",D18) -> 41.121454 | K18: % of GDP | L18: FPP Dec 2025; 2025 not published in this series | M18: https://www.imf.org/external/datamapper/api/v2/exp/ARG?periods=2016,2017,2018,2019,2020,2021,2022,2023,2024,2025 | N18: Indicador exp; fonte IMF: Public Finances in Modern History Database (Dec 2025); metadado do endpoint preservado.
A19: Argentina | B19: 2017 | C19: Gross debt (% GDP) | D19: =IF('Dados brutos atualizados'!E19="","",'Dados brutos atualizados'!E19) -> 57 | E19: =IF(D19="","",D19*'Dados brutos atualizados'!G19) -> 57 | J19: =IF(D19="","",D19) -> 57 | K19: Percent of GDP | L19: WEO October 2026; latest history/vintage, subject to revision | M19: https://www.imf.org/external/datamapper/api/v2/GGXWDG_NGDP/ARG?periods=2016,2017,2018,2019,2020,2021,2022,2023,2024,2025 | N19: Indicador GGXWDG_NGDP; fonte IMF: World Economic Outlook (October 2026); metadado do endpoint preservado.
A20: Argentina | B20: 2017 | C20: Juros líquidos intra-SPN, base caja (2025) | D20: =IF('Dados brutos atualizados'!E20="","",'Dados brutos atualizados'!E20) | E20: =IF(D20="","",D20*'Dados brutos atualizados'!G20) | F20: =IF(E20="","",Deflatores!E15) | G20: =IF(OR(E20="",F20=""),"",E20*F20) | H20: =IF('Dados tratados'!E22="","",'Dados tratados'!E22) -> 44045000 | I20: =IF(OR(G20="",H20="",H20=0),"",G20/H20) | K20: millones de pesos argentinos (ARS) | L20: Publicado somente para 2025; anos anteriores não preenchidos nesta observação de fonte | M20: https://www.argentina.gob.ar/noticias/en-el-ano-2025-el-sector-publico-nacional-registro-un-superavit-financiero-de-1453819 | N20: Resultado primário e financeiro do SPN base caixa; perímetro distinto das contas de governo geral IMF.
A21: Argentina | B21: 2017 | C21: Net lending/borrowing (% GDP) | D21: =IF('Dados brutos atualizados'!E21="","",'Dados brutos atualizados'!E21) -> -6.6933411 | E21: =IF(D21="","",D21*'Dados brutos atualizados'!G21) -> -6.6933411 | J21: =IF(D21="","",D21) -> -6.6933411 | K21: % of GDP | L21: WEO October 2026; latest history/vintage, subject to revision | M21: https://www.imf.org/external/datamapper/api/v2/GGXCNL_G01_GDP_PT/ARG?periods=2016,2017,2018,2019,2020,2021,2022,2023,2024,2025 | N21: Indicador GGXCNL_G01_GDP_PT; fonte IMF: Fiscal Monitor (October 2026); metadado do endpoint preservado.
A22: Argentina | B22: 2017 | C22: Population (IMF WEO) | D22: =IF('Dados brutos atualizados'!E22="","",'Dados brutos atualizados'!E22) -> 44.045 | E22: =IF(D22="","",D22*'Dados brutos atualizados'!G22) -> 44045000 | J22: =IF(D22="","",D22) -> 44.045 | K22: millions of persons | L22: WEO October 2026; latest history/vintage, subject to revision | M22: https://www.imf.org/external/datamapper/api/v2/LP/ARG?periods=2016,2017,2018,2019,2020,2021,2022,2023,2024,2025 | N22: Indicador LP; fonte IMF: World Economic Outlook (October 2026); metadado do endpoint preservado.
A23: Argentina | B23: 2017 | C23: RON transferências a províncias/CABA (monto publicado) | D23: =IF('Dados brutos atualizados'!E23="","",'Dados brutos atualizados'!E23) -> 1457199.8 | J23: =IF(D23="","",D23) -> 1457199.8 | K23: monto conforme CSV; unidade/escala não declarada | L23: Publicado em unidade reportada; não convertida | M23: https://www.argentina.gob.ar/sites/default/files/serie_ron_2003_2025.csv | N23: RON inclui coparticipação e outros regimes distribuídos; o arquivo não declara unidade monetária. Valores nominais não foram deflacionados nem usados em comparações de nível.
A24: Argentina | B24: 2017 | C24: Resultado financeiro SPN, base caja (2025) | D24: =IF('Dados brutos atualizados'!E24="","",'Dados brutos atualizados'!E24) | E24: =IF(D24="","",D24*'Dados brutos atualizados'!G24) | F24: =IF(E24="","",Deflatores!E15) | G24: =IF(OR(E24="",F24=""),"",E24*F24) | H24: =IF('Dados tratados'!E22="","",'Dados tratados'!E22) -> 44045000 | I24: =IF(OR(G24="",H24="",H24=0),"",G24/H24) | K24: millones de pesos argentinos (ARS) | L24: Publicado somente para 2025; anos anteriores não preenchidos nesta observação de fonte | M24: https://www.argentina.gob.ar/noticias/en-el-ano-2025-el-sector-publico-nacional-registro-un-superavit-financiero-de-1453819 | N24: Resultado primário e financeiro do SPN base caixa; perímetro distinto das contas de governo geral IMF.
A25: Argentina | B25: 2017 | C25: Resultado primário SPN, base caja (2025) | D25: =IF('Dados brutos atualizados'!E25="","",'Dados brutos atualizados'!E25) | E25: =IF(D25="","",D25*'Dados brutos atualizados'!G25) | F25: =IF(E25="","",Deflatores!E15) | G25: =IF(OR(E25="",F25=""),"",E25*F25) | H25: =IF('Dados tratados'!E22="","",'Dados tratados'!E22) -> 44045000 | I25: =IF(OR(G25="",H25="",H25=0),"",G25/H25) | K25: millones de pesos argentinos (ARS) | L25: Publicado somente para 2025; anos anteriores não preenchidos nesta observação de fonte | M25: https://www.argentina.gob.ar/noticias/en-el-ano-2025-el-sector-publico-nacional-registro-un-superavit-financiero-de-1453819 | N25: Resultado primário e financeiro do SPN base caixa; perímetro distinto das contas de governo geral IMF.
A26: Argentina | B26: 2018 | C26: Arrecadação federal total ARCA (TOTAL GENERAL) | D26: =IF('Dados brutos atualizados'!E26="","",'Dados brutos atualizados'!E26) -> 3.7134091e+09 | E26: =IF(D26="","",D26*'Dados brutos atualizados'!G26) -> 3.7134091e+12 | F26: =IF(E26="","",Deflatores!E16) -> 59.1087 | G26: =IF(OR(E26="",F26=""),"",E26*F26) -> 219494786934247 | H26: =IF('Dados tratados'!E34="","",'Dados tratados'!E34) -> 44495000 | I26: =IF(OR(G26="",H26="",H26=0),"",G26/H26) -> 4933021.4 | K26: mil pesos argentinos (ARS) | L26: Publicado | M26: https://contenidos.afip.gob.ar/institucional/estudios/archivos/serie2018.xls | N26: Total de tributos, recursos da seguridade social e aduanas; não é receita total de todo o governo.
A27: Argentina | B27: 2018 | C27: CPI inflation annual average (%) | D27: =IF('Dados brutos atualizados'!E27="","",'Dados brutos atualizados'!E27) -> 34.3 | E27: =IF(D27="","",D27*'Dados brutos atualizados'!G27) -> 34.3 | J27: =IF(D27="","",D27) -> 34.3 | K27: Annual percent change | L27: WEO October 2026; latest history/vintage, subject to revision | M27: https://www.imf.org/external/datamapper/api/v2/PCPIPCH/ARG?periods=2016,2017,2018,2019,2020,2021,2022,2023,2024,2025 | N27: Indicador PCPIPCH; fonte IMF: World Economic Outlook (October 2026); metadado do endpoint preservado.
A28: Argentina | B28: 2018 | C28: GDP nominal current (USD billion) | D28: =IF('Dados brutos atualizados'!E28="","",'Dados brutos atualizados'!E28) -> 524.431 | E28: =IF(D28="","",D28*'Dados brutos atualizados'!G28) -> 524.431 | J28: =IF(D28="","",D28) -> 524.431 | K28: Billions of U.S. dollars | L28: WEO October 2026; latest history/vintage, subject to revision | M28: https://www.imf.org/external/datamapper/api/v2/NGDPD/ARG?periods=2016,2017,2018,2019,2020,2021,2022,2023,2024,2025 | N28: Indicador NGDPD; fonte IMF: World Economic Outlook (October 2026); metadado do endpoint preservado.
A29: Argentina | B29: 2018 | C29: GDP real growth (%) | D29: =IF('Dados brutos atualizados'!E29="","",'Dados brutos atualizados'!E29) -> -2.6 | E29: =IF(D29="","",D29*'Dados brutos atualizados'!G29) -> -2.6 | J29: =IF(D29="","",D29) -> -2.6 | K29: Annual percent change | L29: WEO October 2026; latest history/vintage, subject to revision | M29: https://www.imf.org/external/datamapper/api/v2/NGDP_RPCH/ARG?periods=2016,2017,2018,2019,2020,2021,2022,2023,2024,2025 | N29: Indicador NGDP_RPCH; fonte IMF: World Economic Outlook (October 2026); metadado do endpoint preservado.
A30: Argentina | B30: 2018 | C30: Government expenditure (% GDP, FPP) | D30: =IF('Dados brutos atualizados'!E30="","",'Dados brutos atualizados'!E30) -> 38.949208 | E30: =IF(D30="","",D30*'Dados brutos atualizados'!G30) -> 38.949208 | J30: =IF(D30="","",D30) -> 38.949208 | K30: % of GDP | L30: FPP Dec 2025; 2025 not published in this series | M30: https://www.imf.org/external/datamapper/api/v2/exp/ARG?periods=2016,2017,2018,2019,2020,2021,2022,2023,2024,2025 | N30: Indicador exp; fonte IMF: Public Finances in Modern History Database (Dec 2025); metadado do endpoint preservado.
A31: Argentina | B31: 2018 | C31: Gross debt (% GDP) | D31: =IF('Dados brutos atualizados'!E31="","",'Dados brutos atualizados'!E31) -> 85.2 | E31: =IF(D31="","",D31*'Dados brutos atualizados'!G31) -> 85.2 | J31: =IF(D31="","",D31) -> 85.2 | K31: Percent of GDP | L31: WEO October 2026; latest history/vintage, subject to revision | M31: https://www.imf.org/external/datamapper/api/v2/GGXWDG_NGDP/ARG?periods=2016,2017,2018,2019,2020,2021,2022,2023,2024,2025 | N31: Indicador GGXWDG_NGDP; fonte IMF: World Economic Outlook (October 2026); metadado do endpoint preservado.
A32: Argentina | B32: 2018 | C32: Juros líquidos intra-SPN, base caja (2025) | D32: =IF('Dados brutos atualizados'!E32="","",'Dados brutos atualizados'!E32) | E32: =IF(D32="","",D32*'Dados brutos atualizados'!G32) | F32: =IF(E32="","",Deflatores!E16) | G32: =IF(OR(E32="",F32=""),"",E32*F32) | H32: =IF('Dados tratados'!E34="","",'Dados tratados'!E34) -> 44495000 | I32: =IF(OR(G32="",H32="",H32=0),"",G32/H32) | K32: millones de pesos argentinos (ARS) | L32: Publicado somente para 2025; anos anteriores não preenchidos nesta observação de fonte | M32: https://www.argentina.gob.ar/noticias/en-el-ano-2025-el-sector-publico-nacional-registro-un-superavit-financiero-de-1453819 | N32: Resultado primário e financeiro do SPN base caixa; perímetro distinto das contas de governo geral IMF.
A33: Argentina | B33: 2018 | C33: Net lending/borrowing (% GDP) | D33: =IF('Dados brutos atualizados'!E33="","",'Dados brutos atualizados'!E33) -> -5.4411455 | E33: =IF(D33="","",D33*'Dados brutos atualizados'!G33) -> -5.4411455 | J33: =IF(D33="","",D33) -> -5.4411455 | K33: % of GDP | L33: WEO October 2026; latest history/vintage, subject to revision | M33: https://www.imf.org/external/datamapper/api/v2/GGXCNL_G01_GDP_PT/ARG?periods=2016,2017,2018,2019,2020,2021,2022,2023,2024,2025 | N33: Indicador GGXCNL_G01_GDP_PT; fonte IMF: Fiscal Monitor (October 2026); metadado do endpoint preservado.
A34: Argentina | B34: 2018 | C34: Population (IMF WEO) | D34: =IF('Dados brutos atualizados'!E34="","",'Dados brutos atualizados'!E34) -> 44.495 | E34: =IF(D34="","",D34*'Dados brutos atualizados'!G34) -> 44495000 | J34: =IF(D34="","",D34) -> 44.495 | K34: millions of persons | L34: WEO October 2026; latest history/vintage, subject to revision | M34: https://www.imf.org/external/datamapper/api/v2/LP/ARG?periods=2016,2017,2018,2019,2020,2021,2022,2023,2024,2025 | N34: Indicador LP; fonte IMF: World Economic Outlook (October 2026); metadado do endpoint preservado.
A35: Argentina | B35: 2018 | C35: RON transferências a províncias/CABA (monto publicado) | D35: =IF('Dados brutos atualizados'!E35="","",'Dados brutos atualizados'!E35) -> 1924313.8 | J35: =IF(D35="","",D35) -> 1924313.8 | K35: monto conforme CSV; unidade/escala não declarada | L35: Publicado em unidade reportada; não convertida | M35: https://www.argentina.gob.ar/sites/default/files/serie_ron_2003_2025.csv | N35: RON inclui coparticipação e outros regimes distribuídos; o arquivo não declara unidade monetária. Valores nominais não foram deflacionados nem usados em comparações de nível.
A36: Argentina | B36: 2018 | C36: Resultado financeiro SPN, base caja (2025) | D36: =IF('Dados brutos atualizados'!E36="","",'Dados brutos atualizados'!E36) | E36: =IF(D36="","",D36*'Dados brutos atualizados'!G36) | F36: =IF(E36="","",Deflatores!E16) | G36: =IF(OR(E36="",F36=""),"",E36*F36) | H36: =IF('Dados tratados'!E34="","",'Dados tratados'!E34) -> 44495000 | I36: =IF(OR(G36="",H36="",H36=0),"",G36/H36) | K36: millones de pesos argentinos (ARS) | L36: Publicado somente para 2025; anos anteriores não preenchidos nesta observação de fonte | M36: https://www.argentina.gob.ar/noticias/en-el-ano-2025-el-sector-publico-nacional-registro-un-superavit-financiero-de-1453819 | N36: Resultado primário e financeiro do SPN base caixa; perímetro distinto das contas de governo geral IMF.
A37: Argentina | B37: 2018 | C37: Resultado primário SPN, base caja (2025) | D37: =IF('Dados brutos atualizados'!E37="","",'Dados brutos atualizados'!E37) | E37: =IF(D37="","",D37*'Dados brutos atualizados'!G37) | F37: =IF(E37="","",Deflatores!E16) | G37: =IF(OR(E37="",F37=""),"",E37*F37) | H37: =IF('Dados tratados'!E34="","",'Dados tratados'!E34) -> 44495000 | I37: =IF(OR(G37="",H37="",H37=0),"",G37/H37) | K37: millones de pesos argentinos (ARS) | L37: Publicado somente para 2025; anos anteriores não preenchidos nesta observação de fonte | M37: https://www.argentina.gob.ar/noticias/en-el-ano-2025-el-sector-publico-nacional-registro-un-superavit-financiero-de-1453819 | N37: Resultado primário e financeiro do SPN base caixa; perímetro distinto das contas de governo geral IMF.
A38: Argentina | B38: 2019 | C38: Arrecadação federal total ARCA (TOTAL GENERAL) | D38: =IF('Dados brutos atualizados'!E38="","",'Dados brutos atualizados'!E38) -> 5.4735379e+09 | E38: =IF(D38="","",D38*'Dados brutos atualizados'!G38) -> 5.4735379e+12 | F38: =IF(E38="","",Deflatores!E17) -> 38.507296 | G38: =IF(OR(E38="",F38=""),"",E38*F38) -> 210771147006548 | H38: =IF('Dados tratados'!E46="","",'Dados tratados'!E46) -> 44939000 | I38: =IF(OR(G38="",H38="",H38=0),"",G38/H38) -> 4690161 | K38: mil pesos argentinos (ARS) | L38: Publicado | M38: https://contenidos.afip.gob.ar/institucional/estudios/archivos/serie2019.xls | N38: Total de tributos, recursos da seguridade social e aduanas; não é receita total de todo o governo.
A39: Argentina | B39: 2019 | C39: CPI inflation annual average (%) | D39: =IF('Dados brutos atualizados'!E39="","",'Dados brutos atualizados'!E39) -> 53.5 | E39: =IF(D39="","",D39*'Dados brutos atualizados'!G39) -> 53.5 | J39: =IF(D39="","",D39) -> 53.5 | K39: Annual percent change | L39: WEO October 2026; latest history/vintage, subject to revision | M39: https://www.imf.org/external/datamapper/api/v2/PCPIPCH/ARG?periods=2016,2017,2018,2019,2020,2021,2022,2023,2024,2025 | N39: Indicador PCPIPCH; fonte IMF: World Economic Outlook (October 2026); metadado do endpoint preservado.
A40: Argentina | B40: 2019 | C40: GDP nominal current (USD billion) | D40: =IF('Dados brutos atualizados'!E40="","",'Dados brutos atualizados'!E40) -> 446.762 | E40: =IF(D40="","",D40*'Dados brutos atualizados'!G40) -> 446.762 | J40: =IF(D40="","",D40) -> 446.762 | K40: Billions of U.S. dollars | L40: WEO October 2026; latest history/vintage, subject to revision | M40: https://www.imf.org/external/datamapper/api/v2/NGDPD/ARG?periods=2016,2017,2018,2019,2020,2021,2022,2023,2024,2025 | N40: Indicador NGDPD; fonte IMF: World Economic Outlook (October 2026); metadado do endpoint preservado.
A41: Argentina | B41: 2019 | C41: GDP real growth (%) | D41: =IF('Dados brutos atualizados'!E41="","",'Dados brutos atualizados'!E41) -> -2 | E41: =IF(D41="","",D41*'Dados brutos atualizados'!G41) -> -2 | J41: =IF(D41="","",D41) -> -2 | K41: Annual percent change | L41: WEO October 2026; latest history/vintage, subject to revision | M41: https://www.imf.org/external/datamapper/api/v2/NGDP_RPCH/ARG?periods=2016,2017,2018,2019,2020,2021,2022,2023,2024,2025 | N41: Indicador NGDP_RPCH; fonte IMF: World Economic Outlook (October 2026); metadado do endpoint preservado.
A42: Argentina | B42: 2019 | C42: Government expenditure (% GDP, FPP) | D42: =IF('Dados brutos atualizados'!E42="","",'Dados brutos atualizados'!E42) -> 38.129058 | E42: =IF(D42="","",D42*'Dados brutos atualizados'!G42) -> 38.129058 | J42: =IF(D42="","",D42) -> 38.129058 | K42: % of GDP | L42: FPP Dec 2025; 2025 not published in this series | M42: https://www.imf.org/external/datamapper/api/v2/exp/ARG?periods=2016,2017,2018,2019,2020,2021,2022,2023,2024,2025 | N42: Indicador exp; fonte IMF: Public Finances in Modern History Database (Dec 2025); metadado do endpoint preservado.
A43: Argentina | B43: 2019 | C43: Gross debt (% GDP) | D43: =IF('Dados brutos atualizados'!E43="","",'Dados brutos atualizados'!E43) -> 89.8 | E43: =IF(D43="","",D43*'Dados brutos atualizados'!G43) -> 89.8 | J43: =IF(D43="","",D43) -> 89.8 | K43: Percent of GDP | L43: WEO October 2026; latest history/vintage, subject to revision | M43: https://www.imf.org/external/datamapper/api/v2/GGXWDG_NGDP/ARG?periods=2016,2017,2018,2019,2020,2021,2022,2023,2024,2025 | N43: Indicador GGXWDG_NGDP; fonte IMF: World Economic Outlook (October 2026); metadado do endpoint preservado.
A44: Argentina | B44: 2019 | C44: Juros líquidos intra-SPN, base caja (2025) | D44: =IF('Dados brutos atualizados'!E44="","",'Dados brutos atualizados'!E44) | E44: =IF(D44="","",D44*'Dados brutos atualizados'!G44) | F44: =IF(E44="","",Deflatores!E17) | G44: =IF(OR(E44="",F44=""),"",E44*F44) | H44: =IF('Dados tratados'!E46="","",'Dados tratados'!E46) -> 44939000 | I44: =IF(OR(G44="",H44="",H44=0),"",G44/H44) | K44: millones de pesos argentinos (ARS) | L44: Publicado somente para 2025; anos anteriores não preenchidos nesta observação de fonte | M44: https://www.argentina.gob.ar/noticias/en-el-ano-2025-el-sector-publico-nacional-registro-un-superavit-financiero-de-1453819 | N44: Resultado primário e financeiro do SPN base caixa; perímetro distinto das contas de governo geral IMF.
A45: Argentina | B45: 2019 | C45: Net lending/borrowing (% GDP) | D45: =IF('Dados brutos atualizados'!E45="","",'Dados brutos atualizados'!E45) -> -4.4447575 | E45: =IF(D45="","",D45*'Dados brutos atualizados'!G45) -> -4.4447575 | J45: =IF(D45="","",D45) -> -4.4447575 | K45: % of GDP | L45: WEO October 2026; latest history/vintage, subject to revision | M45: https://www.imf.org/external/datamapper/api/v2/GGXCNL_G01_GDP_PT/ARG?periods=2016,2017,2018,2019,2020,2021,2022,2023,2024,2025 | N45: Indicador GGXCNL_G01_GDP_PT; fonte IMF: Fiscal Monitor (October 2026); metadado do endpoint preservado.
A46: Argentina | B46: 2019 | C46: Population (IMF WEO) | D46: =IF('Dados brutos atualizados'!E46="","",'Dados brutos atualizados'!E46) -> 44.939 | E46: =IF(D46="","",D46*'Dados brutos atualizados'!G46) -> 44939000 | J46: =IF(D46="","",D46) -> 44.939 | K46: millions of persons | L46: WEO October 2026; latest history/vintage, subject to revision | M46: https://www.imf.org/external/datamapper/api/v2/LP/ARG?periods=2016,2017,2018,2019,2020,2021,2022,2023,2024,2025 | N46: Indicador LP; fonte IMF: World Economic Outlook (October 2026); metadado do endpoint preservado.
A47: Argentina | B47: 2019 | C47: RON transferências a províncias/CABA (monto publicado) | D47: =IF('Dados brutos atualizados'!E47="","",'Dados brutos atualizados'!E47) -> 2754645.6 | J47: =IF(D47="","",D47) -> 2754645.6 | K47: monto conforme CSV; unidade/escala não declarada | L47: Publicado em unidade reportada; não convertida | M47: https://www.argentina.gob.ar/sites/default/files/serie_ron_2003_2025.csv | N47: RON inclui coparticipação e outros regimes distribuídos; o arquivo não declara unidade monetária. Valores nominais não foram deflacionados nem usados em comparações de nível.
A48: Argentina | B48: 2019 | C48: Resultado financeiro SPN, base caja (2025) | D48: =IF('Dados brutos atualizados'!E48="","",'Dados brutos atualizados'!E48) | E48: =IF(D48="","",D48*'Dados brutos atualizados'!G48) | F48: =IF(E48="","",Deflatores!E17) | G48: =IF(OR(E48="",F48=""),"",E48*F48) | H48: =IF('Dados tratados'!E46="","",'Dados tratados'!E46) -> 44939000 | I48: =IF(OR(G48="",H48="",H48=0),"",G48/H48) | K48: millones de pesos argentinos (ARS) | L48: Publicado somente para 2025; anos anteriores não preenchidos nesta observação de fonte | M48: https://www.argentina.gob.ar/noticias/en-el-ano-2025-el-sector-publico-nacional-registro-un-superavit-financiero-de-1453819 | N48: Resultado primário e financeiro do SPN base caixa; perímetro distinto das contas de governo geral IMF.
A49: Argentina | B49: 2019 | C49: Resultado primário SPN, base caja (2025) | D49: =IF('Dados brutos atualizados'!E49="","",'Dados brutos atualizados'!E49) | E49: =IF(D49="","",D49*'Dados brutos atualizados'!G49) | F49: =IF(E49="","",Deflatores!E17) | G49: =IF(OR(E49="",F49=""),"",E49*F49) | H49: =IF('Dados tratados'!E46="","",'Dados tratados'!E46) -> 44939000 | I49: =IF(OR(G49="",H49="",H49=0),"",G49/H49) | K49: millones de pesos argentinos (ARS) | L49: Publicado somente para 2025; anos anteriores não preenchidos nesta observação de fonte | M49: https://www.argentina.gob.ar/noticias/en-el-ano-2025-el-sector-publico-nacional-registro-un-superavit-financiero-de-1453819 | N49: Resultado primário e financeiro do SPN base caixa; perímetro distinto das contas de governo geral IMF.
A50: Argentina | B50: 2020 | C50: Arrecadação federal total ARCA (TOTAL GENERAL) | D50: =IF('Dados brutos atualizados'!E50="","",'Dados brutos atualizados'!E50) -> 7.2374102e+09 | E50: =IF(D50="","",D50*'Dados brutos atualizados'!G50) -> 7.2374102e+12 | F50: =IF(E50="","",Deflatores!E18) -> 27.117814 | G50: =IF(OR(E50="",F50=""),"",E50*F50) -> 1.9626275e+14 | H50: =IF('Dados tratados'!E58="","",'Dados tratados'!E58) -> 45377000 | I50: =IF(OR(G50="",H50="",H50=0),"",G50/H50) -> 4325159.2 | K50: mil pesos argentinos (ARS) | L50: Publicado | M50: https://contenidos.afip.gob.ar/institucional/estudios/archivos/serie2020.xls | N50: Total de tributos, recursos da seguridade social e aduanas; não é receita total de todo o governo.
A51: Argentina | B51: 2020 | C51: CPI inflation annual average (%) | D51: =IF('Dados brutos atualizados'!E51="","",'Dados brutos atualizados'!E51) -> 42 | E51: =IF(D51="","",D51*'Dados brutos atualizados'!G51) -> 42 | J51: =IF(D51="","",D51) -> 42 | K51: Annual percent change | L51: WEO October 2026; latest history/vintage, subject to revision | M51: https://www.imf.org/external/datamapper/api/v2/PCPIPCH/ARG?periods=2016,2017,2018,2019,2020,2021,2022,2023,2024,2025 | N51: Indicador PCPIPCH; fonte IMF: World Economic Outlook (October 2026); metadado do endpoint preservado.
A52: Argentina | B52: 2020 | C52: GDP nominal current (USD billion) | D52: =IF('Dados brutos atualizados'!E52="","",'Dados brutos atualizados'!E52) -> 385.218 | E52: =IF(D52="","",D52*'Dados brutos atualizados'!G52) -> 385.218 | J52: =IF(D52="","",D52) -> 385.218 | K52: Billions of U.S. dollars | L52: WEO October 2026; latest history/vintage, subject to revision | M52: https://www.imf.org/external/datamapper/api/v2/NGDPD/ARG?periods=2016,2017,2018,2019,2020,2021,2022,2023,2024,2025 | N52: Indicador NGDPD; fonte IMF: World Economic Outlook (October 2026); metadado do endpoint preservado.
A53: Argentina | B53: 2020 | C53: GDP real growth (%) | D53: =IF('Dados brutos atualizados'!E53="","",'Dados brutos atualizados'!E53) -> -9.9 | E53: =IF(D53="","",D53*'Dados brutos atualizados'!G53) -> -9.9 | J53: =IF(D53="","",D53) -> -9.9 | K53: Annual percent change | L53: WEO October 2026; latest history/vintage, subject to revision | M53: https://www.imf.org/external/datamapper/api/v2/NGDP_RPCH/ARG?periods=2016,2017,2018,2019,2020,2021,2022,2023,2024,2025 | N53: Indicador NGDP_RPCH; fonte IMF: World Economic Outlook (October 2026); metadado do endpoint preservado.
A54: Argentina | B54: 2020 | C54: Government expenditure (% GDP, FPP) | D54: =IF('Dados brutos atualizados'!E54="","",'Dados brutos atualizados'!E54) -> 42.47924 | E54: =IF(D54="","",D54*'Dados brutos atualizados'!G54) -> 42.47924 | J54: =IF(D54="","",D54) -> 42.47924 | K54: % of GDP | L54: FPP Dec 2025; 2025 not published in this series | M54: https://www.imf.org/external/datamapper/api/v2/exp/ARG?periods=2016,2017,2018,2019,2020,2021,2022,2023,2024,2025 | N54: Indicador exp; fonte IMF: Public Finances in Modern History Database (Dec 2025); metadado do endpoint preservado.
A55: Argentina | B55: 2020 | C55: Gross debt (% GDP) | D55: =IF('Dados brutos atualizados'!E55="","",'Dados brutos atualizados'!E55) -> 103.8 | E55: =IF(D55="","",D55*'Dados brutos atualizados'!G55) -> 103.8 | J55: =IF(D55="","",D55) -> 103.8 | K55: Percent of GDP | L55: WEO October 2026; latest history/vintage, subject to revision | M55: https://www.imf.org/external/datamapper/api/v2/GGXWDG_NGDP/ARG?periods=2016,2017,2018,2019,2020,2021,2022,2023,2024,2025 | N55: Indicador GGXWDG_NGDP; fonte IMF: World Economic Outlook (October 2026); metadado do endpoint preservado.
A56: Argentina | B56: 2020 | C56: Juros líquidos intra-SPN, base caja (2025) | D56: =IF('Dados brutos atualizados'!E56="","",'Dados brutos atualizados'!E56) | E56: =IF(D56="","",D56*'Dados brutos atualizados'!G56) | F56: =IF(E56="","",Deflatores!E18) | G56: =IF(OR(E56="",F56=""),"",E56*F56) | H56: =IF('Dados tratados'!E58="","",'Dados tratados'!E58) -> 45377000 | I56: =IF(OR(G56="",H56="",H56=0),"",G56/H56) | K56: millones de pesos argentinos (ARS) | L56: Publicado somente para 2025; anos anteriores não preenchidos nesta observação de fonte | M56: https://www.argentina.gob.ar/noticias/en-el-ano-2025-el-sector-publico-nacional-registro-un-superavit-financiero-de-1453819 | N56: Resultado primário e financeiro do SPN base caixa; perímetro distinto das contas de governo geral IMF.
A57: Argentina | B57: 2020 | C57: Net lending/borrowing (% GDP) | D57: =IF('Dados brutos atualizados'!E57="","",'Dados brutos atualizados'!E57) -> -8.6740712 | E57: =IF(D57="","",D57*'Dados brutos atualizados'!G57) -> -8.6740712 | J57: =IF(D57="","",D57) -> -8.6740712 | K57: % of GDP | L57: WEO October 2026; latest history/vintage, subject to revision | M57: https://www.imf.org/external/datamapper/api/v2/GGXCNL_G01_GDP_PT/ARG?periods=2016,2017,2018,2019,2020,2021,2022,2023,2024,2025 | N57: Indicador GGXCNL_G01_GDP_PT; fonte IMF: Fiscal Monitor (October 2026); metadado do endpoint preservado.
A58: Argentina | B58: 2020 | C58: Population (IMF WEO) | D58: =IF('Dados brutos atualizados'!E58="","",'Dados brutos atualizados'!E58) -> 45.377 | E58: =IF(D58="","",D58*'Dados brutos atualizados'!G58) -> 45377000 | J58: =IF(D58="","",D58) -> 45.377 | K58: millions of persons | L58: WEO October 2026; latest history/vintage, subject to revision | M58: https://www.imf.org/external/datamapper/api/v2/LP/ARG?periods=2016,2017,2018,2019,2020,2021,2022,2023,2024,2025 | N58: Indicador LP; fonte IMF: World Economic Outlook (October 2026); metadado do endpoint preservado.
A59: Argentina | B59: 2020 | C59: RON transferências a províncias/CABA (monto publicado) | D59: =IF('Dados brutos atualizados'!E59="","",'Dados brutos atualizados'!E59) -> 3742115.7 | J59: =IF(D59="","",D59) -> 3742115.7 | K59: monto conforme CSV; unidade/escala não declarada | L59: Publicado em unidade reportada; não convertida | M59: https://www.argentina.gob.ar/sites/default/files/serie_ron_2003_2025.csv | N59: RON inclui coparticipação e outros regimes distribuídos; o arquivo não declara unidade monetária. Valores nominais não foram deflacionados nem usados em comparações de nível.
A60: Argentina | B60: 2020 | C60: Resultado financeiro SPN, base caja (2025) | D60: =IF('Dados brutos atualizados'!E60="","",'Dados brutos atualizados'!E60) | E60: =IF(D60="","",D60*'Dados brutos atualizados'!G60) | F60: =IF(E60="","",Deflatores!E18) | G60: =IF(OR(E60="",F60=""),"",E60*F60) | H60: =IF('Dados tratados'!E58="","",'Dados tratados'!E58) -> 45377000 | I60: =IF(OR(G60="",H60="",H60=0),"",G60/H60) | K60: millones de pesos argentinos (ARS) | L60: Publicado somente para 2025; anos anteriores não preenchidos nesta observação de fonte | M60: https://www.argentina.gob.ar/noticias/en-el-ano-2025-el-sector-publico-nacional-registro-un-superavit-financiero-de-1453819 | N60: Resultado primário e financeiro do SPN base caixa; perímetro distinto das contas de governo geral IMF.
A61: Argentina | B61: 2020 | C61: Resultado primário SPN, base caja (2025) | D61: =IF('Dados brutos atualizados'!E61="","",'Dados brutos atualizados'!E61) | E61: =IF(D61="","",D61*'Dados brutos atualizados'!G61) | F61: =IF(E61="","",Deflatores!E18) | G61: =IF(OR(E61="",F61=""),"",E61*F61) | H61: =IF('Dados tratados'!E58="","",'Dados tratados'!E58) -> 45377000 | I61: =IF(OR(G61="",H61="",H61=0),"",G61/H61) | K61: millones de pesos argentinos (ARS) | L61: Publicado somente para 2025; anos anteriores não preenchidos nesta observação de fonte | M61: https://www.argentina.gob.ar/noticias/en-el-ano-2025-el-sector-publico-nacional-registro-un-superavit-financiero-de-1453819 | N61: Resultado primário e financeiro do SPN base caixa; perímetro distinto das contas de governo geral IMF.
A62: Argentina | B62: 2021 | C62: Arrecadação federal total ARCA (TOTAL GENERAL) | D62: =IF('Dados brutos atualizados'!E62="","",'Dados brutos atualizados'!E62) -> 11906731 | E62: =IF(D62="","",D62*'Dados brutos atualizados'!G62) -> 11906730771054 | F62: =IF(E62="","",Deflatores!E19) -> 18.27346 | G62: =IF(OR(E62="",F62=""),"",E62*F62) -> 2.1757717e+14 | H62: =IF('Dados tratados'!E70="","",'Dados tratados'!E70) -> 45809000 | I62: =IF(OR(G62="",H62="",H62=0),"",G62/H62) -> 4749659.8 | K62: millones de pesos argentinos (ARS) | L62: Publicado | M62: https://contenidos.afip.gob.ar/institucional/estudios/archivos/serie2021.xls | N62: Total de tributos, recursos da seguridade social e aduanas; não é receita total de todo o governo.
A63: Argentina | B63: 2021 | C63: CPI inflation annual average (%) | D63: =IF('Dados brutos atualizados'!E63="","",'Dados brutos atualizados'!E63) -> 48.4 | E63: =IF(D63="","",D63*'Dados brutos atualizados'!G63) -> 48.4 | J63: =IF(D63="","",D63) -> 48.4 | K63: Annual percent change | L63: WEO October 2026; latest history/vintage, subject to revision | M63: https://www.imf.org/external/datamapper/api/v2/PCPIPCH/ARG?periods=2016,2017,2018,2019,2020,2021,2022,2023,2024,2025 | N63: Indicador PCPIPCH; fonte IMF: World Economic Outlook (October 2026); metadado do endpoint preservado.
A64: Argentina | B64: 2021 | C64: GDP nominal current (USD billion) | D64: =IF('Dados brutos atualizados'!E64="","",'Dados brutos atualizados'!E64) -> 486.04 | E64: =IF(D64="","",D64*'Dados brutos atualizados'!G64) -> 486.04 | J64: =IF(D64="","",D64) -> 486.04 | K64: Billions of U.S. dollars | L64: WEO October 2026; latest history/vintage, subject to revision | M64: https://www.imf.org/external/datamapper/api/v2/NGDPD/ARG?periods=2016,2017,2018,2019,2020,2021,2022,2023,2024,2025 | N64: Indicador NGDPD; fonte IMF: World Economic Outlook (October 2026); metadado do endpoint preservado.
A65: Argentina | B65: 2021 | C65: GDP real growth (%) | D65: =IF('Dados brutos atualizados'!E65="","",'Dados brutos atualizados'!E65) -> 10.4 | E65: =IF(D65="","",D65*'Dados brutos atualizados'!G65) -> 10.4 | J65: =IF(D65="","",D65) -> 10.4 | K65: Annual percent change | L65: WEO October 2026; latest history/vintage, subject to revision | M65: https://www.imf.org/external/datamapper/api/v2/NGDP_RPCH/ARG?periods=2016,2017,2018,2019,2020,2021,2022,2023,2024,2025 | N65: Indicador NGDP_RPCH; fonte IMF: World Economic Outlook (October 2026); metadado do endpoint preservado.
A66: Argentina | B66: 2021 | C66: Government expenditure (% GDP, FPP) | D66: =IF('Dados brutos atualizados'!E66="","",'Dados brutos atualizados'!E66) -> 37.883365 | E66: =IF(D66="","",D66*'Dados brutos atualizados'!G66) -> 37.883365 | J66: =IF(D66="","",D66) -> 37.883365 | K66: % of GDP | L66: FPP Dec 2025; 2025 not published in this series | M66: https://www.imf.org/external/datamapper/api/v2/exp/ARG?periods=2016,2017,2018,2019,2020,2021,2022,2023,2024,2025 | N66: Indicador exp; fonte IMF: Public Finances in Modern History Database (Dec 2025); metadado do endpoint preservado.
A67: Argentina | B67: 2021 | C67: Gross debt (% GDP) | D67: =IF('Dados brutos atualizados'!E67="","",'Dados brutos atualizados'!E67) -> 81 | E67: =IF(D67="","",D67*'Dados brutos atualizados'!G67) -> 81 | J67: =IF(D67="","",D67) -> 81 | K67: Percent of GDP | L67: WEO October 2026; latest history/vintage, subject to revision | M67: https://www.imf.org/external/datamapper/api/v2/GGXWDG_NGDP/ARG?periods=2016,2017,2018,2019,2020,2021,2022,2023,2024,2025 | N67: Indicador GGXWDG_NGDP; fonte IMF: World Economic Outlook (October 2026); metadado do endpoint preservado.
A68: Argentina | B68: 2021 | C68: Juros líquidos intra-SPN, base caja (2025) | D68: =IF('Dados brutos atualizados'!E68="","",'Dados brutos atualizados'!E68) | E68: =IF(D68="","",D68*'Dados brutos atualizados'!G68) | F68: =IF(E68="","",Deflatores!E19) | G68: =IF(OR(E68="",F68=""),"",E68*F68) | H68: =IF('Dados tratados'!E70="","",'Dados tratados'!E70) -> 45809000 | I68: =IF(OR(G68="",H68="",H68=0),"",G68/H68) | K68: millones de pesos argentinos (ARS) | L68: Publicado somente para 2025; anos anteriores não preenchidos nesta observação de fonte | M68: https://www.argentina.gob.ar/noticias/en-el-ano-2025-el-sector-publico-nacional-registro-un-superavit-financiero-de-1453819 | N68: Resultado primário e financeiro do SPN base caixa; perímetro distinto das contas de governo geral IMF.
A69: Argentina | B69: 2021 | C69: Net lending/borrowing (% GDP) | D69: =IF('Dados brutos atualizados'!E69="","",'Dados brutos atualizados'!E69) -> -4.332952 | E69: =IF(D69="","",D69*'Dados brutos atualizados'!G69) -> -4.332952 | J69: =IF(D69="","",D69) -> -4.332952 | K69: % of GDP | L69: WEO October 2026; latest history/vintage, subject to revision | M69: https://www.imf.org/external/datamapper/api/v2/GGXCNL_G01_GDP_PT/ARG?periods=2016,2017,2018,2019,2020,2021,2022,2023,2024,2025 | N69: Indicador GGXCNL_G01_GDP_PT; fonte IMF: Fiscal Monitor (October 2026); metadado do endpoint preservado.
A70: Argentina | B70: 2021 | C70: Population (IMF WEO) | D70: =IF('Dados brutos atualizados'!E70="","",'Dados brutos atualizados'!E70) -> 45.809 | E70: =IF(D70="","",D70*'Dados brutos atualizados'!G70) -> 45809000 | J70: =IF(D70="","",D70) -> 45.809 | K70: millions of persons | L70: WEO October 2026; latest history/vintage, subject to revision | M70: https://www.imf.org/external/datamapper/api/v2/LP/ARG?periods=2016,2017,2018,2019,2020,2021,2022,2023,2024,2025 | N70: Indicador LP; fonte IMF: World Economic Outlook (October 2026); metadado do endpoint preservado.
A71: Argentina | B71: 2021 | C71: RON transferências a províncias/CABA (monto publicado) | D71: =IF('Dados brutos atualizados'!E71="","",'Dados brutos atualizados'!E71) -> 6116121.7 | J71: =IF(D71="","",D71) -> 6116121.7 | K71: monto conforme CSV; unidade/escala não declarada | L71: Publicado em unidade reportada; não convertida | M71: https://www.argentina.gob.ar/sites/default/files/serie_ron_2003_2025.csv | N71: RON inclui coparticipação e outros regimes distribuídos; o arquivo não declara unidade monetária. Valores nominais não foram deflacionados nem usados em comparações de nível.
A72: Argentina | B72: 2021 | C72: Resultado financeiro SPN, base caja (2025) | D72: =IF('Dados brutos atualizados'!E72="","",'Dados brutos atualizados'!E72) | E72: =IF(D72="","",D72*'Dados brutos atualizados'!G72) | F72: =IF(E72="","",Deflatores!E19) | G72: =IF(OR(E72="",F72=""),"",E72*F72) | H72: =IF('Dados tratados'!E70="","",'Dados tratados'!E70) -> 45809000 | I72: =IF(OR(G72="",H72="",H72=0),"",G72/H72) | K72: millones de pesos argentinos (ARS) | L72: Publicado somente para 2025; anos anteriores não preenchidos nesta observação de fonte | M72: https://www.argentina.gob.ar/noticias/en-el-ano-2025-el-sector-publico-nacional-registro-un-superavit-financiero-de-1453819 | N72: Resultado primário e financeiro do SPN base caixa; perímetro distinto das contas de governo geral IMF.
A73: Argentina | B73: 2021 | C73: Resultado primário SPN, base caja (2025) | D73: =IF('Dados brutos atualizados'!E73="","",'Dados brutos atualizados'!E73) | E73: =IF(D73="","",D73*'Dados brutos atualizados'!G73) | F73: =IF(E73="","",Deflatores!E19) | G73: =IF(OR(E73="",F73=""),"",E73*F73) | H73: =IF('Dados tratados'!E70="","",'Dados tratados'!E70) -> 45809000 | I73: =IF(OR(G73="",H73="",H73=0),"",G73/H73) | K73: millones de pesos argentinos (ARS) | L73: Publicado somente para 2025; anos anteriores não preenchidos nesta observação de fonte | M73: https://www.argentina.gob.ar/noticias/en-el-ano-2025-el-sector-publico-nacional-registro-un-superavit-financiero-de-1453819 | N73: Resultado primário e financeiro do SPN base caixa; perímetro distinto das contas de governo geral IMF.
A74: Argentina | B74: 2022 | C74: Arrecadação federal total ARCA (TOTAL GENERAL) | D74: =IF('Dados brutos atualizados'!E74="","",'Dados brutos atualizados'!E74) -> 21540626 | E74: =IF(D74="","",D74*'Dados brutos atualizados'!G74) -> 2.1540626e+13 | F74: =IF(E74="","",Deflatores!E20) -> 10.599455 | G74: =IF(OR(E74="",F74=""),"",E74*F74) -> 2.2831889e+14 | H74: =IF('Dados tratados'!E82="","",'Dados tratados'!E82) -> 46235000 | I74: =IF(OR(G74="",H74="",H74=0),"",G74/H74) -> 4938226.3 | K74: millones de pesos argentinos (ARS) | L74: Publicado | M74: https://contenidos.afip.gob.ar/institucional/estudios/archivos/serie2022.xls | N74: Total de tributos, recursos da seguridade social e aduanas; não é receita total de todo o governo.
A75: Argentina | B75: 2022 | C75: CPI inflation annual average (%) | D75: =IF('Dados brutos atualizados'!E75="","",'Dados brutos atualizados'!E75) -> 72.4 | E75: =IF(D75="","",D75*'Dados brutos atualizados'!G75) -> 72.4 | J75: =IF(D75="","",D75) -> 72.4 | K75: Annual percent change | L75: WEO October 2026; latest history/vintage, subject to revision | M75: https://www.imf.org/external/datamapper/api/v2/PCPIPCH/ARG?periods=2016,2017,2018,2019,2020,2021,2022,2023,2024,2025 | N75: Indicador PCPIPCH; fonte IMF: World Economic Outlook (October 2026); metadado do endpoint preservado.
A76: Argentina | B76: 2022 | C76: GDP nominal current (USD billion) | D76: =IF('Dados brutos atualizados'!E76="","",'Dados brutos atualizados'!E76) -> 633.52 | E76: =IF(D76="","",D76*'Dados brutos atualizados'!G76) -> 633.52 | J76: =IF(D76="","",D76) -> 633.52 | K76: Billions of U.S. dollars | L76: WEO October 2026; latest history/vintage, subject to revision | M76: https://www.imf.org/external/datamapper/api/v2/NGDPD/ARG?periods=2016,2017,2018,2019,2020,2021,2022,2023,2024,2025 | N76: Indicador NGDPD; fonte IMF: World Economic Outlook (October 2026); metadado do endpoint preservado.
A77: Argentina | B77: 2022 | C77: GDP real growth (%) | D77: =IF('Dados brutos atualizados'!E77="","",'Dados brutos atualizados'!E77) -> 6 | E77: =IF(D77="","",D77*'Dados brutos atualizados'!G77) -> 6 | J77: =IF(D77="","",D77) -> 6 | K77: Annual percent change | L77: WEO October 2026; latest history/vintage, subject to revision | M77: https://www.imf.org/external/datamapper/api/v2/NGDP_RPCH/ARG?periods=2016,2017,2018,2019,2020,2021,2022,2023,2024,2025 | N77: Indicador NGDP_RPCH; fonte IMF: World Economic Outlook (October 2026); metadado do endpoint preservado.
A78: Argentina | B78: 2022 | C78: Government expenditure (% GDP, FPP) | D78: =IF('Dados brutos atualizados'!E78="","",'Dados brutos atualizados'!E78) -> 37.643123 | E78: =IF(D78="","",D78*'Dados brutos atualizados'!G78) -> 37.643123 | J78: =IF(D78="","",D78) -> 37.643123 | K78: % of GDP | L78: FPP Dec 2025; 2025 not published in this series | M78: https://www.imf.org/external/datamapper/api/v2/exp/ARG?periods=2016,2017,2018,2019,2020,2021,2022,2023,2024,2025 | N78: Indicador exp; fonte IMF: Public Finances in Modern History Database (Dec 2025); metadado do endpoint preservado.
A79: Argentina | B79: 2022 | C79: Gross debt (% GDP) | D79: =IF('Dados brutos atualizados'!E79="","",'Dados brutos atualizados'!E79) -> 84.3 | E79: =IF(D79="","",D79*'Dados brutos atualizados'!G79) -> 84.3 | J79: =IF(D79="","",D79) -> 84.3 | K79: Percent of GDP | L79: WEO October 2026; latest history/vintage, subject to revision | M79: https://www.imf.org/external/datamapper/api/v2/GGXWDG_NGDP/ARG?periods=2016,2017,2018,2019,2020,2021,2022,2023,2024,2025 | N79: Indicador GGXWDG_NGDP; fonte IMF: World Economic Outlook (October 2026); metadado do endpoint preservado.
A80: Argentina | B80: 2022 | C80: Juros líquidos intra-SPN, base caja (2025) | D80: =IF('Dados brutos atualizados'!E80="","",'Dados brutos atualizados'!E80) | E80: =IF(D80="","",D80*'Dados brutos atualizados'!G80) | F80: =IF(E80="","",Deflatores!E20) | G80: =IF(OR(E80="",F80=""),"",E80*F80) | H80: =IF('Dados tratados'!E82="","",'Dados tratados'!E82) -> 46235000 | I80: =IF(OR(G80="",H80="",H80=0),"",G80/H80) | K80: millones de pesos argentinos (ARS) | L80: Publicado somente para 2025; anos anteriores não preenchidos nesta observação de fonte | M80: https://www.argentina.gob.ar/noticias/en-el-ano-2025-el-sector-publico-nacional-registro-un-superavit-financiero-de-1453819 | N80: Resultado primário e financeiro do SPN base caixa; perímetro distinto das contas de governo geral IMF.
A81: Argentina | B81: 2022 | C81: Net lending/borrowing (% GDP) | D81: =IF('Dados brutos atualizados'!E81="","",'Dados brutos atualizados'!E81) -> -3.8363851 | E81: =IF(D81="","",D81*'Dados brutos atualizados'!G81) -> -3.8363851 | J81: =IF(D81="","",D81) -> -3.8363851 | K81: % of GDP | L81: WEO October 2026; latest history/vintage, subject to revision | M81: https://www.imf.org/external/datamapper/api/v2/GGXCNL_G01_GDP_PT/ARG?periods=2016,2017,2018,2019,2020,2021,2022,2023,2024,2025 | N81: Indicador GGXCNL_G01_GDP_PT; fonte IMF: Fiscal Monitor (October 2026); metadado do endpoint preservado.
A82: Argentina | B82: 2022 | C82: Population (IMF WEO) | D82: =IF('Dados brutos atualizados'!E82="","",'Dados brutos atualizados'!E82) -> 46.235 | E82: =IF(D82="","",D82*'Dados brutos atualizados'!G82) -> 46235000 | J82: =IF(D82="","",D82) -> 46.235 | K82: millions of persons | L82: WEO October 2026; latest history/vintage, subject to revision | M82: https://www.imf.org/external/datamapper/api/v2/LP/ARG?periods=2016,2017,2018,2019,2020,2021,2022,2023,2024,2025 | N82: Indicador LP; fonte IMF: World Economic Outlook (October 2026); metadado do endpoint preservado.
A83: Argentina | B83: 2022 | C83: RON transferências a províncias/CABA (monto publicado) | D83: =IF('Dados brutos atualizados'!E83="","",'Dados brutos atualizados'!E83) -> 11276057 | J83: =IF(D83="","",D83) -> 11276057 | K83: monto conforme CSV; unidade/escala não declarada | L83: Publicado em unidade reportada; não convertida | M83: https://www.argentina.gob.ar/sites/default/files/serie_ron_2003_2025.csv | N83: RON inclui coparticipação e outros regimes distribuídos; o arquivo não declara unidade monetária. Valores nominais não foram deflacionados nem usados em comparações de nível.
A84: Argentina | B84: 2022 | C84: Resultado financeiro SPN, base caja (2025) | D84: =IF('Dados brutos atualizados'!E84="","",'Dados brutos atualizados'!E84) | E84: =IF(D84="","",D84*'Dados brutos atualizados'!G84) | F84: =IF(E84="","",Deflatores!E20) | G84: =IF(OR(E84="",F84=""),"",E84*F84) | H84: =IF('Dados tratados'!E82="","",'Dados tratados'!E82) -> 46235000 | I84: =IF(OR(G84="",H84="",H84=0),"",G84/H84) | K84: millones de pesos argentinos (ARS) | L84: Publicado somente para 2025; anos anteriores não preenchidos nesta observação de fonte | M84: https://www.argentina.gob.ar/noticias/en-el-ano-2025-el-sector-publico-nacional-registro-un-superavit-financiero-de-1453819 | N84: Resultado primário e financeiro do SPN base caixa; perímetro distinto das contas de governo geral IMF.
A85: Argentina | B85: 2022 | C85: Resultado primário SPN, base caja (2025) | D85: =IF('Dados brutos atualizados'!E85="","",'Dados brutos atualizados'!E85) | E85: =IF(D85="","",D85*'Dados brutos atualizados'!G85) | F85: =IF(E85="","",Deflatores!E20) | G85: =IF(OR(E85="",F85=""),"",E85*F85) | H85: =IF('Dados tratados'!E82="","",'Dados tratados'!E82) -> 46235000 | I85: =IF(OR(G85="",H85="",H85=0),"",G85/H85) | K85: millones de pesos argentinos (ARS) | L85: Publicado somente para 2025; anos anteriores não preenchidos nesta observação de fonte | M85: https://www.argentina.gob.ar/noticias/en-el-ano-2025-el-sector-publico-nacional-registro-un-superavit-financiero-de-1453819 | N85: Resultado primário e financeiro do SPN base caixa; perímetro distinto das contas de governo geral IMF.
A86: Argentina | B86: 2023 | C86: Arrecadação federal total ARCA (TOTAL GENERAL) | D86: =IF('Dados brutos atualizados'!E86="","",'Dados brutos atualizados'!E86) -> 46463191 | E86: =IF(D86="","",D86*'Dados brutos atualizados'!G86) -> 4.6463191e+13 | F86: =IF(E86="","",Deflatores!E21) -> 4.539381 | G86: =IF(OR(E86="",F86=""),"",E86*F86) -> 2.1091413e+14 | H86: =IF('Dados tratados'!E94="","",'Dados tratados'!E94) -> 46655000 | I86: =IF(OR(G86="",H86="",H86=0),"",G86/H86) -> 4520718.6 | K86: millones de pesos argentinos (ARS) | L86: Publicado | M86: https://contenidos.afip.gob.ar/institucional/estudios/archivos/serie2023.xls | N86: Total de tributos, recursos da seguridade social e aduanas; não é receita total de todo o governo.
A87: Argentina | B87: 2023 | C87: CPI inflation annual average (%) | D87: =IF('Dados brutos atualizados'!E87="","",'Dados brutos atualizados'!E87) -> 133.5 | E87: =IF(D87="","",D87*'Dados brutos atualizados'!G87) -> 133.5 | J87: =IF(D87="","",D87) -> 133.5 | K87: Annual percent change | L87: WEO October 2026; latest history/vintage, subject to revision | M87: https://www.imf.org/external/datamapper/api/v2/PCPIPCH/ARG?periods=2016,2017,2018,2019,2020,2021,2022,2023,2024,2025 | N87: Indicador PCPIPCH; fonte IMF: World Economic Outlook (October 2026); metadado do endpoint preservado.
A88: Argentina | B88: 2023 | C88: GDP nominal current (USD billion) | D88: =IF('Dados brutos atualizados'!E88="","",'Dados brutos atualizados'!E88) -> 654.081 | E88: =IF(D88="","",D88*'Dados brutos atualizados'!G88) -> 654.081 | J88: =IF(D88="","",D88) -> 654.081 | K88: Billions of U.S. dollars | L88: WEO October 2026; latest history/vintage, subject to revision | M88: https://www.imf.org/external/datamapper/api/v2/NGDPD/ARG?periods=2016,2017,2018,2019,2020,2021,2022,2023,2024,2025 | N88: Indicador NGDPD; fonte IMF: World Economic Outlook (October 2026); metadado do endpoint preservado.
A89: Argentina | B89: 2023 | C89: GDP real growth (%) | D89: =IF('Dados brutos atualizados'!E89="","",'Dados brutos atualizados'!E89) -> -1.9 | E89: =IF(D89="","",D89*'Dados brutos atualizados'!G89) -> -1.9 | J89: =IF(D89="","",D89) -> -1.9 | K89: Annual percent change | L89: WEO October 2026; latest history/vintage, subject to revision | M89: https://www.imf.org/external/datamapper/api/v2/NGDP_RPCH/ARG?periods=2016,2017,2018,2019,2020,2021,2022,2023,2024,2025 | N89: Indicador NGDP_RPCH; fonte IMF: World Economic Outlook (October 2026); metadado do endpoint preservado.
A90: Argentina | B90: 2023 | C90: Government expenditure (% GDP, FPP) | D90: =IF('Dados brutos atualizados'!E90="","",'Dados brutos atualizados'!E90) -> 37.637348 | E90: =IF(D90="","",D90*'Dados brutos atualizados'!G90) -> 37.637348 | J90: =IF(D90="","",D90) -> 37.637348 | K90: % of GDP | L90: FPP Dec 2025; 2025 not published in this series | M90: https://www.imf.org/external/datamapper/api/v2/exp/ARG?periods=2016,2017,2018,2019,2020,2021,2022,2023,2024,2025 | N90: Indicador exp; fonte IMF: Public Finances in Modern History Database (Dec 2025); metadado do endpoint preservado.
A91: Argentina | B91: 2023 | C91: Gross debt (% GDP) | D91: =IF('Dados brutos atualizados'!E91="","",'Dados brutos atualizados'!E91) -> 153.4 | E91: =IF(D91="","",D91*'Dados brutos atualizados'!G91) -> 153.4 | J91: =IF(D91="","",D91) -> 153.4 | K91: Percent of GDP | L91: WEO October 2026; latest history/vintage, subject to revision | M91: https://www.imf.org/external/datamapper/api/v2/GGXWDG_NGDP/ARG?periods=2016,2017,2018,2019,2020,2021,2022,2023,2024,2025 | N91: Indicador GGXWDG_NGDP; fonte IMF: World Economic Outlook (October 2026); metadado do endpoint preservado.
A92: Argentina | B92: 2023 | C92: Juros líquidos intra-SPN, base caja (2025) | D92: =IF('Dados brutos atualizados'!E92="","",'Dados brutos atualizados'!E92) | E92: =IF(D92="","",D92*'Dados brutos atualizados'!G92) | F92: =IF(E92="","",Deflatores!E21) | G92: =IF(OR(E92="",F92=""),"",E92*F92) | H92: =IF('Dados tratados'!E94="","",'Dados tratados'!E94) -> 46655000 | I92: =IF(OR(G92="",H92="",H92=0),"",G92/H92) | K92: millones de pesos argentinos (ARS) | L92: Publicado somente para 2025; anos anteriores não preenchidos nesta observação de fonte | M92: https://www.argentina.gob.ar/noticias/en-el-ano-2025-el-sector-publico-nacional-registro-un-superavit-financiero-de-1453819 | N92: Resultado primário e financeiro do SPN base caixa; perímetro distinto das contas de governo geral IMF.
A93: Argentina | B93: 2023 | C93: Net lending/borrowing (% GDP) | D93: =IF('Dados brutos atualizados'!E93="","",'Dados brutos atualizados'!E93) -> -5.2809834 | E93: =IF(D93="","",D93*'Dados brutos atualizados'!G93) -> -5.2809834 | J93: =IF(D93="","",D93) -> -5.2809834 | K93: % of GDP | L93: WEO October 2026; latest history/vintage, subject to revision | M93: https://www.imf.org/external/datamapper/api/v2/GGXCNL_G01_GDP_PT/ARG?periods=2016,2017,2018,2019,2020,2021,2022,2023,2024,2025 | N93: Indicador GGXCNL_G01_GDP_PT; fonte IMF: Fiscal Monitor (October 2026); metadado do endpoint preservado.
A94: Argentina | B94: 2023 | C94: Population (IMF WEO) | D94: =IF('Dados brutos atualizados'!E94="","",'Dados brutos atualizados'!E94) -> 46.655 | E94: =IF(D94="","",D94*'Dados brutos atualizados'!G94) -> 46655000 | J94: =IF(D94="","",D94) -> 46.655 | K94: millions of persons | L94: WEO October 2026; latest history/vintage, subject to revision | M94: https://www.imf.org/external/datamapper/api/v2/LP/ARG?periods=2016,2017,2018,2019,2020,2021,2022,2023,2024,2025 | N94: Indicador LP; fonte IMF: World Economic Outlook (October 2026); metadado do endpoint preservado.
A95: Argentina | B95: 2023 | C95: RON transferências a províncias/CABA (monto publicado) | D95: =IF('Dados brutos atualizados'!E95="","",'Dados brutos atualizados'!E95) -> 25030205 | J95: =IF(D95="","",D95) -> 25030205 | K95: monto conforme CSV; unidade/escala não declarada | L95: Publicado em unidade reportada; não convertida | M95: https://www.argentina.gob.ar/sites/default/files/serie_ron_2003_2025.csv | N95: RON inclui coparticipação e outros regimes distribuídos; o arquivo não declara unidade monetária. Valores nominais não foram deflacionados nem usados em comparações de nível.
A96: Argentina | B96: 2023 | C96: Resultado financeiro SPN, base caja (2025) | D96: =IF('Dados brutos atualizados'!E96="","",'Dados brutos atualizados'!E96) | E96: =IF(D96="","",D96*'Dados brutos atualizados'!G96) | F96: =IF(E96="","",Deflatores!E21) | G96: =IF(OR(E96="",F96=""),"",E96*F96) | H96: =IF('Dados tratados'!E94="","",'Dados tratados'!E94) -> 46655000 | I96: =IF(OR(G96="",H96="",H96=0),"",G96/H96) | K96: millones de pesos argentinos (ARS) | L96: Publicado somente para 2025; anos anteriores não preenchidos nesta observação de fonte | M96: https://www.argentina.gob.ar/noticias/en-el-ano-2025-el-sector-publico-nacional-registro-un-superavit-financiero-de-1453819 | N96: Resultado primário e financeiro do SPN base caixa; perímetro distinto das contas de governo geral IMF.
A97: Argentina | B97: 2023 | C97: Resultado primário SPN, base caja (2025) | D97: =IF('Dados brutos atualizados'!E97="","",'Dados brutos atualizados'!E97) | E97: =IF(D97="","",D97*'Dados brutos atualizados'!G97) | F97: =IF(E97="","",Deflatores!E21) | G97: =IF(OR(E97="",F97=""),"",E97*F97) | H97: =IF('Dados tratados'!E94="","",'Dados tratados'!E94) -> 46655000 | I97: =IF(OR(G97="",H97="",H97=0),"",G97/H97) | K97: millones de pesos argentinos (ARS) | L97: Publicado somente para 2025; anos anteriores não preenchidos nesta observação de fonte | M97: https://www.argentina.gob.ar/noticias/en-el-ano-2025-el-sector-publico-nacional-registro-un-superavit-financiero-de-1453819 | N97: Resultado primário e financeiro do SPN base caixa; perímetro distinto das contas de governo geral IMF.
A98: Argentina | B98: 2024 | C98: Arrecadação federal total ARCA (TOTAL GENERAL) | D98: =IF('Dados brutos atualizados'!E98="","",'Dados brutos atualizados'!E98) -> 1.4203145e+08 | E98: =IF(D98="","",D98*'Dados brutos atualizados'!G98) -> 142031453049165 | F98: =IF(E98="","",Deflatores!E22) -> 1.419 | G98: =IF(OR(E98="",F98=""),"",E98*F98) -> 2.0154263e+14 | H98: =IF('Dados tratados'!E106="","",'Dados tratados'!E106) -> 47068000 | I98: =IF(OR(G98="",H98="",H98=0),"",G98/H98) -> 4281945.9 | K98: millones de pesos argentinos (ARS) | L98: Publicado | M98: https://contenidos.afip.gob.ar/institucional/estudios/archivos/serie2024.xls | N98: Total de tributos, recursos da seguridade social e aduanas; não é receita total de todo o governo.
A99: Argentina | B99: 2024 | C99: CPI inflation annual average (%) | D99: =IF('Dados brutos atualizados'!E99="","",'Dados brutos atualizados'!E99) -> 219.9 | E99: =IF(D99="","",D99*'Dados brutos atualizados'!G99) -> 219.9 | J99: =IF(D99="","",D99) -> 219.9 | K99: Annual percent change | L99: WEO October 2026; latest history/vintage, subject to revision | M99: https://www.imf.org/external/datamapper/api/v2/PCPIPCH/ARG?periods=2016,2017,2018,2019,2020,2021,2022,2023,2024,2025 | N99: Indicador PCPIPCH; fonte IMF: World Economic Outlook (October 2026); metadado do endpoint preservado.
A100: Argentina | B100: 2024 | C100: GDP nominal current (USD billion) | D100: =IF('Dados brutos atualizados'!E100="","",'Dados brutos atualizados'!E100) -> 637.744 | E100: =IF(D100="","",D100*'Dados brutos atualizados'!G100) -> 637.744 | J100: =IF(D100="","",D100) -> 637.744 | K100: Billions of U.S. dollars | L100: WEO October 2026; latest history/vintage, subject to revision | M100: https://www.imf.org/external/datamapper/api/v2/NGDPD/ARG?periods=2016,2017,2018,2019,2020,2021,2022,2023,2024,2025 | N100: Indicador NGDPD; fonte IMF: World Economic Outlook (October 2026); metadado do endpoint preservado.
...

Sheet IDEB
A1: Município | B1: Ano | C1: Etapa | D1: Rede | E1: Indicador rendimento P | F1: Nota padronizada N | G1: IDEB=P×N | H1: IDEB arredondado (1 casa) | I1: Fonte | J1: Status
A2: Fortaleza/CE | B2: 2005 | C2: Anos finais | D2: Municipal | E2: =IF('Dados brutos atualizados'!E268="","",'Dados brutos atualizados'!E268) -> 0.611207 | F2: =IF('Dados brutos atualizados'!E266="","",'Dados brutos atualizados'!E266) -> 4.122 | G2: =IF(OR(E2="",F2=""),"",E2*F2) -> 2.5193953 | H2: =IF(G2="","",ROUND(G2,1)) -> 2.5 | I2: https://download.inep.gov.br/ideb/resultados/divulgacao_anos_finais_municipios_2025.zip | J2: P×N; rede municipal; bienal
A3: Fortaleza/CE | B3: 2005 | C3: Anos iniciais | D3: Municipal | E3: =IF('Dados brutos atualizados'!E269="","",'Dados brutos atualizados'!E269) -> 0.764176 | F3: =IF('Dados brutos atualizados'!E267="","",'Dados brutos atualizados'!E267) -> 4.219172 | G3: =IF(OR(E3="",F3=""),"",E3*F3) -> 3.22419 | H3: =IF(G3="","",ROUND(G3,1)) -> 3.2 | I3: https://download.inep.gov.br/ideb/resultados/divulgacao_anos_iniciais_municipios_2025.zip | J3: P×N; rede municipal; bienal
A4: Fortaleza/CE | B4: 2007 | C4: Anos finais | D4: Municipal | E4: =IF('Dados brutos atualizados'!E272="","",'Dados brutos atualizados'!E272) -> 0.637522 | F4: =IF('Dados brutos atualizados'!E270="","",'Dados brutos atualizados'!E270) -> 4.1775 | G4: =IF(OR(E4="",F4=""),"",E4*F4) -> 2.6632482 | H4: =IF(G4="","",ROUND(G4,1)) -> 2.7 | I4: https://download.inep.gov.br/ideb/resultados/divulgacao_anos_finais_municipios_2025.zip | J4: P×N; rede municipal; bienal
A5: Fortaleza/CE | B5: 2007 | C5: Anos iniciais | D5: Municipal | E5: =IF('Dados brutos atualizados'!E273="","",'Dados brutos atualizados'!E273) -> 0.783682 | F5: =IF('Dados brutos atualizados'!E271="","",'Dados brutos atualizados'!E271) -> 4.387938 | G5: =IF(OR(E5="",F5=""),"",E5*F5) -> 3.438748 | H5: =IF(G5="","",ROUND(G5,1)) -> 3.4 | I5: https://download.inep.gov.br/ideb/resultados/divulgacao_anos_iniciais_municipios_2025.zip | J5: P×N; rede municipal; bienal
A6: Fortaleza/CE | B6: 2009 | C6: Anos finais | D6: Municipal | E6: =IF('Dados brutos atualizados'!E276="","",'Dados brutos atualizados'!E276) -> 0.739476 | F6: =IF('Dados brutos atualizados'!E274="","",'Dados brutos atualizados'!E274) -> 4.4425 | G6: =IF(OR(E6="",F6=""),"",E6*F6) -> 3.2851221 | H6: =IF(G6="","",ROUND(G6,1)) -> 3.3 | I6: https://download.inep.gov.br/ideb/resultados/divulgacao_anos_finais_municipios_2025.zip | J6: P×N; rede municipal; bienal
A7: Fortaleza/CE | B7: 2009 | C7: Anos iniciais | D7: Municipal | E7: =IF('Dados brutos atualizados'!E277="","",'Dados brutos atualizados'!E277) -> 0.819127 | F7: =IF('Dados brutos atualizados'!E275="","",'Dados brutos atualizados'!E275) -> 4.715745 | G7: =IF(OR(E7="",F7=""),"",E7*F7) -> 3.8627941 | H7: =IF(G7="","",ROUND(G7,1)) -> 3.9 | I7: https://download.inep.gov.br/ideb/resultados/divulgacao_anos_iniciais_municipios_2025.zip | J7: P×N; rede municipal; bienal
A8: Fortaleza/CE | B8: 2011 | C8: Anos finais | D8: Municipal | E8: =IF('Dados brutos atualizados'!E282="","",'Dados brutos atualizados'!E282) -> 0.752205 | F8: =IF('Dados brutos atualizados'!E280="","",'Dados brutos atualizados'!E280) -> 4.6495 | G8: =IF(OR(E8="",F8=""),"",E8*F8) -> 3.4973771 | H8: =IF(G8="","",ROUND(G8,1)) -> 3.5 | I8: https://download.inep.gov.br/ideb/resultados/divulgacao_anos_finais_municipios_2025.zip | J8: P×N; rede municipal; bienal
A9: Fortaleza/CE | B9: 2011 | C9: Anos iniciais | D9: Municipal | E9: =IF('Dados brutos atualizados'!E283="","",'Dados brutos atualizados'!E283) -> 0.841441 | F9: =IF('Dados brutos atualizados'!E281="","",'Dados brutos atualizados'!E281) -> 5.014963 | G9: =IF(OR(E9="",F9=""),"",E9*F9) -> 4.2197955 | H9: =IF(G9="","",ROUND(G9,1)) -> 4.2 | I9: https://download.inep.gov.br/ideb/resultados/divulgacao_anos_iniciais_municipios_2025.zip | J9: P×N; rede municipal; bienal
A10: Fortaleza/CE | B10: 2013 | C10: Anos finais | D10: Municipal | E10: =IF('Dados brutos atualizados'!E290="","",'Dados brutos atualizados'!E290) -> 0.797956 | F10: =IF('Dados brutos atualizados'!E288="","",'Dados brutos atualizados'!E288) -> 4.768833 | G10: =IF(OR(E10="",F10=""),"",E10*F10) -> 3.8053189 | H10: =IF(G10="","",ROUND(G10,1)) -> 3.8 | I10: https://download.inep.gov.br/ideb/resultados/divulgacao_anos_finais_municipios_2025.zip | J10: P×N; rede municipal; bienal
A11: Fortaleza/CE | B11: 2013 | C11: Anos iniciais | D11: Municipal | E11: =IF('Dados brutos atualizados'!E291="","",'Dados brutos atualizados'!E291) -> 0.918793 | F11: =IF('Dados brutos atualizados'!E289="","",'Dados brutos atualizados'!E289) -> 5.04929 | G11: =IF(OR(E11="",F11=""),"",E11*F11) -> 4.6392523 | H11: =IF(G11="","",ROUND(G11,1)) -> 4.6 | I11: https://download.inep.gov.br/ideb/resultados/divulgacao_anos_iniciais_municipios_2025.zip | J11: P×N; rede municipal; bienal
A12: Fortaleza/CE | B12: 2015 | C12: Anos finais | D12: Municipal | E12: =IF('Dados brutos atualizados'!E298="","",'Dados brutos atualizados'!E298) -> 0.844363 | F12: =IF('Dados brutos atualizados'!E296="","",'Dados brutos atualizados'!E296) -> 5.174167 | G12: =IF(OR(E12="",F12=""),"",E12*F12) -> 4.3688752 | H12: =IF(G12="","",ROUND(G12,1)) -> 4.4 | I12: https://download.inep.gov.br/ideb/resultados/divulgacao_anos_finais_municipios_2025.zip | J12: P×N; rede municipal; bienal
A13: Fortaleza/CE | B13: 2015 | C13: Anos iniciais | D13: Municipal | E13: =IF('Dados brutos atualizados'!E299="","",'Dados brutos atualizados'!E299) -> 0.930844 | F13: =IF('Dados brutos atualizados'!E297="","",'Dados brutos atualizados'!E297) -> 5.774936 | G13: =IF(OR(E13="",F13=""),"",E13*F13) -> 5.3755645 | H13: =IF(G13="","",ROUND(G13,1)) -> 5.4 | I13: https://download.inep.gov.br/ideb/resultados/divulgacao_anos_iniciais_municipios_2025.zip | J13: P×N; rede municipal; bienal
A14: Fortaleza/CE | B14: 2017 | C14: Anos finais | D14: Municipal | E14: =IF('Dados brutos atualizados'!E326="","",'Dados brutos atualizados'!E326) -> 0.919907 | F14: =IF('Dados brutos atualizados'!E324="","",'Dados brutos atualizados'!E324) -> 5.336 | G14: =IF(OR(E14="",F14=""),"",E14*F14) -> 4.9086238 | H14: =IF(G14="","",ROUND(G14,1)) -> 4.9 | I14: https://download.inep.gov.br/ideb/resultados/divulgacao_anos_finais_municipios_2025.zip | J14: P×N; rede municipal; bienal
A15: Fortaleza/CE | B15: 2017 | C15: Anos iniciais | D15: Municipal | E15: =IF('Dados brutos atualizados'!E327="","",'Dados brutos atualizados'!E327) -> 0.965418 | F15: =IF('Dados brutos atualizados'!E325="","",'Dados brutos atualizados'!E325) -> 6.174518 | G15: =IF(OR(E15="",F15=""),"",E15*F15) -> 5.9609908 | H15: =IF(G15="","",ROUND(G15,1)) -> 6 | I15: https://download.inep.gov.br/ideb/resultados/divulgacao_anos_iniciais_municipios_2025.zip | J15: P×N; rede municipal; bienal
A16: Fortaleza/CE | B16: 2019 | C16: Anos finais | D16: Municipal | E16: =IF('Dados brutos atualizados'!E360="","",'Dados brutos atualizados'!E360) -> 0.970312 | F16: =IF('Dados brutos atualizados'!E358="","",'Dados brutos atualizados'!E358) -> 5.3655 | G16: =IF(OR(E16="",F16=""),"",E16*F16) -> 5.206209 | H16: =IF(G16="","",ROUND(G16,1)) -> 5.2 | I16: https://download.inep.gov.br/ideb/resultados/divulgacao_anos_finais_municipios_2025.zip | J16: P×N; rede municipal; bienal
A17: Fortaleza/CE | B17: 2019 | C17: Anos iniciais | D17: Municipal | E17: =IF('Dados brutos atualizados'!E361="","",'Dados brutos atualizados'!E361) -> 0.991736 | F17: =IF('Dados brutos atualizados'!E359="","",'Dados brutos atualizados'!E359) -> 6.237625 | G17: =IF(OR(E17="",F17=""),"",E17*F17) -> 6.1860773 | H17: =IF(G17="","",ROUND(G17,1)) -> 6.2 | I17: https://download.inep.gov.br/ideb/resultados/divulgacao_anos_iniciais_municipios_2025.zip | J17: P×N; rede municipal; bienal
A18: Fortaleza/CE | B18: 2021 | C18: Anos finais | D18: Municipal | E18: =IF('Dados brutos atualizados'!E394="","",'Dados brutos atualizados'!E394) -> 0.99825 | F18: =IF('Dados brutos atualizados'!E392="","",'Dados brutos atualizados'!E392) -> 5.209667 | G18: =IF(OR(E18="",F18=""),"",E18*F18) -> 5.2005501 | H18: =IF(G18="","",ROUND(G18,1)) -> 5.2 | I18: https://download.inep.gov.br/ideb/resultados/divulgacao_anos_finais_municipios_2025.zip | J18: P×N; rede municipal; bienal
A19: Fortaleza/CE | B19: 2021 | C19: Anos iniciais | D19: Municipal | E19: =IF('Dados brutos atualizados'!E395="","",'Dados brutos atualizados'!E395) -> 0.9992 | F19: =IF('Dados brutos atualizados'!E393="","",'Dados brutos atualizados'!E393) -> 5.849514 | G19: =IF(OR(E19="",F19=""),"",E19*F19) -> 5.8448344 | H19: =IF(G19="","",ROUND(G19,1)) -> 5.8 | I19: https://download.inep.gov.br/ideb/resultados/divulgacao_anos_iniciais_municipios_2025.zip | J19: P×N; rede municipal; bienal
A20: Fortaleza/CE | B20: 2023 | C20: Anos finais | D20: Municipal | E20: =IF('Dados brutos atualizados'!E428="","",'Dados brutos atualizados'!E428) -> 0.989485 | F20: =IF('Dados brutos atualizados'!E426="","",'Dados brutos atualizados'!E426) -> 5.205333 | G20: =IF(OR(E20="",F20=""),"",E20*F20) -> 5.1505989 | H20: =IF(G20="","",ROUND(G20,1)) -> 5.2 | I20: https://download.inep.gov.br/ideb/resultados/divulgacao_anos_finais_municipios_2025.zip | J20: P×N; rede municipal; bienal
A21: Fortaleza/CE | B21: 2023 | C21: Anos iniciais | D21: Municipal | E21: =IF('Dados brutos atualizados'!E429="","",'Dados brutos atualizados'!E429) -> 0.998599 | F21: =IF('Dados brutos atualizados'!E427="","",'Dados brutos atualizados'!E427) -> 5.945477 | G21: =IF(OR(E21="",F21=""),"",E21*F21) -> 5.9371474 | H21: =IF(G21="","",ROUND(G21,1)) -> 5.9 | I21: https://download.inep.gov.br/ideb/resultados/divulgacao_anos_iniciais_municipios_2025.zip | J21: P×N; rede municipal; bienal
A22: Fortaleza/CE | B22: 2025 | C22: Anos finais | D22: Municipal | E22: =IF('Dados brutos atualizados'!E460="","",'Dados brutos atualizados'!E460) -> 0.991991 | F22: =IF('Dados brutos atualizados'!E458="","",'Dados brutos atualizados'!E458) -> 5.210167 | G22: =IF(OR(E22="",F22=""),"",E22*F22) -> 5.1684388 | H22: =IF(G22="","",ROUND(G22,1)) -> 5.2 | I22: https://download.inep.gov.br/ideb/resultados/divulgacao_anos_finais_municipios_2025.zip | J22: P×N; rede municipal; bienal
A23: Fortaleza/CE | B23: 2025 | C23: Anos iniciais | D23: Municipal | E23: =IF('Dados brutos atualizados'!E461="","",'Dados brutos atualizados'!E461) -> 0.998399 | F23: =IF('Dados brutos atualizados'!E459="","",'Dados brutos atualizados'!E459) -> 6.110665 | G23: =IF(OR(E23="",F23=""),"",E23*F23) -> 6.1008818 | H23: =IF(G23="","",ROUND(G23,1)) -> 6.1 | I23: https://download.inep.gov.br/ideb/resultados/divulgacao_anos_iniciais_municipios_2025.zip | J23: P×N; rede municipal; bienal
A24: Juazeiro do Norte/CE | B24: 2005 | C24: Anos finais | D24: Municipal | E24: =IF('Dados brutos atualizados'!E471="","",'Dados brutos atualizados'!E471) -> 0.730373 | F24: =IF('Dados brutos atualizados'!E469="","",'Dados brutos atualizados'!E469) -> 4.220167 | G24: =IF(OR(E24="",F24=""),"",E24*F24) -> 3.082296 | H24: =IF(G24="","",ROUND(G24,1)) -> 3.1 | I24: https://download.inep.gov.br/ideb/resultados/divulgacao_anos_finais_municipios_2025.zip | J24: P×N; rede municipal; bienal
A25: Juazeiro do Norte/CE | B25: 2005 | C25: Anos iniciais | D25: Municipal | E25: =IF('Dados brutos atualizados'!E472="","",'Dados brutos atualizados'!E472) -> 0.783406 | F25: =IF('Dados brutos atualizados'!E470="","",'Dados brutos atualizados'!E470) -> 4.226437 | G25: =IF(OR(E25="",F25=""),"",E25*F25) -> 3.3110161 | H25: =IF(G25="","",ROUND(G25,1)) -> 3.3 | I25: https://download.inep.gov.br/ideb/resultados/divulgacao_anos_iniciais_municipios_2025.zip | J25: P×N; rede municipal; bienal
A26: Juazeiro do Norte/CE | B26: 2007 | C26: Anos finais | D26: Municipal | E26: =IF('Dados brutos atualizados'!E475="","",'Dados brutos atualizados'!E475) -> 0.792406 | F26: =IF('Dados brutos atualizados'!E473="","",'Dados brutos atualizados'!E473) -> 4.104667 | G26: =IF(OR(E26="",F26=""),"",E26*F26) -> 3.2525628 | H26: =IF(G26="","",ROUND(G26,1)) -> 3.3 | I26: https://download.inep.gov.br/ideb/resultados/divulgacao_anos_finais_municipios_2025.zip | J26: P×N; rede municipal; bienal
A27: Juazeiro do Norte/CE | B27: 2007 | C27: Anos iniciais | D27: Municipal | E27: =IF('Dados brutos atualizados'!E476="","",'Dados brutos atualizados'!E476) -> 0.852842 | F27: =IF('Dados brutos atualizados'!E474="","",'Dados brutos atualizados'!E474) -> 4.314544 | G27: =IF(OR(E27="",F27=""),"",E27*F27) -> 3.6796243 | H27: =IF(G27="","",ROUND(G27,1)) -> 3.7 | I27: https://download.inep.gov.br/ideb/resultados/divulgacao_anos_iniciais_municipios_2025.zip | J27: P×N; rede municipal; bienal
A28: Juazeiro do Norte/CE | B28: 2009 | C28: Anos finais | D28: Municipal | E28: =IF('Dados brutos atualizados'!E479="","",'Dados brutos atualizados'!E479) -> 0.795917 | F28: =IF('Dados brutos atualizados'!E477="","",'Dados brutos atualizados'!E477) -> 4.387667 | G28: =IF(OR(E28="",F28=""),"",E28*F28) -> 3.4922188 | H28: =IF(G28="","",ROUND(G28,1)) -> 3.5 | I28: https://download.inep.gov.br/ideb/resultados/divulgacao_anos_finais_municipios_2025.zip | J28: P×N; rede municipal; bienal
A29: Juazeiro do Norte/CE | B29: 2009 | C29: Anos iniciais | D29: Municipal | E29: =IF('Dados brutos atualizados'!E480="","",'Dados brutos atualizados'!E480) -> 0.872112 | F29: =IF('Dados brutos atualizados'!E478="","",'Dados brutos atualizados'!E478) -> 4.453699 | G29: =IF(OR(E29="",F29=""),"",E29*F29) -> 3.8841243 | H29: =IF(G29="","",ROUND(G29,1)) -> 3.9 | I29: https://download.inep.gov.br/ideb/resultados/divulgacao_anos_iniciais_municipios_2025.zip | J29: P×N; rede municipal; bienal
A30: Juazeiro do Norte/CE | B30: 2011 | C30: Anos finais | D30: Municipal | E30: =IF('Dados brutos atualizados'!E485="","",'Dados brutos atualizados'!E485) -> 0.809508 | F30: =IF('Dados brutos atualizados'!E483="","",'Dados brutos atualizados'!E483) -> 4.321167 | G30: =IF(OR(E30="",F30=""),"",E30*F30) -> 3.4980193 | H30: =IF(G30="","",ROUND(G30,1)) -> 3.5 | I30: https://download.inep.gov.br/ideb/resultados/divulgacao_anos_finais_municipios_2025.zip | J30: P×N; rede municipal; bienal
A31: Juazeiro do Norte/CE | B31: 2011 | C31: Anos iniciais | D31: Municipal | E31: =IF('Dados brutos atualizados'!E486="","",'Dados brutos atualizados'!E486) -> 0.885115 | F31: =IF('Dados brutos atualizados'!E484="","",'Dados brutos atualizados'!E484) -> 4.700899 | G31: =IF(OR(E31="",F31=""),"",E31*F31) -> 4.1608362 | H31: =IF(G31="","",ROUND(G31,1)) -> 4.2 | I31: https://download.inep.gov.br/ideb/resultados/divulgacao_anos_iniciais_municipios_2025.zip | J31: P×N; rede municipal; bienal
A32: Juazeiro do Norte/CE | B32: 2013 | C32: Anos finais | D32: Municipal | E32: =IF('Dados brutos atualizados'!E493="","",'Dados brutos atualizados'!E493) -> 0.809413 | F32: =IF('Dados brutos atualizados'!E491="","",'Dados brutos atualizados'!E491) -> 4.459667 | G32: =IF(OR(E32="",F32=""),"",E32*F32) -> 3.6097124 | H32: =IF(G32="","",ROUND(G32,1)) -> 3.6 | I32: https://download.inep.gov.br/ideb/resultados/divulgacao_anos_finais_municipios_2025.zip | J32: P×N; rede municipal; bienal
A33: Juazeiro do Norte/CE | B33: 2013 | C33: Anos iniciais | D33: Municipal | E33: =IF('Dados brutos atualizados'!E494="","",'Dados brutos atualizados'!E494) -> 0.902105 | F33: =IF('Dados brutos atualizados'!E492="","",'Dados brutos atualizados'!E492) -> 4.616616 | G33: =IF(OR(E33="",F33=""),"",E33*F33) -> 4.1646724 | H33: =IF(G33="","",ROUND(G33,1)) -> 4.2 | I33: https://download.inep.gov.br/ideb/resultados/divulgacao_anos_iniciais_municipios_2025.zip | J33: P×N; rede municipal; bienal
A34: Juazeiro do Norte/CE | B34: 2015 | C34: Anos finais | D34: Municipal | E34: =IF('Dados brutos atualizados'!E501="","",'Dados brutos atualizados'!E501) -> 0.835111 | F34: =IF('Dados brutos atualizados'!E499="","",'Dados brutos atualizados'!E499) -> 5.104333 | G34: =IF(OR(E34="",F34=""),"",E34*F34) -> 4.2626846 | H34: =IF(G34="","",ROUND(G34,1)) -> 4.3 | I34: https://download.inep.gov.br/ideb/resultados/divulgacao_anos_finais_municipios_2025.zip | J34: P×N; rede municipal; bienal
A35: Juazeiro do Norte/CE | B35: 2015 | C35: Anos iniciais | D35: Municipal | E35: =IF('Dados brutos atualizados'!E502="","",'Dados brutos atualizados'!E502) -> 0.922766 | F35: =IF('Dados brutos atualizados'!E500="","",'Dados brutos atualizados'!E500) -> 5.303207 | G35: =IF(OR(E35="",F35=""),"",E35*F35) -> 4.8936191 | H35: =IF(G35="","",ROUND(G35,1)) -> 4.9 | I35: https://download.inep.gov.br/ideb/resultados/divulgacao_anos_iniciais_municipios_2025.zip | J35: P×N; rede municipal; bienal
A36: Juazeiro do Norte/CE | B36: 2017 | C36: Anos finais | D36: Municipal | E36: =IF('Dados brutos atualizados'!E529="","",'Dados brutos atualizados'!E529) -> 0.858127 | F36: =IF('Dados brutos atualizados'!E527="","",'Dados brutos atualizados'!E527) -> 5.031 | G36: =IF(OR(E36="",F36=""),"",E36*F36) -> 4.3172369 | H36: =IF(G36="","",ROUND(G36,1)) -> 4.3 | I36: https://download.inep.gov.br/ideb/resultados/divulgacao_anos_finais_municipios_2025.zip | J36: P×N; rede municipal; bienal
A37: Juazeiro do Norte/CE | B37: 2017 | C37: Anos iniciais | D37: Municipal | E37: =IF('Dados brutos atualizados'!E530="","",'Dados brutos atualizados'!E530) -> 0.938313 | F37: =IF('Dados brutos atualizados'!E528="","",'Dados brutos atualizados'!E528) -> 5.360786 | G37: =IF(OR(E37="",F37=""),"",E37*F37) -> 5.0300952 | H37: =IF(G37="","",ROUND(G37,1)) -> 5 | I37: https://download.inep.gov.br/ideb/resultados/divulgacao_anos_iniciais_municipios_2025.zip | J37: P×N; rede municipal; bienal
A38: Juazeiro do Norte/CE | B38: 2019 | C38: Anos finais | D38: Municipal | E38: =IF('Dados brutos atualizados'!E563="","",'Dados brutos atualizados'!E563) -> 0.929007 | F38: =IF('Dados brutos atualizados'!E561="","",'Dados brutos atualizados'!E561) -> 5.209833 | G38: =IF(OR(E38="",F38=""),"",E38*F38) -> 4.8399713 | H38: =IF(G38="","",ROUND(G38,1)) -> 4.8 | I38: https://download.inep.gov.br/ideb/resultados/divulgacao_anos_finais_municipios_2025.zip | J38: P×N; rede municipal; bienal
A39: Juazeiro do Norte/CE | B39: 2019 | C39: Anos iniciais | D39: Municipal | E39: =IF('Dados brutos atualizados'!E564="","",'Dados brutos atualizados'!E564) -> 0.976735 | F39: =IF('Dados brutos atualizados'!E562="","",'Dados brutos atualizados'!E562) -> 5.627565 | G39: =IF(OR(E39="",F39=""),"",E39*F39) -> 5.4966397 | H39: =IF(G39="","",ROUND(G39,1)) -> 5.5 | I39: https://download.inep.gov.br/ideb/resultados/divulgacao_anos_iniciais_municipios_2025.zip | J39: P×N; rede municipal; bienal
A40: Juazeiro do Norte/CE | B40: 2021 | C40: Anos finais | D40: Municipal | E40: =IF('Dados brutos atualizados'!E597="","",'Dados brutos atualizados'!E597) -> 0.997999 | F40: =IF('Dados brutos atualizados'!E595="","",'Dados brutos atualizados'!E595) -> 4.978333 | G40: =IF(OR(E40="",F40=""),"",E40*F40) -> 4.9683714 | H40: =IF(G40="","",ROUND(G40,1)) -> 5 | I40: https://download.inep.gov.br/ideb/resultados/divulgacao_anos_finais_municipios_2025.zip | J40: P×N; rede municipal; bienal
A41: Juazeiro do Norte/CE | B41: 2021 | C41: Anos iniciais | D41: Municipal | E41: =IF('Dados brutos atualizados'!E598="","",'Dados brutos atualizados'!E598) -> 1 | F41: =IF('Dados brutos atualizados'!E596="","",'Dados brutos atualizados'!E596) -> 5.446628 | G41: =IF(OR(E41="",F41=""),"",E41*F41) -> 5.446628 | H41: =IF(G41="","",ROUND(G41,1)) -> 5.4 | I41: https://download.inep.gov.br/ideb/resultados/divulgacao_anos_iniciais_municipios_2025.zip | J41: P×N; rede municipal; bienal
A42: Juazeiro do Norte/CE | B42: 2023 | C42: Anos finais | D42: Municipal | E42: =IF('Dados brutos atualizados'!E631="","",'Dados brutos atualizados'!E631) -> 0.968208 | F42: =IF('Dados brutos atualizados'!E629="","",'Dados brutos atualizados'!E629) -> 5.050333 | G42: =IF(OR(E42="",F42=""),"",E42*F42) -> 4.8897728 | H42: =IF(G42="","",ROUND(G42,1)) -> 4.9 | I42: https://download.inep.gov.br/ideb/resultados/divulgacao_anos_finais_municipios_2025.zip | J42: P×N; rede municipal; bienal
A43: Juazeiro do Norte/CE | B43: 2023 | C43: Anos iniciais | D43: Municipal | E43: =IF('Dados brutos atualizados'!E632="","",'Dados brutos atualizados'!E632) -> 0.995993 | F43: =IF('Dados brutos atualizados'!E630="","",'Dados brutos atualizados'!E630) -> 5.538987 | G43: =IF(OR(E43="",F43=""),"",E43*F43) -> 5.5167923 | H43: =IF(G43="","",ROUND(G43,1)) -> 5.5 | I43: https://download.inep.gov.br/ideb/resultados/divulgacao_anos_iniciais_municipios_2025.zip | J43: P×N; rede municipal; bienal
A44: Juazeiro do Norte/CE | B44: 2025 | C44: Anos finais | D44: Municipal | E44: =IF('Dados brutos atualizados'!E663="","",'Dados brutos atualizados'!E663) -> 0.975208 | F44: =IF('Dados brutos atualizados'!E661="","",'Dados brutos atualizados'!E661) -> 5.0735 | G44: =IF(OR(E44="",F44=""),"",E44*F44) -> 4.9477178 | H44: =IF(G44="","",ROUND(G44,1)) -> 4.9 | I44: https://download.inep.gov.br/ideb/resultados/divulgacao_anos_finais_municipios_2025.zip | J44: P×N; rede municipal; bienal
A45: Juazeiro do Norte/CE | B45: 2025 | C45: Anos iniciais | D45: Municipal | E45: =IF('Dados brutos atualizados'!E664="","",'Dados brutos atualizados'!E664) -> 0.996794 | F45: =IF('Dados brutos atualizados'!E662="","",'Dados brutos atualizados'!E662) -> 5.622615 | G45: =IF(OR(E45="",F45=""),"",E45*F45) -> 5.6045889 | H45: =IF(G45="","",ROUND(G45,1)) -> 5.6 | I45: https://download.inep.gov.br/ideb/resultados/divulgacao_anos_iniciais_municipios_2025.zip | J45: P×N; rede municipal; bienal

Sheet Comparação legado
A1: Entidade | B1: Ano | C1: Variável/legado | D1: Valor original armazenado | E1: Unidade/escala original | F1: Valor atualizado | G1: Unidade atualizada | H1: Diferença calculada | I1: Comparabilidade e interpretação | J1: Fórmula original/nota
A2: Argentina | B2: 2014 | C2: Gasto Público (% PIB) | D2: 0.442 | E2: fração do PIB/decimal | G2: % | I2: perímetro/vintage IMF distinto; comparação apenas lado a lado | J2: Valores originais mantidos; sem sobrescrever.
A3: Argentina | B3: 2014 | C3: Déficit Fiscal (% PIB) | D3: -0.0425 | E3: fração do PIB/decimal | G3: % | I3: sinal de borrowing é negativo nas duas fontes; perímetro FMI vs série legada não documentada | J3: Valores originais mantidos; sem sobrescrever.
A4: Argentina | B4: 2014 | C4: Inflação (%) | D4: 0.385 | E4: fração anual | G4: % | I4: não calcular delta: ano-base média anual no FMI vs definição antiga não documentada/possivelmente dez-dez | J4: Valores originais mantidos; sem sobrescrever.
A5: Argentina | B5: 2014 | C5: PIB Real (var. %) | D5: -0.025 | E5: fração do PIB/decimal | G5: % | I5: mesma grandeza, mas WEO vintage 2026 revisa históricos | J5: Valores originais mantidos; sem sobrescrever.
A6: Argentina | B6: 2014 | C6: Dívida Públ. (% PIB) | D6: 0.44 | E6: fração do PIB/decimal | G6: % | I6: comparável como razão, mas perímetro e vintage podem diferir | J6: Valores originais mantidos; sem sobrescrever.
A7: Argentina | B7: 2015 | C7: Gasto Público (% PIB) | D7: 0.474 | E7: fração do PIB/decimal | G7: % | I7: perímetro/vintage IMF distinto; comparação apenas lado a lado | J7: Valores originais mantidos; sem sobrescrever.
A8: Argentina | B8: 2015 | C8: Déficit Fiscal (% PIB) | D8: -0.06 | E8: fração do PIB/decimal | G8: % | I8: sinal de borrowing é negativo nas duas fontes; perímetro FMI vs série legada não documentada | J8: Valores originais mantidos; sem sobrescrever.
A9: Argentina | B9: 2015 | C9: Inflação (%) | D9: 0.269 | E9: fração anual | G9: % | I9: não calcular delta: ano-base média anual no FMI vs definição antiga não documentada/possivelmente dez-dez | J9: Valores originais mantidos; sem sobrescrever.
A10: Argentina | B10: 2015 | C10: PIB Real (var. %) | D10: 0.027 | E10: fração do PIB/decimal | G10: % | I10: mesma grandeza, mas WEO vintage 2026 revisa históricos | J10: Valores originais mantidos; sem sobrescrever.
A11: Argentina | B11: 2015 | C11: Dívida Públ. (% PIB) | D11: 0.52 | E11: fração do PIB/decimal | G11: % | I11: comparável como razão, mas perímetro e vintage podem diferir | J11: Valores originais mantidos; sem sobrescrever.
A12: Argentina | B12: 2016 | C12: Gasto Público (% PIB) | D12: 0.424 | E12: fração do PIB/decimal | F12: 41.522021 | G12: % | I12: perímetro/vintage IMF distinto; comparação apenas lado a lado | J12: Valores originais mantidos; sem sobrescrever.
A13: Argentina | B13: 2016 | C13: Déficit Fiscal (% PIB) | D13: -0.0666 | E13: fração do PIB/decimal | F13: -6.654669 | G13: % | H13: 0.0053310174 | I13: sinal de borrowing é negativo nas duas fontes; perímetro FMI vs série legada não documentada | J13: Valores originais mantidos; sem sobrescrever.
A14: Argentina | B14: 2016 | C14: Inflação (%) | D14: 0.41 | E14: fração anual | G14: % | I14: não calcular delta: ano-base média anual no FMI vs definição antiga não documentada/possivelmente dez-dez | J14: Valores originais mantidos; sem sobrescrever.
A15: Argentina | B15: 2016 | C15: PIB Real (var. %) | D15: -0.021 | E15: fração do PIB/decimal | F15: -2.1 | G15: % | H15: 0 | I15: mesma grandeza, mas WEO vintage 2026 revisa históricos | J15: Valores originais mantidos; sem sobrescrever.
A16: Argentina | B16: 2016 | C16: Dívida Públ. (% PIB) | D16: 0.54 | E16: fração do PIB/decimal | F16: 53.1 | G16: % | H16: -0.9 | I16: comparável como razão, mas perímetro e vintage podem diferir | J16: Valores originais mantidos; sem sobrescrever.
A17: Argentina | B17: 2017 | C17: Gasto Público (% PIB) | D17: 0.418 | E17: fração do PIB/decimal | F17: 41.121454 | G17: % | I17: perímetro/vintage IMF distinto; comparação apenas lado a lado | J17: Valores originais mantidos; sem sobrescrever.
A18: Argentina | B18: 2017 | C18: Déficit Fiscal (% PIB) | D18: -0.0669 | E18: fração do PIB/decimal | F18: -6.6933411 | G18: % | H18: -0.0033411316 | I18: sinal de borrowing é negativo nas duas fontes; perímetro FMI vs série legada não documentada | J18: Valores originais mantidos; sem sobrescrever.
A19: Argentina | B19: 2017 | C19: Inflação (%) | D19: 0.257 | E19: fração anual | F19: 25.7 | G19: % | I19: não calcular delta: ano-base média anual no FMI vs definição antiga não documentada/possivelmente dez-dez | J19: Valores originais mantidos; sem sobrescrever.
A20: Argentina | B20: 2017 | C20: PIB Real (var. %) | D20: 0.029 | E20: fração do PIB/decimal | F20: 2.8 | G20: % | H20: -0.1 | I20: mesma grandeza, mas WEO vintage 2026 revisa históricos | J20: Valores originais mantidos; sem sobrescrever.
A21: Argentina | B21: 2017 | C21: Dívida Públ. (% PIB) | D21: 0.57 | E21: fração do PIB/decimal | F21: 57 | G21: % | H21: 7.1054274e-15 | I21: comparável como razão, mas perímetro e vintage podem diferir | J21: Valores originais mantidos; sem sobrescrever.
A22: Argentina | B22: 2018 | C22: Gasto Público (% PIB) | D22: 0.403 | E22: fração do PIB/decimal | F22: 38.949208 | G22: % | I22: perímetro/vintage IMF distinto; comparação apenas lado a lado | J22: Valores originais mantidos; sem sobrescrever.
A23: Argentina | B23: 2018 | C23: Déficit Fiscal (% PIB) | D23: -0.0544 | E23: fração do PIB/decimal | F23: -5.4411455 | G23: % | H23: -0.0011455069 | I23: sinal de borrowing é negativo nas duas fontes; perímetro FMI vs série legada não documentada | J23: Valores originais mantidos; sem sobrescrever.
A24: Argentina | B24: 2018 | C24: Inflação (%) | D24: 0.476 | E24: fração anual | F24: 34.3 | G24: % | I24: não calcular delta: ano-base média anual no FMI vs definição antiga não documentada/possivelmente dez-dez | J24: Valores originais mantidos; sem sobrescrever.
A25: Argentina | B25: 2018 | C25: PIB Real (var. %) | D25: -0.026 | E25: fração do PIB/decimal | F25: -2.6 | G25: % | H25: 0 | I25: mesma grandeza, mas WEO vintage 2026 revisa históricos | J25: Valores originais mantidos; sem sobrescrever.
A26: Argentina | B26: 2018 | C26: Dívida Públ. (% PIB) | D26: 0.86 | E26: fração do PIB/decimal | F26: 85.2 | G26: % | H26: -0.8 | I26: comparável como razão, mas perímetro e vintage podem diferir | J26: Valores originais mantidos; sem sobrescrever.
A27: Argentina | B27: 2019 | C27: Gasto Público (% PIB) | D27: 0.436 | E27: fração do PIB/decimal | F27: 38.129058 | G27: % | I27: perímetro/vintage IMF distinto; comparação apenas lado a lado | J27: Valores originais mantidos; sem sobrescrever.
A28: Argentina | B28: 2019 | C28: Déficit Fiscal (% PIB) | D28: -0.044 | E28: fração do PIB/decimal | F28: -4.4447575 | G28: % | H28: -0.044757513 | I28: sinal de borrowing é negativo nas duas fontes; perímetro FMI vs série legada não documentada | J28: Valores originais mantidos; sem sobrescrever.
A29: Argentina | B29: 2019 | C29: Inflação (%) | D29: 0.538 | E29: fração anual | F29: 53.5 | G29: % | I29: não calcular delta: ano-base média anual no FMI vs definição antiga não documentada/possivelmente dez-dez | J29: Valores originais mantidos; sem sobrescrever.
A30: Argentina | B30: 2019 | C30: PIB Real (var. %) | D30: -0.021 | E30: fração do PIB/decimal | F30: -2 | G30: % | H30: 0.1 | I30: mesma grandeza, mas WEO vintage 2026 revisa históricos | J30: Valores originais mantidos; sem sobrescrever.
A31: Argentina | B31: 2019 | C31: Dívida Públ. (% PIB) | D31: 0.9 | E31: fração do PIB/decimal | F31: 89.8 | G31: % | H31: -0.2 | I31: comparável como razão, mas perímetro e vintage podem diferir | J31: Valores originais mantidos; sem sobrescrever.
A32: Argentina | B32: 2020 | C32: Gasto Público (% PIB) | D32: 0.495 | E32: fração do PIB/decimal | F32: 42.47924 | G32: % | I32: perímetro/vintage IMF distinto; comparação apenas lado a lado | J32: Valores originais mantidos; sem sobrescrever.
A33: Argentina | B33: 2020 | C33: Déficit Fiscal (% PIB) | D33: -0.0863 | E33: fração do PIB/decimal | F33: -8.6740712 | G33: % | H33: -0.044071154 | I33: sinal de borrowing é negativo nas duas fontes; perímetro FMI vs série legada não documentada | J33: Valores originais mantidos; sem sobrescrever.
A34: Argentina | B34: 2020 | C34: Inflação (%) | D34: 0.361 | E34: fração anual | F34: 42 | G34: % | I34: não calcular delta: ano-base média anual no FMI vs definição antiga não documentada/possivelmente dez-dez | J34: Valores originais mantidos; sem sobrescrever.
A35: Argentina | B35: 2020 | C35: PIB Real (var. %) | D35: -0.099 | E35: fração do PIB/decimal | F35: -9.9 | G35: % | H35: 0 | I35: mesma grandeza, mas WEO vintage 2026 revisa históricos | J35: Valores originais mantidos; sem sobrescrever.
A36: Argentina | B36: 2020 | C36: Dívida Públ. (% PIB) | D36: 1.03 | E36: fração do PIB/decimal | F36: 103.8 | G36: % | H36: 0.8 | I36: comparável como razão, mas perímetro e vintage podem diferir | J36: Valores originais mantidos; sem sobrescrever.
A37: Argentina | B37: 2021 | C37: Gasto Público (% PIB) | D37: 0.467 | E37: fração do PIB/decimal | F37: 37.883365 | G37: % | I37: perímetro/vintage IMF distinto; comparação apenas lado a lado | J37: Valores originais mantidos; sem sobrescrever.
A38: Argentina | B38: 2021 | C38: Déficit Fiscal (% PIB) | D38: -0.0458 | E38: fração do PIB/decimal | F38: -4.332952 | G38: % | H38: 0.24704798 | I38: sinal de borrowing é negativo nas duas fontes; perímetro FMI vs série legada não documentada | J38: Valores originais mantidos; sem sobrescrever.
A39: Argentina | B39: 2021 | C39: Inflação (%) | D39: 0.509 | E39: fração anual | F39: 48.4 | G39: % | I39: não calcular delta: ano-base média anual no FMI vs definição antiga não documentada/possivelmente dez-dez | J39: Valores originais mantidos; sem sobrescrever.
A40: Argentina | B40: 2021 | C40: PIB Real (var. %) | D40: 0.104 | E40: fração do PIB/decimal | F40: 10.4 | G40: % | H40: 0 | I40: mesma grandeza, mas WEO vintage 2026 revisa históricos | J40: Valores originais mantidos; sem sobrescrever.
A41: Argentina | B41: 2021 | C41: Dívida Públ. (% PIB) | D41: 0.8 | E41: fração do PIB/decimal | F41: 81 | G41: % | H41: 1 | I41: comparável como razão, mas perímetro e vintage podem diferir | J41: Valores originais mantidos; sem sobrescrever.
A42: Argentina | B42: 2022 | C42: Gasto Público (% PIB) | D42: 0.45 | E42: fração do PIB/decimal | F42: 37.643123 | G42: % | I42: perímetro/vintage IMF distinto; comparação apenas lado a lado | J42: Valores originais mantidos; sem sobrescrever.
A43: Argentina | B43: 2022 | C43: Déficit Fiscal (% PIB) | D43: -0.0384 | E43: fração do PIB/decimal | F43: -3.8363851 | G43: % | H43: 0.0036148953 | I43: sinal de borrowing é negativo nas duas fontes; perímetro FMI vs série legada não documentada | J43: Valores originais mantidos; sem sobrescrever.
A44: Argentina | B44: 2022 | C44: Inflação (%) | D44: 0.948 | E44: fração anual | F44: 72.4 | G44: % | I44: não calcular delta: ano-base média anual no FMI vs definição antiga não documentada/possivelmente dez-dez | J44: Valores originais mantidos; sem sobrescrever.
A45: Argentina | B45: 2022 | C45: PIB Real (var. %) | D45: 0.05 | E45: fração do PIB/decimal | F45: 6 | G45: % | H45: 1 | I45: mesma grandeza, mas WEO vintage 2026 revisa históricos | J45: Valores originais mantidos; sem sobrescrever.
A46: Argentina | B46: 2022 | C46: Dívida Públ. (% PIB) | D46: 0.77 | E46: fração do PIB/decimal | F46: 84.3 | G46: % | H46: 7.3 | I46: comparável como razão, mas perímetro e vintage podem diferir | J46: Valores originais mantidos; sem sobrescrever.
A47: Argentina | B47: 2023 | C47: Gasto Público (% PIB) | D47: 0.419 | E47: fração do PIB/decimal | F47: 37.637348 | G47: % | I47: perímetro/vintage IMF distinto; comparação apenas lado a lado | J47: Valores originais mantidos; sem sobrescrever.
A48: Argentina | B48: 2023 | C48: Déficit Fiscal (% PIB) | D48: -0.029 | E48: fração do PIB/decimal | F48: -5.2809834 | G48: % | H48: -2.3809834 | I48: sinal de borrowing é negativo nas duas fontes; perímetro FMI vs série legada não documentada | J48: Valores originais mantidos; sem sobrescrever.
A49: Argentina | B49: 2023 | C49: Inflação (%) | D49: 2.114 | E49: fração anual | F49: 133.5 | G49: % | I49: não calcular delta: ano-base média anual no FMI vs definição antiga não documentada/possivelmente dez-dez | J49: Valores originais mantidos; sem sobrescrever.
A50: Argentina | B50: 2023 | C50: PIB Real (var. %) | D50: -0.016 | E50: fração do PIB/decimal | F50: -1.9 | G50: % | H50: -0.3 | I50: mesma grandeza, mas WEO vintage 2026 revisa históricos | J50: Valores originais mantidos; sem sobrescrever.
A51: Argentina | B51: 2023 | C51: Dívida Públ. (% PIB) | D51: 0.88 | E51: fração do PIB/decimal | F51: 153.4 | G51: % | H51: 65.4 | I51: comparável como razão, mas perímetro e vintage podem diferir | J51: Valores originais mantidos; sem sobrescrever.
A52: Fortaleza/CE | B52: 2014 | C52: Receita nominal legada vs receita bruta DCA | D52: 3.82 | E52: R$ bilhões | G52: R$ corrente | I52: Δ% indicativa somente: planilha antiga não informa fonte/perímetro; não reconciliar como erro contábil sem origem. | J52: Original mantida; célula real anterior usa fórmula que referencia bloco Argentina (ex.: =B3*C3).
A53: Fortaleza/CE | B53: 2014 | C53: Despesa pessoal legada vs DTP legal (RGF) | D53: 1.75 | E53: R$ bilhões | G53: R$ corrente | I53: Não equiparar: DTP RGF é métrica líquida da LRF; rubrica legada não tem fonte/metodologia. | J53: Fórmula original usa unidade nominal não explicitada em fonte.
A54: Fortaleza/CE | B54: 2014 | C54: RCL legada vs RCL legal RGF | D54: 3.8 | E54: R$ bilhões | G54: R$ corrente | I54: Não calcular delta: fonte antiga não especificada; para Juazeiro a RCL legada coincide com receita nominal em todos os anos. | J54: RCL RGF é conceito legal distinto da receita total.
A55: Fortaleza/CE | B55: 2014 | C55: Percentual de despesa pessoal legada vs RGF | D55: 46.1% | E55: % ou fração conforme célula original | G55: % reportado pelo RGF | I55: Diferença em pontos percentuais é indicativa; denominador e perímetro antigos não são verificáveis. | J55: Original mantida.
